Workbook
Name VisibleFunds: 'PPT Attributes'!#REF!

Sheet Output Dashboard (option 1)
A1: Portfolio
A3: Selected Funds | B3: Allocation | C3: Large | D3: Mid | E3: Small | S3: Stock Exposure | V3: Position Concentration | Z3: Equity Sector Exposure | AD3: Fund | AF3: Returns | AQ3: Year | AR3: Equity | AS3: =IF($AR$3='Drop Downs'!$I$18,'Drop Downs'!$D$2,'Drop Downs'!$E$2) -> Nifty 50
A4: {=_xlfn._xlws.FILTER('Selector Sheet '!$B$14:$B$43,'Selector Sheet '!$A$14:$A$43=TRUE,"No funds selected")} -> Renaissance Opportunities Fund PMS | B4: {=_xlfn.IFNA(VLOOKUP($A$4:$A$25,'Selector Sheet '!$B$14:$D$43,3,FALSE),"")} -> 0.2 | C4: {=VLOOKUP(_xlfn.ANCHORARRAY($A$4),source_data!$T$2:$W$24,2,FALSE)} -> 0.78 | D4: {=VLOOKUP(_xlfn.ANCHORARRAY($A$4),source_data!$T$2:$W$24,3,FALSE)} -> 0.14 | E4: {=VLOOKUP(_xlfn.ANCHORARRAY($A$4),source_data!$T$2:$W$24,4,FALSE)} -> 0.07 | S4: Name | T4: Percentage | V4: Top 3 | W4: =SUM($T$5:$T$7) -> #N/A | Z4: {=_xlfn._xlws.SORT(_xlfn.HSTACK(_xlfn.UNIQUE(source_data!$J$2:$J$192),_xlfn.BYROW(_xlfn.UNIQUE(source_data!$J$2:$J$192),_xlfn.LAMBDA(_xlpm.x,SUMIF(source_data!$J$2:$J$192,_xlpm.x,source_data!$L$2:$L$192)))),2,-1)} -> Financial | AA4: #N/A | AE4: Expense Ratio | AF4: 1 month | AG4: 3 months | AH4: 6 months | AI4: {=IFERROR(INDEX(performace_data!#REF!,MATCH(TRIM(_xlfn.ANCHORARRAY($AD$5)),performace_data!#REF!,0),MATCH(TRIM(#REF!),performace_data!#REF!,0)),"")} -> #VALUE! | AJ4: 1 Year | AK4: 2 Year | AL4: 3 Year | AM4: 5 Year | AN4: 10 Year | AQ4: CY 2025 | AR4: {=SUMPRODUCT(_xlfn._xlws.FILTER((VLOOKUP(_xlfn._xlws.FILTER('Drop Downs'!$J$26:$J$48,'Drop Downs'!$I$26:$I$48=$L$30,"Not Found"),$AD$33:$AN$48,2,FALSE)),NOT(ISNA((VLOOKUP(_xlfn._xlws.FILTER('Drop Downs'!$J$26:$J$48,'Drop Downs'!$I$26:$I$48=$L$30,"Not Found"),$AD$33:$AN$48,2,FALSE))))),_xlfn.IFNA(VLOOKUP(_xlfn._xlws.FILTER(_xlfn.ANCHORARRAY($AD$33),ISNUMBER(MATCH(_xlfn.ANCHORARRAY($AD$33),_xlfn._xlws.FILTER('Drop Downs'!$J$26:$J$48,'Drop Downs'!$I$26:$I$48=$L$30,"Not Found"),0))),'Selector Sheet '!$B$14:$D$43,2,FALSE),0))} -> 0.020314068 | AS4: {=IF($AS$3='Drop Downs'!$D$2,(VLOOKUP('Output Dashboard (option 1)'!$AQ$4:$AQ$11,'Drop Downs'!$C$3:$E$10,2,FALSE)),VLOOKUP('Output Dashboard (option 1)'!$AQ$4:$AQ$11,'Drop Downs'!$C$3:$E$10,3,FALSE))} -> -0.005306
A5: Nippon India Large Cap Fund(G) | B5: 0.2 | C5: 0.837409 | D5: 0.107269 | E5: 0.038736 | S5: {=_xlfn._xlws.SORT(_xlfn.TAKE(_xlfn._xlws.SORT(_xlfn.HSTACK(_xlfn.UNIQUE(source_data!$B$2:$B$567),_xlfn.BYROW(_xlfn.UNIQUE(source_data!$B$2:$B$567),_xlfn.LAMBDA(_xlpm.x,SUMIF(source_data!$B$2:$B$567,_xlpm.x,source_data!$D$2:$D$567)))),2,-1),20),2,-1)} -> HDFC Bank | T5: #N/A | V5: Top5 | W5: =SUM($T$5:$T$9) -> #N/A | Z5: Technology | AA5: #N/A | AD5: {=IF($A$4:$A$19>0,$A$4:$A$19,"")} -> Renaissance Opportunities Fund PMS | AE5: {=IFERROR(INDEX(performace_data!$B$3:$AN$293,MATCH(TRIM(_xlfn.ANCHORARRAY($AD$5)),performace_data!$B$3:$B$294,0),MATCH(TRIM(AE$4),performace_data!$B$4:$AM$4,0)),"")} -> 2.5 | AF5: {=IFERROR(INDEX(performace_data!$B$3:$AN$293,MATCH(TRIM(_xlfn.ANCHORARRAY($AD$5)),performace_data!$B$3:$B$294,0),MATCH(TRIM(AF$4),performace_data!$B$4:$AM$4,0)),"")} -> -0.0338 | AG5: {=IFERROR(INDEX(performace_data!$B$3:$AN$293,MATCH(TRIM(_xlfn.ANCHORARRAY($AD$5)),performace_data!$B$3:$B$294,0),MATCH(TRIM(AG$4),performace_data!$B$4:$AM$4,0)),"")} -> 0.01297865 | AH5: {=IFERROR(INDEX(performace_data!$B$3:$AN$293,MATCH(TRIM(_xlfn.ANCHORARRAY($AD$5)),performace_data!$B$3:$B$294,0),MATCH(TRIM(AH$4),performace_data!$B$4:$AM$4,0)),"")} -> 0.033656097 | AI5: {=IFERROR(INDEX(performace_data!$B$3:$AN$293,MATCH(TRIM(_xlfn.ANCHORARRAY($AD$5)),performace_data!$B$3:$B$294,0),MATCH(TRIM(AI$4),performace_data!$B$4:$AM$4,0)),"")} | AJ5: {=IFERROR(INDEX(performace_data!$B$3:$AN$293,MATCH(TRIM(_xlfn.ANCHORARRAY($AD$5)),performace_data!$B$3:$B$294,0),MATCH(TRIM(AJ$4),performace_data!$B$4:$AM$4,0)),"")} -> -0.027164836 | AK5: {=IFERROR(INDEX(performace_data!$B$3:$AN$293,MATCH(TRIM(_xlfn.ANCHORARRAY($AD$5)),performace_data!$B$3:$B$294,0),MATCH(TRIM(AK$4),performace_data!$B$4:$AM$4,0)),"")} | AL5: {=IFERROR(INDEX(performace_data!$B$3:$AN$293,MATCH(TRIM(_xlfn.ANCHORARRAY($AD$5)),performace_data!$B$3:$B$294,0),MATCH(TRIM(AL$4),performace_data!$B$4:$AM$4,0)),"")} -> 0.18337125 | ... AN5: {=IFERROR(INDEX(performace_data!$B$3:$AN$293,MATCH(TRIM(_xlfn.ANCHORARRAY($AD$5)),performace_data!$B$3:$B$294,0),MATCH(TRIM(AN$4),performace_data!$B$4:$AM$4,0)),"")} -> NA | AQ5: 2024 | AR5: {=SUMPRODUCT(_xlfn._xlws.FILTER((VLOOKUP(_xlfn._xlws.FILTER('Drop Downs'!$J$26:$J$48,'Drop Downs'!$I$26:$I$48=$AR$3,"Not Found"),$AD$33:$AN$48,3,FALSE)),NOT(ISNA((VLOOKUP(_xlfn._xlws.FILTER('Drop Downs'!$J$26:$J$48,'Drop Downs'!$I$26:$I$48=$AR$3,"Not Found"),$AD$33:$AN$48,3,FALSE))))),_xlfn.IFNA(VLOOKUP(_xlfn._xlws.FILTER(_xlfn.ANCHORARRAY($AD$33),ISNUMBER(MATCH(_xlfn.ANCHORARRAY($AD$33),_xlfn._xlws.FILTER('Drop Downs'!$J$26:$J$48,'Drop Downs'!$I$26:$I$48=$AR$3,"Not Found"),0))),'Selector Sheet '!$B$14:$D$43,2,FALSE),0))} -> 0.25862624 | AS5: 0.08804769
A6: SBI Large & Midcap Fund-Reg(G) | B6: 0.04 | C6: 0.433817 | D6: 0.360591 | E6: 0.149174 | S6: ICICI Bank | T6: #N/A | V6: Top 10 | W6: =SUM($T$5:$T$14) -> #N/A | Z6: Consumer Discretionary | AA6: #N/A | AD6: Nippon India Large Cap Fund(G) | AE6: 1.51 | AF6: -0.017875 | AG6: 0.047609 | AH6: 0.078495 | AJ6: 0.006832 | AL6: 0.204123 | AM6: 0.251486 | AN6: 0.137065 | AQ6: 2023 | AR6: {=SUMPRODUCT(_xlfn._xlws.FILTER((VLOOKUP(_xlfn._xlws.FILTER('Drop Downs'!$J$26:$J$41,'Drop Downs'!$I$26:$I$41=$AR$3,"Not Found"),$AD$33:$AN$48,4,FALSE)),NOT(ISNA((VLOOKUP(_xlfn._xlws.FILTER('Drop Downs'!$J$26:$J$41,'Drop Downs'!$I$26:$I$41=$AR$3,"Not Found"),$AD$33:$AN$48,4,FALSE))))),_xlfn.IFNA(VLOOKUP(_xlfn._xlws.FILTER(_xlfn.ANCHORARRAY($AD$33),ISNUMBER(MATCH(_xlfn.ANCHORARRAY($AD$33),_xlfn._xlws.FILTER('Drop Downs'!$J$26:$J$41,'Drop Downs'!$I$26:$I$41=$AR$3,"Not Found"),0))),'Selector Sheet '!$B$14:$D$43,2,FALSE),0))} -> 0.34784956 | AS6: 0.20027839
A7: Canara Rob Emerg Equities Fund-Reg(G) | B7: 0.04 | C7: 0.453308 | D7: 0.392334 | E7: 0.125245 | S7: Reliance Ind | T7: #N/A | V7: Top 20 | W7: =SUM($T$5:$T$24) -> #N/A | Z7: Energy & Utilities | AA7: #N/A | AD7: SBI Large & Midcap Fund-Reg(G) | AE7: 1.58 | AF7: -0.009427 | AG7: 0.065682 | AH7: 0.085126 | AJ7: 0.02127 | AL7: 0.192237 | AM7: 0.246868 | AN7: 0.141788 | AQ7: 2022 | AR7: {=SUMPRODUCT(_xlfn._xlws.FILTER((VLOOKUP(_xlfn._xlws.FILTER('Drop Downs'!$J$26:$J$41,'Drop Downs'!$I$26:$I$41=$AR$3,"Not Found"),$AD$33:$AN$48,5,FALSE)),NOT(ISNA((VLOOKUP(_xlfn._xlws.FILTER('Drop Downs'!$J$26:$J$41,'Drop Downs'!$I$26:$I$41=$AR$3,"Not Found"),$AD$33:$AN$48,5,FALSE))))),_xlfn.IFNA(VLOOKUP(_xlfn._xlws.FILTER(_xlfn.ANCHORARRAY($AD$33),ISNUMBER(MATCH(_xlfn.ANCHORARRAY($AD$33),_xlfn._xlws.FILTER('Drop Downs'!$J$26:$J$41,'Drop Downs'!$I$26:$I$41=$AR$3,"Not Found"),0))),'Selector Sheet '!$B$14:$D$43,2,FALSE),0))} -> 0.11269717 | AS7: 0.043289607
S8: Infosys | T8: #N/A | Z8: Consumer Staples | AA8: #N/A | AD8: Canara Rob Emerg Equities Fund-Reg(G) | AE8: 1.6 | AF8: -0.025189 | AG8: 0.055282 | AH8: 0.073313 | AJ8: 0.005758 | AL8: 0.173117 | AM8: 0.221895 | AN8: 0.147989 | AQ8: 2021 | AR8: {=SUMPRODUCT(_xlfn._xlws.FILTER((VLOOKUP(_xlfn._xlws.FILTER('Drop Downs'!$J$26:$J$41,'Drop Downs'!$I$26:$I$41=$AR$3,"Not Found"),$AD$33:$AN$48,7,FALSE)),NOT(ISNA((VLOOKUP(_xlfn._xlws.FILTER('Drop Downs'!$J$26:$J$41,'Drop Downs'!$I$26:$I$41=$AR$3,"Not Found"),$AD$33:$AN$48,7,FALSE))))),_xlfn.IFNA(VLOOKUP(_xlfn._xlws.FILTER(_xlfn.ANCHORARRAY($AD$33),ISNUMBER(MATCH(_xlfn.ANCHORARRAY($AD$33),_xlfn._xlws.FILTER('Drop Downs'!$J$26:$J$41,'Drop Downs'!$I$26:$I$41=$AR$3,"Not Found"),0))),'Selector Sheet '!$B$14:$D$43,2,FALSE),0))} -> 0.41996909 | AS8: 0.24119298
S9: Larsen & Toubro | T9: #N/A | Z9: Industrials | AA9: #N/A | AQ9: 2020 | AR9: {=SUMPRODUCT(_xlfn._xlws.FILTER((VLOOKUP(_xlfn._xlws.FILTER('Drop Downs'!$J$26:$J$41,'Drop Downs'!$I$26:$I$41=$AR$3,"Not Found"),$AD$33:$AN$48,9,FALSE)),NOT(ISNA((VLOOKUP(_xlfn._xlws.FILTER('Drop Downs'!$J$26:$J$41,'Drop Downs'!$I$26:$I$41=$AR$3,"Not Found"),$AD$33:$AN$48,9,FALSE))))),_xlfn.IFNA(VLOOKUP(_xlfn._xlws.FILTER(_xlfn.ANCHORARRAY($AD$33),ISNUMBER(MATCH(_xlfn.ANCHORARRAY($AD$33),_xlfn._xlws.FILTER('Drop Downs'!$J$26:$J$41,'Drop Downs'!$I$26:$I$41=$AR$3,"Not Found"),0))),'Selector Sheet '!$B$14:$D$43,2,FALSE),0))} -> 0.10952456 | AS9: 0.14901651
S10: Bharti Airtel | T10: #N/A | Z10: Materials | AA10: #N/A | AQ10: 2019 | AR10: {=SUMPRODUCT(_xlfn._xlws.FILTER((VLOOKUP(_xlfn._xlws.FILTER('Drop Downs'!$J$26:$J$41,'Drop Downs'!$I$26:$I$41=$AR$3,"Not Found"),$AD$33:$AN$48,10,FALSE)),NOT(ISNA((VLOOKUP(_xlfn._xlws.FILTER('Drop Downs'!$J$26:$J$41,'Drop Downs'!$I$26:$I$41=$AR$3,"Not Found"),$AD$33:$AN$48,10,FALSE))))),_xlfn.IFNA(VLOOKUP(_xlfn._xlws.FILTER(_xlfn.ANCHORARRAY($AD$33),ISNUMBER(MATCH(_xlfn.ANCHORARRAY($AD$33),_xlfn._xlws.FILTER('Drop Downs'!$J$26:$J$41,'Drop Downs'!$I$26:$I$41=$AR$3,"Not Found"),0))),'Selector Sheet '!$B$14:$D$43,2,FALSE),0))} -> 0.10641471 | AS10: 0.12022039
S11: Mahindra & Mahindra | T11: #N/A | Z11: Healthcare | AA11: #N/A | AQ11: 2018 | AR11: {=SUMPRODUCT(_xlfn._xlws.FILTER((VLOOKUP(_xlfn._xlws.FILTER('Drop Downs'!$J$26:$J$41,'Drop Downs'!$I$26:$I$41=$AR$3,"Not Found"),$AD$33:$AN$48,11,FALSE)),NOT(ISNA((VLOOKUP(_xlfn._xlws.FILTER('Drop Downs'!$J$26:$J$41,'Drop Downs'!$I$26:$I$41=$AR$3,"Not Found"),$AD$33:$AN$48,11,FALSE))))),_xlfn.IFNA(VLOOKUP(_xlfn._xlws.FILTER(_xlfn.ANCHORARRAY($AD$33),ISNUMBER(MATCH(_xlfn.ANCHORARRAY($AD$33),_xlfn._xlws.FILTER('Drop Downs'!$J$26:$J$41,'Drop Downs'!$I$26:$I$41=$AR$3,"Not Found"),0))),'Selector Sheet '!$B$14:$D$43,2,FALSE),0))} -> -0.054133307 | AS11: 0.031512625
S12: Axis Bank | T12: #N/A | Z12: Real Estate | AA12: #N/A
S13: ITC | T13: #N/A | Z13: Diversified | AA13: #N/A
S14: SBI | T14: #N/A | Z14: Cash (Unclassified) | AA14: 0
S15: Maruti Suzuki | T15: #N/A
S16: NTPC | T16: #N/A
S17: Tata Consultancy | T17: #N/A
S18: Sun Pharmaceutical | T18: #N/A
S19: Ultratech Cement | T19: #N/A
S20: Interglobe Aviation | T20: #N/A
S21: Hindustan Unilever | T21: #N/A | V21: Market Cap Exposure | W21: Portfolio | X21: Equity
S22: Bajaj Finance | T22: #N/A | V22: Large | W22: {=SUMPRODUCT(source_data!$U$2:$U$24,_xlfn.IFNA(VLOOKUP(source_data!$T$2:$T$24,'Selector Sheet '!$B$15:$D$43,3,FALSE),0))} -> 0.3589668 | X22: =($W$22/SUM($W$22:$W$24))*1 -> 0.76171458
S23: Kotak Bank | T23: #N/A | V23: Mid | W23: {=SUMPRODUCT(source_data!$V$2:$V$24,_xlfn.IFNA(VLOOKUP(source_data!$T$2:$T$24,'Selector Sheet '!$B$15:$D$43,3,FALSE),0))} -> 0.0795708 | X23: =($W$23/SUM($W$22:$W$24))*1 -> 0.16884636
S24: Tech Mahindra | T24: #N/A | V24: Small | W24: {=SUMPRODUCT(source_data!$W$2:$W$24,_xlfn.IFNA(VLOOKUP(source_data!$T$2:$T$24,'Selector Sheet '!$B$15:$D$43,3,FALSE),0))} -> 0.03272396 | X24: =($W$24/SUM($W$22:$W$24))*1 -> 0.069439061
A28: Returns Summary | K28: Backtested Retruns
A30: Fund | C30: Returns | K30: Year | L30: Equity | M30: =IF($L$30='Drop Downs'!$I$18,'Drop Downs'!$D$2,'Drop Downs'!$E$2) -> Nifty 50
B31: Expense Ratio | C31: 1 month | D31: 3 months | E31: 6 months | F31: 1 Year | G31: 3 Year | H31: 5 Year | I31: 10 Year | K31: CY 2025 | L31: {=_xlfn.LET(_xlpm.FilteredList,_xlfn._xlws.FILTER('Drop Downs'!$J$26:$J$48,'Drop Downs'!$I$26:$I$48=$L$30),_xlpm.DataValues,_xlfn.IFNA(VLOOKUP(_xlpm.FilteredList,$A$57:$I$78,2,FALSE),0),_xlpm.Weights,_xlfn.IFNA(VLOOKUP(_xlpm.FilteredList,'Selector Sheet '!$B$14:$D$43,2,FALSE),0),SUMPRODUCT(_xlpm.DataValues,_xlpm.Weights))} -> 0.020314068 | M31: {=IF($M$30='Drop Downs'!$D$2,(VLOOKUP('Output Dashboard (option 1)'!$AQ$4:$AQ$11,'Drop Downs'!$C$3:$E$10,2,FALSE)),VLOOKUP('Output Dashboard (option 1)'!$AQ$4:$AQ$11,'Drop Downs'!$C$3:$E$10,3,FALSE))} -> -0.005306 | AD31: Fund | AF31: Returns
A32: {=IF($A$4:$A$25>0,$A$4:$A$25,"")} -> Renaissance Opportunities Fund PMS | B32: {=IFERROR(INDEX(performace_data!$B$3:$AN$293,MATCH(TRIM(_xlfn.ANCHORARRAY($A$32)),performace_data!$B$3:$B$294,0),MATCH(TRIM(B$31),performace_data!$B$4:$AM$4,0)),"")} -> 2.5 | C32: {=IFERROR(INDEX(performace_data!$B$3:$AN$293,MATCH(TRIM(_xlfn.ANCHORARRAY($A$32)),performace_data!$B$3:$B$294,0),MATCH(TRIM(C$31),performace_data!$B$4:$AM$4,0)),"")} -> -0.0338 | D32: {=IFERROR(INDEX(performace_data!$B$3:$AN$293,MATCH(TRIM(_xlfn.ANCHORARRAY($A$32)),performace_data!$B$3:$B$294,0),MATCH(TRIM(D$31),performace_data!$B$4:$AM$4,0)),"")} -> 0.01297865 | E32: {=IFERROR(INDEX(performace_data!$B$3:$AN$293,MATCH(TRIM(_xlfn.ANCHORARRAY($A$32)),performace_data!$B$3:$B$294,0),MATCH(TRIM(E$31),performace_data!$B$4:$AM$4,0)),"")} -> 0.033656097 | F32: {=IFERROR(INDEX(performace_data!$B$3:$AN$293,MATCH(TRIM(_xlfn.ANCHORARRAY($A$32)),performace_data!$B$3:$B$294,0),MATCH(TRIM(F$31),performace_data!$B$4:$AM$4,0)),"")} -> -0.027164836 | G32: {=IFERROR(INDEX(performace_data!$B$3:$AN$293,MATCH(TRIM(_xlfn.ANCHORARRAY($A$32)),performace_data!$B$3:$B$294,0),MATCH(TRIM(G$31),performace_data!$B$4:$AM$4,0)),"")} -> 0.18337125 | H32: {=IFERROR(INDEX(performace_data!$B$3:$AN$293,MATCH(TRIM(_xlfn.ANCHORARRAY($A$32)),performace_data!$B$3:$B$294,0),MATCH(TRIM(H$31),performace_data!$B$4:$AM$4,0)),"")} -> 0.2591554 | I32: {=IFERROR(INDEX(performace_data!$B$3:$AN$293,MATCH(TRIM(_xlfn.ANCHORARRAY($A$32)),performace_data!$B$3:$B$294,0),MATCH(TRIM(I$31),performace_data!$B$4:$AM$4,0)),"")} -> NA | K32: 2024 | L32: {=_xlfn.LET(_xlpm.FilteredList,_xlfn._xlws.FILTER('Drop Downs'!$J$26:$J$48,'Drop Downs'!$I$26:$I$48=$L$30),_xlpm.DataValues,_xlfn.IFNA(VLOOKUP(_xlpm.FilteredList,$A$57:$I$78,3,FALSE),0),_xlpm.Weights,_xlfn.IFNA(VLOOKUP(_xlpm.FilteredList,'Selector Sheet '!$B$14:$D$43,2,FALSE),0),SUMPRODUCT(_xlpm.DataValues,_xlpm.Weights))} -> 0.25862624 | M32: 0.08804769 | AE32: CY 2025 | AF32: 2024 | AG32: 2023 | AH32: 2022 | AI32: 2021 | AJ32: 2021 | AK32: 2019 | AL32: 2020 | AM32: 2019 | AN32: 2018
A33: Nippon India Large Cap Fund(G) | B33: 1.51 | C33: -0.017875 | D33: 0.047609 | E33: 0.078495 | F33: 0.006832 | G33: 0.204123 | H33: 0.251486 | I33: 0.137065 | K33: 2023 | L33: {=_xlfn.LET(_xlpm.FilteredList,_xlfn._xlws.FILTER('Drop Downs'!$J$26:$J$48,'Drop Downs'!$I$26:$I$48=$L$30),_xlpm.DataValues,_xlfn.IFNA(VLOOKUP(_xlpm.FilteredList,$A$57:$I$78,4,FALSE),0),_xlpm.Weights,_xlfn.IFNA(VLOOKUP(_xlpm.FilteredList,'Selector Sheet '!$B$14:$D$43,2,FALSE),0),SUMPRODUCT(_xlpm.DataValues,_xlpm.Weights))} -> 0.34784956 | M33: 0.20027839 | AD33: {=IF($A$4:$A$19>0,$A$4:$A$19,"")} -> Renaissance Opportunities Fund PMS | AE33: {=_xlfn.IFNA(INDEX(performace_data!$B$4:$AN$294,MATCH(_xlfn.ANCHORARRAY($AD$33),performace_data!$B$4:$B$294,0),MATCH(AE$32,performace_data!$B$4:$AM$4,0)),"")} -> -0.015752664 | AF33: {=_xlfn.IFNA(INDEX(performace_data!$B$4:$AN$294,MATCH(_xlfn.ANCHORARRAY($AD$33),performace_data!$B$4:$B$294,0),MATCH(AF$32,performace_data!$B$4:$AM$4,0)),"")} -> 0.24613766 | AG33: {=_xlfn.IFNA(INDEX(performace_data!$B$4:$AN$294,MATCH(_xlfn.ANCHORARRAY($AD$33),performace_data!$B$4:$B$294,0),MATCH(AG$32,performace_data!$B$4:$AM$4,0)),"")} -> 0.27255978 | AH33: {=_xlfn.IFNA(INDEX(performace_data!$B$4:$AN$294,MATCH(_xlfn.ANCHORARRAY($AD$33),performace_data!$B$4:$B$294,0),MATCH(AH$32,performace_data!$B$4:$AM$4,0)),"")} -> 0.10087106 | AI33: {=_xlfn.IFNA(INDEX(performace_data!$B$4:$AN$294,MATCH(_xlfn.ANCHORARRAY($AD$33),performace_data!$B$4:$B$294,0),MATCH(AI$32,performace_data!$B$4:$AM$4,0)),"")} -> 0.36358998 | AJ33: {=_xlfn.IFNA(INDEX(performace_data!$B$4:$AN$294,MATCH(_xlfn.ANCHORARRAY($AD$33),performace_data!$B$4:$B$294,0),MATCH(AJ$32,performace_data!$B$4:$AM$4,0)),"")} -> 0.36358998 | AK33: {=_xlfn.IFNA(INDEX(performace_data!$B$4:$AN$294,MATCH(_xlfn.ANCHORARRAY($AD$33),performace_data!$B$4:$B$294,0),MATCH(AK$32,performace_data!$B$4:$AM$4,0)),"")} -> 0.10929996 | AL33: {=_xlfn.IFNA(INDEX(performace_data!$B$4:$AN$294,MATCH(_xlfn.ANCHORARRAY($AD$33),performace_data!$B$4:$B$294,0),MATCH(AL$32,performace_data!$B$4:$AM$4,0)),"")} -> 0.089364939 | ... AN33: {=_xlfn.IFNA(INDEX(performace_data!$B$4:$AN$294,MATCH(_xlfn.ANCHORARRAY($AD$33),performace_data!$B$4:$B$294,0),MATCH(AN$32,performace_data!$B$4:$AM$4,0)),"")} -> -0.077177992
A34: SBI Large & Midcap Fund-Reg(G) | B34: 1.58 | C34: -0.009427 | D34: 0.065682 | E34: 0.085126 | F34: 0.02127 | G34: 0.192237 | H34: 0.246868 | I34: 0.141788 | K34: 2022 | L34: {=_xlfn.LET(_xlpm.FilteredList,_xlfn._xlws.FILTER('Drop Downs'!$J$26:$J$48,'Drop Downs'!$I$26:$I$48=$L$30),_xlpm.DataValues,_xlfn.IFNA(VLOOKUP(_xlpm.FilteredList,$A$57:$I$78,5,FALSE),0),_xlpm.Weights,_xlfn.IFNA(VLOOKUP(_xlpm.FilteredList,'Selector Sheet '!$B$14:$D$43,2,FALSE),0),SUMPRODUCT(_xlpm.DataValues,_xlpm.Weights))} -> 0.11269717 | M34: 0.043289607 | AD34: Nippon India Large Cap Fund(G) | AE34: 0.045961 | AF34: 0.18239725 | AG34: 0.32147843 | AH34: 0.11327834 | AI34: 0.32367195 | AJ34: 0.32367195 | AK34: 0.072519095 | AL34: 0.049081268 | AM34: 0.072519095 | AN34: -0.0020039659
A35: Canara Rob Emerg Equities Fund-Reg(G) | B35: 1.6 | C35: -0.025189 | D35: 0.055282 | E35: 0.073313 | F35: 0.005758 | G35: 0.173117 | H35: 0.221895 | I35: 0.147989 | K35: 2021 | L35: {=_xlfn.LET(_xlpm.FilteredList,_xlfn._xlws.FILTER('Drop Downs'!$J$26:$J$48,'Drop Downs'!$I$26:$I$48=$L$30),_xlpm.DataValues,_xlfn.IFNA(VLOOKUP(_xlpm.FilteredList,$A$57:$I$78,6,FALSE),0),_xlpm.Weights,_xlfn.IFNA(VLOOKUP(_xlpm.FilteredList,'Selector Sheet '!$B$14:$D$43,2,FALSE),0),SUMPRODUCT(_xlpm.DataValues,_xlpm.Weights))} -> 0.41996909 | M35: 0.24119298 | AD35: SBI Large & Midcap Fund-Reg(G) | AE35: 0.049623 | AF35: 0.18042995 | AG35: 0.26792765 | AH35: 0.072700548 | AI35: 0.39345344 | AJ35: 0.39345344 | AK35: 0.068227156 | AL35: 0.15756187 | AM35: 0.068227156 | AN35: -0.052504277
K36: 2020 | L36: {=_xlfn.LET(_xlpm.FilteredList,_xlfn._xlws.FILTER('Drop Downs'!$J$26:$J$48,'Drop Downs'!$I$26:$I$48=$L$30),_xlpm.DataValues,_xlfn.IFNA(VLOOKUP(_xlpm.FilteredList,$A$57:$I$78,7,FALSE),0),_xlpm.Weights,_xlfn.IFNA(VLOOKUP(_xlpm.FilteredList,'Selector Sheet '!$B$14:$D$43,2,FALSE),0),SUMPRODUCT(_xlpm.DataValues,_xlpm.Weights))} -> 0.10952456 | M36: 0.14901651 | AD36: Canara Rob Emerg Equities Fund-Reg(G) | AE36: 0.002476 | AF36: 0.26315789 | AG36: 0.24037692 | AH36: -0.016475862 | AI36: 0.36992781 | AJ36: 0.36992781 | AK36: 0.086824666 | AL36: 0.24545267 | AM36: 0.086824666 | AN36: -0.092919002
K37: 2019 | L37: {=_xlfn.LET(_xlpm.FilteredList,_xlfn._xlws.FILTER('Drop Downs'!$J$26:$J$48,'Drop Downs'!$I$26:$I$48=$L$30),_xlpm.DataValues,_xlfn.IFNA(VLOOKUP(_xlpm.FilteredList,$A$57:$I$78,8,FALSE),0),_xlpm.Weights,_xlfn.IFNA(VLOOKUP(_xlpm.FilteredList,'Selector Sheet '!$B$14:$D$43,2,FALSE),0),SUMPRODUCT(_xlpm.DataValues,_xlpm.Weights))} -> 0.10641471 | M37: 0.12022039
K38: 2018 | L38: {=_xlfn.LET(_xlpm.FilteredList,_xlfn._xlws.FILTER('Drop Downs'!$J$26:$J$48,'Drop Downs'!$I$26:$I$48=$L$30),_xlpm.DataValues,_xlfn.IFNA(VLOOKUP(_xlpm.FilteredList,$A$57:$I$78,9,FALSE),0),_xlpm.Weights,_xlfn.IFNA(VLOOKUP(_xlpm.FilteredList,'Selector Sheet '!$B$14:$D$43,2,FALSE),0),SUMPRODUCT(_xlpm.DataValues,_xlpm.Weights))} -> -0.054133307 | M38: 0.031512625
A55: Fund | B55: Returns
B56: CY 2025 | C56: 2024 | D56: 2023 | E56: 2022 | F56: 2021 | G56: 2020 | H56: 2019 | I56: 2018
A57: {=IF($A$4:$A$25>0,$A$4:$A$25,"")} -> Renaissance Opportunities Fund PMS | B57: {=_xlfn.IFNA(INDEX(performace_data!$B$4:$AN$294,MATCH(_xlfn.ANCHORARRAY($A$57),performace_data!$B$4:$B$294,0),MATCH(B$56,performace_data!$B$4:$AM$4,0)),"")} -> -0.015752664 | C57: {=_xlfn.IFNA(INDEX(performace_data!$B$4:$AN$294,MATCH(_xlfn.ANCHORARRAY($A$57),performace_data!$B$4:$B$294,0),MATCH(C$56,performace_data!$B$4:$AM$4,0)),"")} -> 0.24613766 | D57: {=_xlfn.IFNA(INDEX(performace_data!$B$4:$AN$294,MATCH(_xlfn.ANCHORARRAY($A$57),performace_data!$B$4:$B$294,0),MATCH(D$56,performace_data!$B$4:$AM$4,0)),"")} -> 0.27255978 | E57: {=_xlfn.IFNA(INDEX(performace_data!$B$4:$AN$294,MATCH(_xlfn.ANCHORARRAY($A$57),performace_data!$B$4:$B$294,0),MATCH(E$56,performace_data!$B$4:$AM$4,0)),"")} -> 0.10087106 | F57: {=_xlfn.IFNA(INDEX(performace_data!$B$4:$AN$294,MATCH(_xlfn.ANCHORARRAY($A$57),performace_data!$B$4:$B$294,0),MATCH(F$56,performace_data!$B$4:$AM$4,0)),"")} -> 0.36358998 | G57: {=_xlfn.IFNA(INDEX(performace_data!$B$4:$AN$294,MATCH(_xlfn.ANCHORARRAY($A$57),performace_data!$B$4:$B$294,0),MATCH(G$56,performace_data!$B$4:$AM$4,0)),"")} -> 0.089364939 | H57: {=_xlfn.IFNA(INDEX(performace_data!$B$4:$AN$294,MATCH(_xlfn.ANCHORARRAY($A$57),performace_data!$B$4:$B$294,0),MATCH(H$56,performace_data!$B$4:$AM$4,0)),"")} -> 0.10929996 | I57: {=_xlfn.IFNA(INDEX(performace_data!$B$4:$AN$294,MATCH(_xlfn.ANCHORARRAY($A$57),performace_data!$B$4:$B$294,0),MATCH(I$56,performace_data!$B$4:$AM$4,0)),"")} -> -0.077177992
A58: Nippon India Large Cap Fund(G) | B58: 0.045961 | C58: 0.18239725 | D58: 0.32147843 | E58: 0.11327834 | F58: 0.32367195 | G58: 0.049081268 | H58: 0.072519095 | I58: -0.0020039659
A59: SBI Large & Midcap Fund-Reg(G) | B59: 0.049623 | C59: 0.18042995 | D59: 0.26792765 | E59: 0.072700548 | F59: 0.39345344 | G59: 0.15756187 | H59: 0.068227156 | I59: -0.052504277
A60: Canara Rob Emerg Equities Fund-Reg(G) | B60: 0.002476 | C60: 0.26315789 | D60: 0.24037692 | E60: -0.016475862 | F60: 0.36992781 | G60: 0.24545267 | H60: 0.086824666 | I60: -0.092919002
A84: Portfolio Details | L84: Market Cap Allocation
A87: Stock Exposure | D87: Position Concentration | H87: Equity Sector Exposure | L87: Market Cap Exposure | M87: Portfolio | N87: Equity
A88: Name | B88: Percentage | D88: Top 3 | E88: =SUM($B$89:$B$91) -> #N/A | H88: {=_xlfn._xlws.SORT(_xlfn.HSTACK(_xlfn.UNIQUE(source_data!$J$2:$J$192),_xlfn.BYROW(_xlfn.UNIQUE(source_data!$J$2:$J$192),_xlfn.LAMBDA(_xlpm.x,SUMIF(source_data!$J$2:$J$192,_xlpm.x,source_data!$L$2:$L$192)))),2,-1)} -> Financial | I88: #N/A | L88: Large | M88: {=SUMPRODUCT(source_data!$U$2:$U$24,_xlfn.IFNA(VLOOKUP(source_data!$T$2:$T$24,'Selector Sheet '!$B$15:$D$43,3,FALSE),0))} -> 0.3589668 | N88: =($W22/SUM($M$88:$M$90))*1 -> 0.76171458
A89: {=_xlfn._xlws.SORT(_xlfn.TAKE(_xlfn._xlws.SORT(_xlfn.HSTACK(_xlfn.UNIQUE(source_data!$B$2:$B$567),_xlfn.BYROW(_xlfn.UNIQUE(source_data!$B$2:$B$567),_xlfn.LAMBDA(_xlpm.x,SUMIF(source_data!$B$2:$B$567,_xlpm.x,source_data!$D$2:$D$567)))),2,-1),20),2,-1)} -> HDFC Bank | B89: #N/A | D89: Top5 | E89: =SUM($B$89:$B$93) -> #N/A | H89: Technology | I89: #N/A | L89: Mid | M89: {=SUMPRODUCT(source_data!$V$2:$V$24,_xlfn.IFNA(VLOOKUP(source_data!$T$2:$T$24,'Selector Sheet '!$B$15:$D$43,3,FALSE),0))} -> 0.0795708 | N89: =($W23/SUM($M$88:$M$90))*1 -> 0.16884636
A90: ICICI Bank | B90: #N/A | D90: Top 10 | E90: =SUM($B$89:$B$98) -> #N/A | H90: Consumer Discretionary | I90: #N/A | L90: Small | M90: {=SUMPRODUCT(source_data!$W$2:$W$24,_xlfn.IFNA(VLOOKUP(source_data!$T$2:$T$24,'Selector Sheet '!$B$15:$D$43,3,FALSE),0))} -> 0.03272396 | N90: =($W24/SUM($M$88:$M$90))*1 -> 0.069439061
A91: Reliance Ind | B91: #N/A | D91: Top 20 | E91: =SUM($B$89:$B$108) -> #N/A | H91: Energy & Utilities | I91: #N/A
A92: Infosys | B92: #N/A | H92: Consumer Staples | I92: #N/A
A93: Larsen & Toubro | B93: #N/A | H93: Industrials | I93: #N/A
A94: Bharti Airtel | B94: #N/A | H94: Materials | I94: #N/A
A95: Mahindra & Mahindra | B95: #N/A | H95: Healthcare | I95: #N/A
A96: Axis Bank | B96: #N/A | H96: Real Estate | I96: #N/A
A97: ITC | B97: #N/A | H97: Diversified | I97: #N/A
A98: SBI | B98: #N/A | H98: Cash (Unclassified) | I98: 0
A99: Maruti Suzuki | B99: #N/A
A100: NTPC | B100: #N/A
A101: Tata Consultancy | B101: #N/A
A102: Sun Pharmaceutical | B102: #N/A
A103: Ultratech Cement | B103: #N/A
A104: Interglobe Aviation | B104: #N/A
A105: Hindustan Unilever | B105: #N/A
A106: Bajaj Finance | B106: #N/A
A107: Kotak Bank | B107: #N/A
A108: Tech Mahindra | B108: #N/A

Sheet selector
A1: N1 | B1: N2 | C1: N3
A2: Equity
B3: Large Cap
C4: Renaissance Opportunities Fund PMS
C5: Nippon India Large Cap Fund(G)
C6: ICICI Pru Bluechip Fund(G)
C7: Kotak Bluechip Fund(G)
C8: Canara Rob Bluechip Equity Fund-Reg(G)
B9: Large -Mid Cap
C10: SBI Large & Midcap Fund-Reg(G)
C11: ICICI Pru Large & Mid Cap Fund(G)
C12: Canara Rob Emerg Equities Fund-Reg(G)
B13: Mid/Small cap
C14: AAA IOP PMS / AIF
C15: Nippon India Multi Cap Fund(G)
C16: SBI Contra Fund-Reg(G)
C17: Abakkus All Cap PMS
C18: Renaissance India Next Portfolio
C19: Parag Parikh Flexi Cap Fund-Reg(G)
C20: Bouyant Oppurtunites PMS
C21: UTI Flexi Cap Fund-Reg(G)
C22: ASK IEP PMS / AIF
A23: Hybrid
B24: sub category
C25: ICICI Pru Balanced Advantage Fund(G)
C26: Tata Balanced Adv Fund-Reg(G)
C27: Kotak Balanced Advantage Fund-Reg(G)
C28: Edelweiss Balanced Advantage Fund-Reg(G)
A29: Debt
B30: Debt Alternatives
C31: Altacura AI Absolute Return Fund LLP
C32: ASK Absolute Return Fund
C33: White Space Alpha Fund 2
C34: Inquant Debt Plus AIF
C35: AlphaMine Absolute Return Fund
C36: MasterTrust Irage PMS
B37: Private Credit
C38: Vivriti Short-term Debt AIF
C39: ICICI CCOF 3
C40: Vivriti Diversified Bond Fund II
C41: UTI SDOF 4
B42: Multi Asset Allocation
C43: Edelweiss Multi Asset Allocation Fund
A44: Alternative
B45: Private Equity/Venture Capital
C46: Oister X Tribe Ace Fund 2
B47: International
C48: Kristal.AI VCC- Client Associates Global FOF
C49: Aditya Birla SL Global Emerging Market Fund (IFSC)

Sheet Output Dashboard Debt
A1: Debt | H1: Debt | I1: 1 Month | J1: 3 Months | K1: 6 Months | L1: 1 Year | M1: 3 Years | N1: 5 Years | Q1: Debt | R1: 2025 | S1: 2024 | T1: 2023 | U1: 2022 | V1: 2021 | W1: 2020 | X1: 2019 | Y1: 2018
A2: Debt Alternatives | B2: {=_xlfn.IFNA(VLOOKUP($A$2:$A$17,'Selector Sheet '!$B$14:$D$59,3,FALSE),"")} | H2: {=IF($A$2:$A$19>0,$A$2:$A$19,"")} -> Debt Alternatives | I2: {=IFERROR(INDEX(performace_data!$AS$3:$BU$501,MATCH(TRIM(_xlfn.ANCHORARRAY($H2)),performace_data!$AS$3:$AS$501,0),MATCH(TRIM(I$1),performace_data!$AS$4:$BD$4,0)),"")} | J2: {=IFERROR(INDEX(performace_data!$AS$3:$BU$501,MATCH(TRIM(_xlfn.ANCHORARRAY($H2)),performace_data!$AS$3:$AS$501,0),MATCH(TRIM(J$1),performace_data!$AS$4:$BS$4,0)),"")} | K2: {=IFERROR(INDEX(performace_data!$AS$3:$BU$501,MATCH(TRIM(_xlfn.ANCHORARRAY($H2)),performace_data!$AS$3:$AS$501,0),MATCH(TRIM(K$1),performace_data!$AS$4:$BD$4,0)),"")} | L2: {=IFERROR(INDEX(performace_data!$AS$3:$BU$501,MATCH(TRIM(_xlfn.ANCHORARRAY($H2)),performace_data!$AS$3:$AS$501,0),MATCH(TRIM(L$1),performace_data!$AS$4:$BD$4,0)),"")} | M2: {=IFERROR(INDEX(performace_data!$AS$3:$BU$501,MATCH(TRIM(_xlfn.ANCHORARRAY($H2)),performace_data!$AS$3:$AS$501,0),MATCH(TRIM(M$1),performace_data!$AS$4:$BD$4,0)),"")} | N2: {=IFERROR(INDEX(performace_data!$AS$3:$BU$501,MATCH(TRIM(_xlfn.ANCHORARRAY($H2)),performace_data!$AS$3:$AS$501,0),MATCH(TRIM(N$1),performace_data!$AS$4:$BD$4,0)),"")} | Q2: {=IF($A$2:$A$19>0,$A$2:$A$19,"")} -> Debt Alternatives | R2: {=_xlfn.IFNA(VLOOKUP(_xlfn.ANCHORARRAY($Q$2),performace_data!$AS$5:$BU$15,14,FALSE),"")} | S2: {=_xlfn.IFNA(VLOOKUP(_xlfn.ANCHORARRAY($Q$2),performace_data!$AS$5:$BU$15,15,FALSE),"")} | T2: {=_xlfn.IFNA(VLOOKUP(_xlfn.ANCHORARRAY($Q$2),performace_data!$AS$5:$BU$15,16,FALSE),"")} | U2: {=_xlfn.IFNA(VLOOKUP(_xlfn.ANCHORARRAY($Q$2),performace_data!$AS$5:$BU$15,17,FALSE),"")} | V2: {=_xlfn.IFNA(VLOOKUP(_xlfn.ANCHORARRAY($Q$2),performace_data!$AS$5:$BU$15,18,FALSE),"")} | W2: {=_xlfn.IFNA(VLOOKUP(_xlfn.ANCHORARRAY($Q$2),performace_data!$AS$5:$BU$15,19,FALSE),"")} | X2: {=_xlfn.IFNA(VLOOKUP(_xlfn.ANCHORARRAY($Q$2),performace_data!$AS$5:$BU$15,20,FALSE),"")} | Y2: {=_xlfn.IFNA(VLOOKUP(_xlfn.ANCHORARRAY($Q$2),performace_data!$AS$5:$BU$15,21,FALSE),"")}
A3: {=_xlfn._xlws.FILTER('Selector Sheet '!$B$46:$B$51,'Selector Sheet '!$A$46:$A$51=TRUE,"No funds selected")} -> No funds selected | H3: No funds selected | Q3: No funds selected
A10: Private Credit | H10: Private Credit | Q10: Private Credit
A11: {=_xlfn._xlws.FILTER('Selector Sheet '!$B$53:$B$56,'Selector Sheet '!$A$53:$A$56=TRUE,"No funds selected")} -> No funds selected | H11: No funds selected | Q11: No funds selected
A15: Multi Asset Allocation | H15: Multi Asset Allocation | Q15: Multi Asset Allocation
A16: {=_xlfn._xlws.FILTER('Selector Sheet '!$B$58,'Selector Sheet '!$A$58=TRUE,"No funds selected")} -> No funds selected | H16: No funds selected | Q16: No funds selected
A18: Multi Asset Allocation | B18: {=_xlfn.IFNA(VLOOKUP($A$18:$A$19,'Selector Sheet '!$B$14:$D$59,3,FALSE),"")} | H18: Multi Asset Allocation | Q18: Multi Asset Allocation
A19: {=_xlfn._xlws.FILTER('Selector Sheet '!$B$58,'Selector Sheet '!$A$58=TRUE,"No funds selected")} -> No funds selected | H19: No funds selected | Q19: No funds selected

Sheet Macro1

Sheet PPT Attributes
Z1: C:\Users\mriganksahi\Desktop\Dynamic Client PPT.pptx
B9: Equity | C9: Portfolio | F9: Large | G9: Mid | H9: Small
A10: Large | B10: =C10/SUM($C$10:$C$12)*1 -> 0.76171458 | C10: =SUMPRODUCT(_xlfn.ANCHORARRAY('Output Dashboard '!$B$5),_xlfn.ANCHORARRAY('Output Dashboard '!$C$5)) -> 0.3589668 | E10: Equity | F10: {=TRANSPOSE($B$10:$B$12)} -> 0.76171458 | G10: 0.16884636 | H10: 0.069439061
A11: Mid | B11: =C11/SUM($C$10:$C$12)*1 -> 0.16884636 | C11: =SUMPRODUCT(_xlfn.ANCHORARRAY('Output Dashboard '!$B$5),_xlfn.ANCHORARRAY('Output Dashboard '!$D$5)) -> 0.0795708 | E11: Portfolio | F11: {=TRANSPOSE($C$10:$C$12)} -> 0.3589668 | G11: 0.0795708 | H11: 0.03272396
A12: Small | B12: =C12/SUM($C$10:$C$12)*1 -> 0.069439061 | C12: =SUMPRODUCT(_xlfn.ANCHORARRAY('Output Dashboard '!$B$5),_xlfn.ANCHORARRAY('Output Dashboard '!$E$5)) -> 0.03272396
A32: Equity Sector Exposure | D32: {='Output Dashboard '!$T$61:$V$64} -> Sector Concentration | E32: 0 | F32: 0
A33: Equity Sector Exposure | B33: Percentage | D33: Top 3 | E33: 0.5670699 | F33: 0
A34: {=_xlfn.IFNA(_xlfn._xlws.SORT(_xlfn.HSTACK(_xlfn.UNIQUE(sheet_2!$F$2:$F$778),_xlfn.BYROW(_xlfn.UNIQUE(sheet_2!$F$2:$F$778),_xlfn.LAMBDA(_xlpm.x,SUMIF(sheet_2!$F$2:$F$778,_xlpm.x,sheet_2!$G$2:$G$778)))),2,-1),"")} -> Financials | B34: 0.16172393 | D34: Top 5 | E34: 0.73640865 | F34: 0
A35: Consumer Discretionary | B35: 0.091712802 | D35: Top 11 | E35: 0.98159365 | F35: 0
A36: Industrials | B36: 0.060909196
A37: Consumer Staples | B37: 0.048566429
A38: Materials | B38: 0.037600355
A39: Information Technology | B39: 0.032326161
A40: Health Care | B40: 0.029019507
A41: Energy | B41: 0.028543337
A42: Utilities | B42: 0.02447258
A43: Communication Services | B43: 0.0027588868
A44: Real Estate | B44: 0.00087270431
A76: {='Output Dashboard '!$M$45:$N$66} -> Equity Stock Exposure | B76: 0 | D76: {='Output Dashboard '!$P$45:$R$49} -> Position Concentration | E76: 0 | F76: 0
A77: Name | B77: Percentage | D77: Top 3 | E77: 0.20788566 | F77: 0
A78: HDFC Bank Ltd | B78: 0.093156791 | D78: Top 5 | E78: 0.28581932 | F78: 0
A79: Reliance Industries Ltd | B79: 0.05812495 | D79: Top 10 | E79: 0.4147325 | F79: 0
A80: ICICI Bank Ltd | B80: 0.056603919 | D80: Top 20 | E80: 0.57178351 | F80: 0
A81: State Bank of India | B81: 0.046722491
A82: Infosys Ltd | B82: 0.031211167
A83: HDFC Asset Management Co Ltd | B83: 0.03010614
A84: Kotak Mahindra Bank Ltd | B84: 0.027928841
A85: Tech Mahindra Ltd | B85: 0.027109853
A86: Larsen & Toubro Ltd | B86: 0.024691642
A87: Axis Bank Ltd | B87: 0.019076709
A88: Tata Steel Ltd | B88: 0.01833052
A89: Info Edge India Ltd | B89: 0.017954939
A90: NTPC Ltd | B90: 0.017744435
A91: United Spirits Ltd | B91: 0.017031673
A92: Jubilant Foodworks Ltd | B92: 0.015725468
... A97: ITC Ltd | B97: 0.01373089
A100: {='Output Dashboard '!$A$44:$D$52} -> Year | B100: Equity | C100: Nifty 50 | D100: S&P BSE 500
A101: CY 2025 | B101: 0.01692839 | C101: 0.047518 | D101: 0.022527
A102: 2024 | B102: 0.21552187 | C102: 0.08804769 | D102: 0.1454658
A103: 2023 | B103: 0.28987463 | C103: 0.20027839 | D103: 0.24849852
A104: 2022 | B104: 0.093914308 | C104: 0.043289607 | D104: 0.033378691
A105: 2021 | B105: 0.34997424 | C105: 0.24119298 | D105: 0.30114043
A106: 2020 | B106: 0.091270464 | C106: 0.14901651 | D106: 0.16803383
A107: 2019 | B107: 0.088678925 | C107: 0.12022039 | D107: 0.077511676
A108: 2018 | B108: -0.045111089 | C108: 0.031512625 | D108: -0.030817058
A111: {='Output Dashboard '!$A$71:$D$78} -> Year | B111: Equity | C111: Nifty 50 | D111: S&P BSE 500
A112: 1 M | B112: -0.024415917 | C112: -0.029341 | D112: -0.028654
A113: 3 M | B113: 0.035325188 | C113: 0.017841 | D113: 0.038723
A114: 6 M | B114: 0.059932874 | C114: 0.053596 | D114: 0.05945
A115: 1 Y | B115: -0.0062196819 | C115: -0.007326 | D115: -0.032041
A116: 3 Y | B116: 0.19190211 | C116: 0.129786 | D116: 0.154431
A117: 5 Y | B117: 0.25183083 | C117: 0.174585 | D117: 0.201781
A118: 10 Y | B118: 0.0812585 | C118: 0.112352 | D118: 0.123351
A120: Portfolio Attribution
A121: {='Output Dashboard '!$H$43:$J$45} -> P/E | B121: 24.745833 | C121: 0
A122: P/B | B122: 2.3241667 | C122: 0
A123: Beta | B123: 0.92916667 | C123: 0

Sheet performace_data
B2: As on 31st March'2025
B3: Large-Cap Funds | C3: Expense Ratio | D3: Corpus | F3: Returns | N3: CY Year Returns | AS3: Banking and PSU Fund | AT3: Expense Ratio | AU3: Corpus | AX3: Risk Return | BF3: Yearly Performance
B4: Large-Cap Funds | C4: Expense Ratio | D4: Month End | E4: AUM (Cr.) | F4: 1 month | G4: 3 months | H4: 6 months | I4: 1 Year | J4: 3 Year | K4: 5 Year | L4: 10 Year | N4: CY 2025 | O4: 2024 | P4: 2023 | Q4: 2022 | R4: 2021 | S4: 2020 | T4: 2019 | U4: 2018 | V4: 2017 | W4: 2016 | X4: 2015 | Y4: 2014 | Z4: 2013 | AA4: 2012 | AB4: 2011 | AC4: 2010 | AD4: 2009 | AE4: 2008 | AF4: 2007 | AG4: 2006 | AH4: 2005 | AI4: 2004 | AJ4: 2003 | AK4: 2002 | AL4: 2001 | AM4: 2000 | AN4: Sharpe Ratio | AO4: Beta | AP4: PE | AQ4: PB | AT4: Ratio | AU4: Month End | AV4: AUM (Cr.) | AX4: 1 Month | AY4: 3 Months | AZ4: 6 Months | BA4: 1 Year | BB4: 3 Years | BC4: 5 Years | BD4: 10 Years | BF4: 2025 | BG4: 2024 | BH4: 2023 | BI4: 2022 | BJ4: 2021 | BK4: 2020 | BL4: 2019 | BM4: 2018 | BN4: 2017 | BO4: 2016 | BP4: 2015 | BQ4: 2014 | BR4: 2013 | BS4: 2012 | BT4: 2011 | BU4: 2010
B5: Aditya Birla SL Frontline Equity Fund(G) | C5: 1.63 | D5: 45838 | E5: 30927.442 | F5: -0.022096 | G5: 0.0339 | H5: 0.074165 | I5: 0.002579 | J5: 0.162269 | K5: 0.200447 | L5: 0.120113 | N5: 0.048146 | O5: 0.15565864 | P5: 0.23070806 | Q5: 0.03537611 | R5: 0.27904615 | S5: 0.14220046 | T5: 0.076442841 | U5: -0.029051233 | V5: 0.3057575 | W5: 0.074258361 | X5: 0.011016302 | Y5: 0.44723989 | Z5: 0.092529199 | AA5: 0.36073435 | AB5: -0.22925026 | AC5: 0.18701429 | AD5: 0.90451182 | AE5: -0.48500123 | AF5: 0.62258129 | AG5: 0.47701827 | AH5: 0.41771094 | AI5: 0.21461187 | AJ5: 0.90803485 | AK5: 0.033 | AL5: NA | AM5: NA | AS5: Altacura AI Absolute Return Fund LLP | AX5: -0.0135 | AY5: 0.0086208814 | AZ5: 0.03917979 | BA5: 0.10592712 | BB5: 0.14255572 | BC5: NA | BD5: NA | BF5: 0.020220022 | BG5: 0.14136615 | BH5: 0.15236217 | BI5: 0.14957355 | BJ5: 0.02509849 | BK5: NA | BL5: NA | BM5: NA | BN5: NA | BO5: NA | BP5: NA | BQ5: NA | BR5: NA | BS5: NA
B6: Axis Bluechip Fund-Reg(G) | C6: 1.56 | D6: 45838 | E6: 34373.875 | F6: -0.02403 | G6: 0.02089 | H6: 0.054932 | I6: 0.001833 | J6: 0.116325 | K6: 0.147279 | L6: 0.116562 | N6: 0.030516 | O6: 0.13725872 | P6: 0.1744905 | Q6: -0.056599698 | R6: 0.20641126 | S6: 0.19719189 | T6: 0.18571957 | U6: 0.065431612 | V6: 0.38030468 | W6: -0.036182486 | X6: -0.012428793 | Y6: 0.40846098 | Z6: 0.13493377 | AA6: 0.31733915 | AB6: -0.22550676 | AC6: 0.184 | AD6: NA | AE6: NA | AF6: NA | AG6: NA | AH6: NA | AI6: NA | AJ6: NA | AK6: NA | AL6: NA | AM6: NA | AS6: ASK Absolute Return Fund | AX6: 0.0063 | AY6: 0.018304052 | AZ6: 0.05671931 | BA6: 0.13126329 | BB6: NA | BC6: NA | BD6: NA | BF6: 0.023497403 | BG6: 0.18006666 | BH6: NA | BI6: NA | BJ6: NA | BK6: NA | BL6: NA | BM6: NA | BN6: NA | BO6: NA | BP6: NA | BQ6: NA | BR6: NA | BS6: NA
B7: Bandhan Large Cap Fund-Reg(G) | C7: 2.03 | D7: 45838 | E7: 1928.3758 | F7: -0.009759 | G7: 0.045971 | H7: 0.085497 | I7: 0.015454 | J7: 0.165152 | K7: 0.184913 | L7: 0.12064 | N7: 0.03456 | O7: 0.18704035 | P7: 0.26771925 | Q7: -0.023183528 | R7: 0.26750314 | S7: 0.17413082 | T7: 0.10589769 | U7: -0.042266355 | V7: 0.34163436 | W7: 0.05284827 | X7: -0.056727651 | Y7: 0.30393294 | Z7: 0.080174756 | AA7: 0.27433523 | AB7: -0.23337071 | AC7: 0.18519573 | AD7: 0.74044045 | AE7: -0.51274325 | AF7: 0.48198398 | AG7: 0.1734 | AH7: NA | AI7: NA | AJ7: NA | AK7: NA | AL7: NA | AM7: NA | AS7: White Space Alpha Fund 2 | AX7: 0.0292 | AY7: 0.031531756 | AZ7: -0.0041260413 | BA7: 0.10107678 | BB7: 0.18686587 | BC7: 0.30179096 | BF7: 0.012964184 | BG7: 0.16109792 | BH7: 0.31611864 | BI7: 0.09406489 | BJ7: 0.44720911 | BK7: 0.26574361 | BL7: NA | BM7: NA | BN7: NA | BO7: NA | BP7: NA | BQ7: NA | BR7: NA | BS7: NA
B8: Canara Rob Bluechip Equity Fund-Reg(G) | C8: 1.64 | D8: 45838 | E8: 16617.33 | F8: -0.022278 | G8: 0.029528 | H8: 0.065354 | I8: 0.018666 | J8: 0.161045 | K8: 0.186387 | L8: 0.131291 | N8: 0.039245 | O8: 0.1778818 | P8: 0.22216925 | Q8: 0.0081711127 | R8: 0.2454355 | S8: 0.2305709 | T8: 0.15679591 | U8: 0.033920705 | V8: 0.31365741 | W8: 0.018867925 | X8: -0.0046948357 | Y8: 0.35885167 | Z8: 0.050251256 | AA8: 0.28387097 | AB8: -0.12757974 | AC8: 0.066 | AD8: NA | AE8: NA | AF8: NA | AG8: NA | AH8: NA | AI8: NA | AJ8: NA | AK8: NA | AL8: NA | AM8: NA | AN8: 0.7 | AO8: 0.9 | AP8: 26.79 | AQ8: 4.13 | AS8: Inquant Debt Plus AIF | AX8: NA | AY8: NA | AZ8: NA | BA8: NA | BB8: NA | BC8: NA | BD8: NA | BF8: NA | BG8: NA | BH8: NA | BI8: NA | BJ8: NA | BK8: NA | BL8: NA | BM8: NA | BN8: NA | BO8: NA | BP8: NA | BQ8: NA | BR8: NA | BS8: NA
B9: DSP Top 100 Equity Fund-Reg(G) | C9: 1.85 | D9: 45838 | E9: 6323.2679 | F9: -0.021492 | G9: 0.01465 | H9: 0.06126 | I9: 0.01562 | J9: 0.185538 | K9: 0.1903 | L9: 0.110868 | N9: 0.044684 | O9: 0.2049885 | P9: 0.26612783 | Q9: 0.014408547 | R9: 0.19525391 | S9: 0.074924487 | T9: 0.14845194 | U9: -0.027213439 | V9: 0.26480237 | W9: 0.048876567 | X9: -0.023289758 | Y9: 0.37488338 | Z9: 0.022260212 | AA9: 0.30285446 | AB9: -0.19847974 | AC9: 0.16797076 | AD9: 0.77127029 | AE9: -0.45541253 | AF9: 0.6493121 | AG9: 0.46598413 | AH9: 0.4290417 | AI9: 0.25011431 | AJ9: 1.187 | AK9: NA | AL9: NA | AM9: NA | AS9: AlphaMine Absolute Return Fund | AX9: 0.0022 | AY9: 0.021370082 | AZ9: 0.021131767 | BA9: 0.1080265 | BB9: 0.15702444 | BC9: NA | BD9: NA | BF9: 0.0050281603 | BG9: 0.16725751 | BH9: 0.1692687 | BI9: 0.13371028 | BJ9: NA | BK9: NA | BL9: NA | BM9: NA | BN9: NA | BO9: NA | BP9: NA | BQ9: NA | BR9: NA | BS9: NA
B10: Edelweiss Large Cap Fund-Reg(G) | C10: 2.11 | D10: 45838 | E10: 1322.0746 | F10: -0.03389 | G10: 0.017227 | H10: 0.042103 | I10: -0.030946 | J10: 0.158246 | K10: 0.184889 | L10: 0.118923 | N10: 0.018229 | O10: 0.14626571 | P10: 0.2571885 | Q10: 0.033761468 | R10: 0.23386914 | S10: 0.17286245 | T10: 0.115191 | U10: 0.016862391 | V10: 0.33803384 | W10: 0.0040453074 | X10: 0.0077456176 | Y10: 0.37654321 | Z10: 0.11097257 | AA10: 0.29773463 | AB10: -0.18577075 | AC10: 0.15966387 | AD10: 0.309 | AE10: NA | AF10: NA | AG10: NA | AH10: NA | AI10: NA | AJ10: NA | AK10: NA | AL10: NA | AM10: NA | AS10: MasterTrust Irage PMS | AX10: 0.0126 | AY10: 0.037250583 | AZ10: 0.079266509 | BA10: 0.17013075 | BB10: 0.13529855 | BC10: 0.12846998 | BF10: 0.054468942 | BG10: 0.1706778 | BH10: 0.10516945 | BI10: 0.092774729 | BJ10: 0.10082501 | BK10: 0.16216316 | BL10: 0.11393722 | BM10: 0.12732582 | BN10: 0.13211315 | BO10: NA | BP10: NA | BQ10: NA | BR10: NA | BS10: NA
B11: Franklin India Bluechip Fund(G) | C11: 1.84 | D11: 45838 | E11: 7983.816 | F11: -0.019053 | G11: 0.036704 | H11: 0.069894 | I11: 0.013708 | J11: 0.146926 | K11: 0.195552 | L11: 0.107427 | N11: 0.040589 | O11: 0.16213533 | P11: 0.21660848 | Q11: -0.022212752 | R11: 0.32758244 | S11: 0.13670259 | T11: 0.052560253 | U11: -0.035776523 | V11: 0.26308045 | W11: 0.064457763 | X11: 0.020175124 | Y11: 0.37221097 | Z11: 0.040781877 | AA11: 0.26788334 | AB11: -0.18248512 | AC11: 0.2296256 | AD11: 0.8448816 | AE11: -0.48142429 | AF11: 0.47408066 | AG11: 0.45523873 | AH11: 0.4122054 | AI11: 0.24601322 | AJ11: 1.2059202 | AK11: 0.23923445 | AL11: -0.16139099 | AM11: -0.13196594 | AS11: Vivriti Short-term Debt AIF
B12: HDFC Top 100 Fund(G) | C12: 1.59 | D12: 45838 | E12: 38905.124 | F12: -0.02065 | G12: 0.018871 | H12: 0.049209 | I12: -0.02436 | J12: 0.171713 | K12: 0.215781 | L12: 0.12449 | N12: 0.033793 | O12: 0.11644625 | P12: 0.30023194 | Q12: 0.10611136 | R12: 0.28536696 | S12: 0.059106121 | T12: 0.076981707 | U12: 0.0012633068 | V12: 0.31966805 | W12: 0.085208398 | X12: -0.060898105 | Y12: 0.46517644 | Z12: 0.040487798 | AA12: 0.32433239 | AB12: -0.24296179 | AC12: 0.25050428 | AD12: 0.94461088 | AE12: -0.45345427 | AF12: 0.54452834 | AG12: 0.37446862 | AH12: 0.55240683 | AI12: 0.27524752 | AJ12: 1.3447475 | AK12: 0.261347 | AL12: -0.10131579 | AM12: -0.21082294 | AS12: ICICI CCOF 3
B13: HSBC Large Cap Fund(G) | C13: 2.13 | D13: 45838 | E13: 1887.7311 | F13: -0.01841 | G13: 0.02958 | H13: 0.036813 | I13: -0.026154 | J13: 0.146284 | K13: 0.176785 | L13: 0.117438 | N13: -0.00662 | O13: 0.18323184 | P13: 0.2351433 | Q13: 0.0051164687 | R13: 0.22700806 | S13: 0.15854095 | T13: 0.15106851 | U13: -0.031707561 | V13: 0.30534337 | W13: 0.080212173 | X13: -0.029875145 | Y13: 0.34854924 | Z13: 0.031850503 | AA13: 0.23237926 | AB13: -0.22681756 | AC13: 0.17997841 | AD13: 0.58548056 | AE13: -0.480475 | AF13: 0.59525125 | AG13: 0.37249896 | AH13: 0.41968203 | AI13: 0.38730957 | AJ13: 1.6025391 | AK13: 0.024 | AL13: NA | AM13: NA | AS13: Vivriti Diversified Bond Fund II
B14: ICICI Pru Bluechip Fund(G) | C14: 1.42 | D14: 45838 | E14: 72336.051 | F14: -0.016662 | G14: 0.029834 | H14: 0.071031 | I14: 0.011239 | J14: 0.189794 | K14: 0.221221 | L14: 0.137519 | N14: 0.057922 | O14: 0.1687317 | P14: 0.27392739 | Q14: 0.068537259 | R14: 0.29174094 | S14: 0.13486177 | T14: 0.097705403 | U14: -0.0080763583 | V14: 0.32748538 | W14: 0.077353868 | X14: -0.0020957038 | Y14: 0.41103992 | Z14: 0.10211841 | AA14: 0.26790634 | AB14: -0.16407599 | AC14: 0.27066569 | AD14: 0.91188811 | AE14: -0.285 | AF14: NA | AG14: NA | AH14: NA | AI14: NA | AJ14: NA | AK14: NA | AL14: NA | AM14: NA | AN14: 0.9 | AO14: 0.89 | AP14: 22.93 | AQ14: 3.49 | AS14: UTI SDOF 4
B15: Invesco India Largecap Fund(G) | C15: 2.05 | D15: 45838 | E15: 1558.2449 | F15: -0.034711 | G15: 0.036672 | H15: 0.070412 | I15: -0.002188 | J15: 0.170622 | K15: 0.191028 | L15: 0.121877 | N15: 0.017854 | O15: 0.19996429 | P15: 0.27789185 | Q15: -0.029880478 | R15: 0.32531534 | S15: 0.14051522 | T15: 0.10499076 | U15: -0.004416636 | V15: 0.28341993 | W15: 0.027669903 | X15: 0.045685279 | Y15: 0.39518414 | Z15: 0.092034029 | AA15: 0.24326923 | AB15: -0.21921922 | AC15: 0.17667845 | AD15: 0.132 | AE15: NA | AF15: NA | AG15: NA | AH15: NA | AI15: NA | AJ15: NA | AK15: NA | AL15: NA | AM15: NA | AS15: Edelweiss Multi Asset Allocation Fund | AX15: 0.0148 | AY15: 0.0283 | AZ15: 0.0472 | BA15: 0.0912 | BB15: NA | BC15: NA | BD15: NA | BF15: 0.0335 | BG15: 0.071 | BH15: 0.0358 | BI15: NA | BJ15: NA | BK15: NA | BL15: NA | BM15: NA | BN15: NA | BO15: NA | BP15: NA | BQ15: NA | BR15: NA | BS15: NA | BT15: NA | BU15: NA
B16: Kotak Bluechip Fund(G) | C16: 1.73 | D16: 45838 | E16: 10515.746 | F16: -0.022727 | G16: 0.035144 | H16: 0.067235 | I16: -0.00366 | J16: 0.159149 | K16: 0.193198 | L16: 0.121931 | N16: 0.038292 | O16: 0.16245345 | P16: 0.22901642 | Q16: 0.019884268 | R16: 0.27737167 | S16: 0.16371431 | T16: 0.14195371 | U16: -0.021050815 | V16: 0.29177695 | W16: 0.0293261 | X16: 0.037691265 | Y16: 0.42456531 | Z16: 0.042604903 | AA16: 0.23411042 | AB16: -0.18461974 | AC16: 0.16290817 | AD16: 0.66706767 | AE16: -0.50345233 | AF16: 0.66563268 | AG16: 0.4361302 | AH16: 0.49369115 | AI16: 0.36761676 | AJ16: 0.93600931 | AK16: NA | AL16: NA | AM16: NA | AN16: 0.65 | AO16: 0.93 | AP16: 23.66 | AQ16: 3.61 | AS16: Aditya Birla SL Banking & PSU Debt(G) | AT16: 0.73 | AU16: 45716 | AV16: 9585.9669 | AX16: 0.013215 | AY16: 0.022823 | AZ16: 0.038488 | BA16: 0.081713 | BB16: 0.065641 | BC16: 0.06502 | BD16: 0.075168 | BF16: 0.022823 | BG16: 0.078779361 | BH16: 0.068615907 | BI16: 0.0365218 | BJ16: 0.03585331 | BK16: 0.10912871 | BL16: 0.099015785 | BM16: 0.066298122 | BN16: 0.056139229 | BO16: 0.12320145 | BP16: 0.085202932 | BQ16: 0.12471321 | BR16: 0.096338822 | BS16: 0.098549163 | BT16: 0.09254704 | BU16: 0.058149316
B17: Mirae Asset Large Cap Fund-Reg(G) | C17: 1.51 | D17: 45838 | E17: 40724.594 | F17: -0.016011 | G17: 0.040576 | H17: 0.074604 | I17: 0.009309 | J17: 0.134872 | K17: 0.176536 | L17: 0.127192 | N17: 0.049824 | O17: 0.12685662 | P17: 0.18449936 | Q17: 0.015984371 | R17: 0.27735736 | S17: 0.13702694 | T17: 0.12725611 | U17: -0.0063769193 | V17: 0.38580335 | W17: 0.080898946 | X17: 0.042540849 | Y17: 0.52859747 | Z17: 0.089469729 | AA17: 0.33276109 | AB17: -0.19641317 | AC17: 0.23121019 | AD17: 1.0933333 | AE17: -0.325 | AF17: NA | AG17: NA | AH17: NA | AI17: NA | AJ17: NA | AK17: NA | AL17: NA | AM17: NA | AS17: Axis Banking & PSU Debt Fund-Reg(G) | AT17: 0.63 | AU17: 45716 | AV17: 12987.924 | AX17: 0.012468 | AY17: 0.023066 | AZ17: 0.039291 | BA17: 0.080002 | BB17: 0.064007 | BC17: 0.061721 | BD17: 0.072638 | BF17: 0.023066 | BG17: 0.075549841 | BH17: 0.065271973 | BI17: 0.037538678 | BJ17: 0.033896428 | BK17: 0.095916205 | BL17: 0.10523663 | BM17: 0.0756194 | BN17: 0.071828814 | BO17: 0.083710786 | BP17: 0.084982704 | BQ17: 0.09271979 | BR17: 0.086891331 | BS17: 0.0518253 | BT17: NA | BU17: NA
B18: Motilal Oswal Focused Fund-Reg(G) | C18: 2.14 | D18: 45838 | E18: 1563.5841 | F18: -0.015099 | G18: 0.118679 | H18: 0.064219 | I18: -0.110031 | J18: 0.106595 | K18: 0.137627 | L18: 0.097715 | N18: -0.037661 | O18: 0.1361965 | P18: 0.18819264 | Q18: 0.01953572 | R18: 0.14587881 | S18: 0.1727827 | T18: 0.17085497 | U18: -0.042033905 | V18: 0.32153901 | W18: 0.028329039 | X18: 0.058967585 | Y18: 0.44235624 | Z18: 0.04183 | AA18: NA | AB18: NA | AC18: NA | AD18: NA | AE18: NA | AF18: NA | AG18: NA | AH18: NA | AI18: NA | AJ18: NA | AK18: NA | AL18: NA | AM18: NA | AS18: Bajaj Finserv Banking and PSU Fund-Reg(G) | AT18: 0.89 | AU18: 45716 | AV18: 118.4179 | AX18: 0.013812 | AY18: 0.023175 | AZ18: 0.037051 | BA18: 0.080731 | BB18: NA | BC18: NA | BD18: NA | BF18: 0.023175 | BG18: 0.078089004 | BH18: 0.01141 | BI18: NA | BJ18: NA | BK18: NA | BL18: NA | BM18: NA | BN18: NA | BO18: NA | BP18: NA | BQ18: NA | BR18: NA | BS18: NA | BT18: NA | BU18: NA
B19: Nippon India Large Cap Fund(G) | C19: 1.51 | D19: 45838 | E19: 43828.6 | F19: -0.017875 | G19: 0.047609 | H19: 0.078495 | I19: 0.006832 | J19: 0.204123 | K19: 0.251486 | L19: 0.137065 | N19: 0.045961 | O19: 0.18239725 | P19: 0.32147843 | Q19: 0.11327834 | R19: 0.32367195 | S19: 0.049081268 | T19: 0.072519095 | U19: -0.0020039659 | V19: 0.38421195 | W19: 0.022273823 | X19: 0.01114297 | Y19: 0.54645567 | Z19: 0.041530123 | AA19: 0.40968364 | AB19: -0.26445203 | AC19: 0.19364058 | AD19: 0.73425141 | AE19: -0.49161838 | AF19: 0.32552 | AG19: NA | AH19: NA | AI19: NA | AJ19: NA | AK19: NA | AL19: NA | AM19: NA | AN19: 0.97 | AO19: 0.93 | AP19: 23.34 | AQ19: 3.48 | AS19: Bandhan Banking & PSU Debt Fund-Reg(G) | AT19: 0.63 | AU19: 45716 | AV19: 13421.371 | AX19: 0.011061 | AY19: 0.021775 | AZ19: 0.037649 | BA19: 0.079011 | BB19: 0.063857 | BC19: 0.063167 | BD19: 0.072341 | BF19: 0.021775 | BG19: 0.075793573 | BH19: 0.067378924 | BI19: 0.03619234 | BJ19: 0.034072003 | BK19: 0.10928488 | BL19: 0.11201107 | BM19: 0.07349549 | BN19: 0.055009909 | BO19: 0.07992761 | BP19: 0.08540439 | BQ19: 0.092553023 | BR19: 0.07171 | BS19: NA | BT19: NA | BU19: NA
B20: Quant Large Cap Fund-Reg(G) | C20: 1.9 | D20: 45838 | E20: 2753.2825 | F20: -0.025314 | G20: 0.065384 | H20: 0.045383 | I20: -0.070916 | J20: NA | K20: NA | L20: NA | N20: 0.015821 | O20: 0.14180552 | P20: 0.2684703 | Q20: 0.01203 | R20: NA | S20: NA | T20: NA | U20: NA | V20: NA | W20: NA | X20: NA | Y20: NA | Z20: NA | AA20: NA | AB20: NA | AC20: NA | AD20: NA | AE20: NA | AF20: NA | AG20: NA | AH20: NA | AI20: NA | AJ20: NA | AK20: NA | AL20: NA | AM20: NA | AS20: Baroda BNP Paribas Banking and PSU Bond Fund-Reg(G) | AT20: 0.79 | AU20: 45716 | AV20: 25.4039 | AX20: 0.014231 | AY20: 0.023712 | AZ20: 0.038273 | BA20: 0.079998 | BB20: 0.057487 | BC20: NA | BD20: NA | BF20: 0.023712 | BG20: 0.078167958 | BH20: 0.062874166 | BI20: 0.016991509 | BJ20: 0.03417652 | BK20: 0.00215 | BL20: NA | BM20: NA | BN20: NA | BO20: NA | BP20: NA | BQ20: NA | BR20: NA | BS20: NA | BT20: NA | BU20: NA
B21: SBI BlueChip Fund-Reg(G) | C21: 1.48 | D21: 45838 | E21: 53959.081 | F21: -0.019714 | G21: 0.034552 | H21: 0.066194 | I21: 0.010644 | J21: 0.151055 | K21: 0.195883 | L21: 0.121038 | N21: 0.050959 | O21: 0.12452086 | P21: 0.22621771 | Q21: 0.043574375 | R21: 0.26083199 | S21: 0.16339437 | T21: 0.116371 | U21: -0.041095749 | V21: 0.30229212 | W21: 0.048280784 | X21: 0.079896741 | Y21: 0.47858033 | Z21: 0.075809179 | AA21: 0.38230384 | AB21: -0.24225174 | AC21: 0.11889597 | AD21: 0.87898936 | AE21: -0.55023923 | AF21: 0.42783945 | AG21: 0.171 | AH21: NA | AI21: NA | AJ21: NA | AK21: NA | AL21: NA | AM21: NA | AS21: Canara Rob Banking and PSU Debt Fund-Reg(G) | AT21: 0.71 | AU21: 45716 | AV21: 230.0894 | AX21: 0.010766 | AY21: 0.020533 | AZ21: 0.035901 | BA21: 0.076772 | BB21: NA | BC21: NA | BD21: NA | BF21: 0.020533 | BG21: 0.076620388 | BH21: 0.06217162 | BI21: 0.01445 | BJ21: NA | BK21: NA | BL21: NA | BM21: NA | BN21: NA | BO21: NA | BP21: NA | BQ21: NA | BR21: NA | BS21: NA | BT21: NA | BU21: NA
B22: Tata Large Cap Fund-Reg(G) | C22: 2 | D22: 45838 | E22: 2701.7776 | F22: -0.029866 | G22: 0.018921 | H22: 0.042854 | I22: -0.041784 | J22: 0.149555 | K22: 0.193573 | L22: 0.111409 | N22: 0.023155 | O22: 0.12893307 | P22: 0.2453916 | Q22: 0.033117279 | R22: 0.32670901 | S22: 0.08334113 | T22: 0.12105105 | U22: -0.036483489 | V22: 0.29538417 | W22: 0.028963337 | X22: 0.013384043 | Y22: 0.36047873 | Z22: 0.079618712 | AA22: 0.28467119 | AB22: -0.21223889 | AC22: 0.18954593 | AD22: 0.77176028 | AE22: -0.49213696 | AF22: 0.61319394 | AG22: 0.42628928 | AH22: 0.44354235 | AI22: 0.29280003 | AJ22: 1.4064585 | AK22: 0.063867887 | AL22: -0.23847844 | AM22: -0.065964847 | AS22: DSP Banking & PSU Debt Fund-Reg(G) | AT22: 0.72 | AU22: 45716 | AV22: 3211.4465 | AX22: 0.016883 | AY22: 0.022519 | AZ22: 0.034762 | BA22: 0.083187 | BB22: 0.066645 | BC22: 0.06364 | BD22: 0.072591 | BF22: 0.022519 | BG22: 0.086378863 | BH22: 0.06710311 | BI22: 0.032067856 | BJ22: 0.031010941 | BK22: 0.10900991 | BL22: 0.099235448 | BM22: 0.063312352 | BN22: 0.054202619 | BO22: 0.10610844 | BP22: 0.085978604 | BQ22: 0.10421488 | BR22: 0.03277 | BS22: NA | BT22: NA | BU22: NA
B23: UTI Mastershare-Reg(G) | C23: 1.74 | D23: 45838 | E23: 13074.263 | F23: -0.023264 | G23: 0.022039 | H23: 0.047724 | I23: -0.009849 | J23: 0.13088 | K23: 0.178196 | L23: 0.112141 | N23: 0.040083 | O23: 0.11214977 | P23: 0.20781484 | Q23: -0.017947658 | R23: 0.29562368 | S23: 0.18671586 | T23: 0.10691731 | U23: -0.0038844725 | V23: 0.29572189 | W23: 0.036009266 | X23: -0.0048597755 | Y23: 0.43292567 | Z23: 0.059010932 | AA23: 0.25065104 | AB23: -0.19721254 | AC23: 0.18472652 | AD23: 0.74155284 | AE23: -0.5030368 | AF23: 0.62543554 | AG23: 0.2699115 | AH23: 0.17606245 | AI23: NA | AJ23: NA | AK23: NA | AL23: NA | AM23: NA | AS23: Edelweiss Banking and PSU Debt Fund-Reg(G) | AT23: 0.7 | AU23: 45716 | AV23: 263.6194 | AX23: 0.016354 | AY23: 0.025413 | AZ23: 0.03911 | BA23: 0.084519 | BB23: 0.06375 | BC23: 0.065044 | BD23: 0.07529 | BF23: 0.025413 | BG23: 0.081863013 | BH23: 0.063965145 | BI23: 0.025818264 | BJ23: 0.045303201 | BK23: 0.12919269 | BL23: 0.12921882 | BM23: 0.058581226 | BN23: 0.060058821 | BO23: 0.08035859 | BP23: 0.083360409 | BQ23: 0.10752458 | BR23: 0.02823 | BS23: NA | BT23: NA | BU23: NA
B24: UTI Nifty 50 ETF | C24: 0.05 | D24: 45838 | E24: 64150.21 | F24: -0.027639 | G24: 0.024295 | H24: 0.061562 | I24: 0.004964 | J24: 0.142216 | K24: 0.187925 | L24: NA | N24: 0.056746 | O24: 0.099910956 | P24: 0.2125411 | Q24: 0.056157732 | R24: 0.25494746 | S24: 0.15693706 | T24: 0.13453962 | U24: 0.045280136 | V24: 0.30309359 | W24: 0.046780383 | X24: 0.021939998 | Y24: NA | Z24: NA | AA24: NA | AB24: NA | AC24: NA | AD24: NA | AE24: NA | AF24: NA | AG24: NA | AH24: NA | AI24: NA | AJ24: NA | AK24: NA | AL24: NA | AM24: NA | AS24: Franklin India Banking & PSU Debt Fund(G) | AT24: 0.51 | AU24: 45716 | AV24: 587.34295 | AX24: 0.010765 | AY24: 0.020875 | AZ24: 0.037637 | BA24: 0.078652 | BB24: 0.063335 | BC24: 0.058892 | BD24: 0.071208 | BF24: 0.020875 | BG24: 0.077025991 | BH24: 0.06836225 | BI24: 0.032700515 | BJ24: 0.036923236 | BK24: 0.091325972 | BL24: 0.11195748 | BM24: 0.068597935 | BN24: 0.0633893 | BO24: 0.096554414 | BP24: 0.072633957 | BQ24: 0.07553 | BR24: NA | BS24: NA | BT24: NA | BU24: NA
B25: S&P BSE 100 | F25: -0.029931 | G25: 0.023115 | H25: 0.054214 | I25: -0.018044 | J25: 0.139445 | K25: 0.183864 | L25: 0.11603 | N25: 0.035912 | O25: 0.11958334 | P25: 0.21490819 | Q25: 0.045369467 | R25: 0.2499945 | S25: 0.15235788 | T25: 0.096332593 | U25: 0.011898696 | V25: 0.31515294 | W25: 0.035704539 | X25: -0.032464002 | Y25: 0.32284501 | Z25: 0.058734148 | AA25: 0.29957962 | AB25: -0.25733626 | AC25: 0.15659331 | AD25: 0.8503695 | AE25: -0.55281414 | AF25: 0.5974498 | AG25: 0.40968359 | AH25: 0.38346335 | AI25: 0.16439201 | AJ25: 0.84712742 | AK25: 0.068999878 | AL25: -0.23372756 | AM25: -0.22567337 | AS25: HDFC Banking and PSU Debt Fund-Reg(G) | AT25: 0.74 | AU25: 45716 | AV25: 5836.8354 | AX25: 0.013555 | AY25: 0.022796 | AZ25: 0.038329 | BA25: 0.080927 | BB25: 0.064865 | BC25: 0.063823 | BD25: 0.073895 | BF25: 0.022796 | BG25: 0.078520718 | BH25: 0.068312675 | BI25: 0.032786797 | BJ25: 0.036586459 | BK25: 0.1056561 | BL25: 0.10229267 | BM25: 0.05868105 | BN25: 0.063229348 | BO25: 0.10829762 | BP25: 0.09755094 | BQ25: 0.06939 | BR25: NA | BS25: NA | BT25: NA | BU25: NA
B26: S&P BSE SENSEX | F26: -0.028956 | G26: 0.011756 | H26: 0.047548 | I26: -0.006799 | J26: 0.121048 | K26: 0.166288 | L26: 0.111775 | N26: 0.038989 | O26: 0.081654606 | P26: 0.18736656 | Q26: 0.044407732 | R26: 0.21994131 | S26: 0.15750305 | T26: 0.14376629 | U26: 0.059063043 | V26: 0.27905963 | W26: 0.019485756 | X26: -0.050251242 | Y26: 0.29893891 | Z26: 0.089771763 | AA26: 0.25699195 | AB26: -0.2464356 | AC26: 0.17430937 | AD26: 0.81032951 | AE26: -0.52445829 | AF26: 0.4714675 | AG26: 0.46701561 | AH26: 0.42334867 | AI26: 0.13079898 | AJ26: 0.72889426 | AK26: 0.035235553 | AL26: -0.17869299 | AM26: -0.20649963 | AS26: HSBC Banking and PSU Debt Fund-Reg(G) | AT26: 0.61 | AU26: 45716 | AV26: 4246.1157 | AX26: 0.012191 | AY26: 0.021556 | AZ26: 0.038828 | BA26: 0.075843 | BB26: 0.054725 | BC26: 0.056754 | BD26: 0.067779 | BF26: 0.021556 | BG26: 0.07264331 | BH26: 0.064940755 | BI26: 0.015603596 | BJ26: 0.030324884 | BK26: 0.10399559 | BL26: 0.095724131 | BM26: 0.062456967 | BN26: 0.054782372 | BO26: 0.10265571 | BP26: 0.077445742 | BQ26: 0.087094941 | BR26: 0.082094723 | BS26: 0.02467 | BT26: -0.19711604 | BU26: 0.056932163
B27: NIFTY 50 | F27: -0.029341 | G27: 0.017841 | H27: 0.053596 | I27: -0.007326 | J27: 0.129786 | K27: 0.174585 | L27: 0.112352 | N27: 0.047518 | O27: 0.08804769 | P27: 0.20027839 | Q27: 0.043289607 | R27: 0.24119298 | S27: 0.14901651 | T27: 0.12022039 | U27: 0.031512625 | V27: 0.28645948 | W27: 0.030133332 | X27: -0.040608739 | Y27: 0.31388008 | Z27: 0.067551777 | AA27: 0.27697165 | AB27: -0.24618143 | AC27: 0.17947338 | AD27: 0.75761621 | AE27: -0.51794383 | AF27: 0.54765026 | AG27: 0.39831838 | AH27: 0.36339822 | AI27: 0.10679612 | AJ27: 0.71902149 | AK27: 0.032529153 | AL27: -0.16184559 | AM27: -0.14650951 | AS27: ICICI Pru Banking & PSU Debt Fund(G) | AT27: 0.74 | AU27: 45716 | AV27: 10092.248 | AX27: 0.011755 | AY27: 0.022022 | AZ27: 0.041196 | BA27: 0.080557 | BB27: 0.070255 | BC27: 0.06704 | BD27: 0.074984 | BF27: 0.022022 | BG27: 0.078957058 | BH27: 0.07315605 | BI27: 0.042694925 | BJ27: 0.042201238 | BK27: 0.092877505 | BL27: 0.10104015 | BM27: 0.057176113 | BN27: 0.056228364 | BO27: 0.12621984 | BP27: 0.086427002 | BQ27: 0.10496887 | BR27: 0.0892704 | BS27: 0.088708492 | BT27: 0.091194672 | BU27: 0.06004
B28: NIFTY NEXT 50 | F28: -0.027567 | G28: 0.040108 | H28: 0.06287 | I28: -0.10285 | J28: 0.178801 | K28: 0.200799 | L28: 0.124071 | N28: -0.013123 | O28: 0.27450752 | P28: 0.26446486 | Q28: -0.00071652072 | R28: 0.29867066 | S28: 0.14840564 | T28: 0.0045690377 | U28: -0.089968722 | V28: 0.44764302 | W28: 0.070713644 | X28: 0.069566917 | Y28: 0.44416137 | Z28: 0.048071118 | AA28: 0.48084746 | AB28: -0.3187487 | AC28: 0.17811841 | AD28: 1.279057 | AE28: -0.63520109 | AF28: 0.75733675 | AG28: 0.28239901 | AH28: 0.24434689 | AI28: 0.30760196 | AJ28: 1.4101766 | AK28: 0.088384811 | AL28: -0.46485027 | AM28: -0.39102114 | AS28: Invesco India Banking and PSU Fund(G) | AT28: 0.63 | AU28: 45716 | AV28: 100.2439 | AX28: 0.014095 | AY28: 0.02258 | AZ28: 0.036818 | BA28: 0.080816 | BB28: 0.057694 | BC28: 0.05639 | BD28: 0.064037 | BF28: 0.02258 | BG28: 0.082240309 | BH28: 0.064597532 | BI28: 0.00706597 | BJ28: 0.034208574 | BK28: 0.094919563 | BL28: 0.096750438 | BM28: 0.0717279 | BN28: 0.048873987 | BO28: 0.074099591 | BP28: 0.068512537 | BQ28: 0.08702073 | BR28: 0.071080341 | BS28: 0.0021083 | BT28: NA | BU28: NA
B29: Category Average | F29: =AVERAGE(F5:F24) -> -0.022027 | G29: =AVERAGE(G5:G24) -> 0.0360513 | H29: =AVERAGE(H5:H24) -> 0.061447 | I29: =AVERAGE(I5:I24) -> -0.010452 | J29: =AVERAGE(J5:J24) -> 0.15538732 | K29: =AVERAGE(K5:K24) -> 0.18994768 | L29: =AVERAGE(L5:L24) -> 0.11975772 | N29: =AVERAGE(N5:N24) -> 0.0321049 | O29: =AVERAGE(O5:O24) -> 0.15274136 | P29: =AVERAGE(P5:P24) -> 0.24029144 | Q29: =AVERAGE(Q5:Q24) -> 0.021761015 | R29: =AVERAGE(R5:R24) -> 0.26562762 | S29: =AVERAGE(S5:S24) -> 0.14392638 | T29: =AVERAGE(T5:T24) -> 0.11911939 | U29: =AVERAGE(U5:U24) -> -0.0088778563 | ... AM29: =AVERAGE(AM5:AM24) -> -0.13625125 | AS29: ITI Banking & PSU Debt Fund-Reg(G) | AT29: 0.7 | AU29: 45716 | AV29: 30.5653 | AX29: 0.010283 | AY29: 0.02064 | AZ29: 0.036304 | BA29: 0.073687 | BB29: 0.064727 | BC29: NA | BD29: NA | BF29: 0.02064 | BG29: 0.076071804 | BH29: 0.062999113 | BI29: 0.042433894 | BJ29: 0.036347106 | BK29: 0.01191 | BL29: NA | BM29: NA | BN29: NA | BO29: NA | BP29: NA | BQ29: NA | BR29: NA | BS29: NA | BT29: NA | BU29: NA
AS30: Kotak Banking and PSU Debt Fund(G) | AT30: 0.75 | AU30: 45716 | AV30: 5761.9869 | AX30: 0.013049 | AY30: 0.022182 | AZ30: 0.037352 | BA30: 0.08135 | BB30: 0.066035 | BC30: 0.064847 | BD30: 0.074685 | BF30: 0.022182 | BG30: 0.080312307 | BH30: 0.067708017 | BI30: 0.03598099 | BJ30: 0.039126906 | BK30: 0.10506663 | BL30: 0.10843988 | BM30: 0.06714405 | BN30: 0.061701811 | BO30: 0.099623332 | BP30: 0.085634079 | BQ30: 0.095126499 | BR30: 0.098275814 | BS30: 0.076329608 | BT30: 0.078518124 | BU30: 0.036520796
AS31: LIC MF Banking & PSU Fund-Reg(G) | AT31: 0.78 | AU31: 45716 | AV31: 1881.9096 | AX31: 0.014643 | AY31: 0.023844 | AZ31: 0.038255 | BA31: 0.080928 | BB31: 0.06325 | BC31: 0.057687 | BD31: 0.066254 | BF31: 0.023844 | BG31: 0.077791605 | BH31: 0.065089002 | BI31: 0.030611229 | BJ31: 0.025743384 | BK31: 0.085582659 | BL31: 0.098575246 | BM31: 0.072010375 | BN31: 0.061304313 | BO31: 0.081421435 | BP31: 0.059928835 | BQ31: 0.075218755 | BR31: 0.08085185 | BS31: 0.087324125 | BT31: 0.082495595 | BU31: 0.054709056
B32: Large-Mid | C32: Expense Ratio | D32: Corpus | F32: Returns | N32: CY Year Returns | AS32: Mirae Asset Banking and PSU Fund-Reg(G) | AT32: 0.81 | AU32: 45716 | AV32: 47.918026 | AX32: 0.013688 | AY32: 0.022021 | AZ32: 0.03885 | BA32: 0.079619 | BB32: 0.061269 | BC32: NA | BD32: NA | BF32: 0.022021 | BG32: 0.079484416 | BH32: 0.063178613 | BI32: 0.026726755 | BJ32: 0.033911107 | BK32: 0.01943 | BL32: NA | BM32: NA | BN32: NA | BO32: NA | BP32: NA | BQ32: NA | BR32: NA | BS32: NA | BT32: NA | BU32: NA
D33: Month End | E33: AUM (Cr.) | F33: 1 month | G33: 3 months | H33: 6 months | I33: 1 Year | J33: 3 Year | K33: 5 Year | L33: 10 Year | N33: CY 2025 | O33: 2024 | P33: 2023 | Q33: 2022 | R33: 2021 | S33: 2020 | T33: 2019 | U33: 2018 | V33: 2017 | W33: 2016 | X33: 2015 | Y33: 2014 | Z33: 2013 | AA33: 2012 | AB33: 2011 | AC33: 2010 | AD33: 2009 | AE33: 2008 | AF33: 2007 | AG33: 2006 | AH33: 2005 | AI33: 2004 | AJ33: 2003 | AK33: 2002 | AL33: 2001 | AM33: 2000 | AS33: Nippon India Banking & PSU Debt Fund(G) | AT33: 0.76 | AU33: 45716 | AV33: 5708.448 | AX33: 0.014032 | AY33: 0.023173 | AZ33: 0.037979 | BA33: 0.080922 | BB33: 0.064005 | BC33: 0.064171 | BD33: NA | BF33: 0.023173 | BG33: 0.078521199 | BH33: 0.067979872 | BI33: 0.03169927 | BJ33: 0.038587829 | BK33: 0.10930828 | BL33: 0.1049394 | BM33: 0.064093829 | BN33: 0.059584891 | BO33: 0.10176312 | BP33: 0.05608 | BQ33: NA | BR33: NA | BS33: NA | BT33: NA | BU33: NA
B34: Aditya Birla SL Equity Advantage Fund(G) | C34: 1.89 | D34: 45838 | E34: 5938.6697 | F34: -0.029179 | G34: 0.059811 | H34: 0.070842 | I34: -0.034068 | J34: 0.145022 | K34: 0.186091 | L34: 0.112275 | N34: 0.009438 | O34: 0.15576279 | P34: 0.26927419 | Q34: -0.12981422 | R34: 0.3826978 | S34: 0.18301905 | T34: 0.089126239 | U34: -0.13718828 | V34: 0.41845156 | W34: 0.084771244 | X34: 0.052353385 | Y34: 0.60146263 | Z34: 0.072240059 | AA34: 0.29713279 | AB34: -0.28030434 | AC34: 0.14394039 | AD34: 0.8728081 | AE34: -0.58375739 | AF34: 0.5654168 | AG34: 0.34385813 | AH34: 0.43246592 | AI34: 0.26936689 | AJ34: 1.1033912 | AK34: 0.033333333 | AL34: -0.23902439 | AM34: -0.46091292 | AS34: SBI Banking and PSU Fund-Reg(G) | AT34: 0.81 | AU34: 45716 | AV34: 3873.701 | AX34: 0.013412 | AY34: 0.022945 | AZ34: 0.037474 | BA34: 0.079409 | BB34: 0.06153 | BC34: 0.059747 | BD34: 0.070359 | BF34: 0.022945 | BG34: 0.076853266 | BH34: 0.065570524 | BI34: 0.028668579 | BJ34: 0.02584904 | BK34: 0.10470041 | BL34: 0.096694565 | BM34: 0.073631934 | BN34: 0.063865533 | BO34: 0.083349621 | BP34: 0.087326405 | BQ34: 0.10015413 | BR34: 0.083364702 | BS34: 0.090831264 | BT34: 0.088368946 | BU34: 0.055658927
B35: Axis Growth Opp Fund-Reg(G) | C35: 1.68 | D35: 45838 | E35: 14954.276 | F35: -0.016359 | G35: 0.06459 | H35: 0.065289 | I35: 0.009012 | J35: 0.178521 | K35: 0.227601 | L35: NA | N35: 0.014054 | O35: 0.25519404 | P35: 0.30954825 | Q35: -0.088868101 | R35: 0.44557133 | S35: 0.2470489 | T35: 0.16388616 | U35: 0.019 | V35: NA | W35: NA | X35: NA | Y35: NA | Z35: NA | AA35: NA | AB35: NA | AC35: NA | AD35: NA | AE35: NA | AF35: NA | AG35: NA | AH35: NA | AI35: NA | AJ35: NA | AK35: NA | AL35: NA | AM35: NA | AS35: Sundaram Banking & PSU Fund(G) | AT35: 0.42 | AU35: 45716 | AV35: 337.32435 | AX35: 0.013264 | AY35: 0.022941 | AZ35: 0.038371 | BA35: 0.083365 | BB35: 0.063686 | BC35: 0.057521 | BD35: 0.066899 | BF35: 0.022941 | BG35: 0.07993559 | BH35: 0.068439989 | BI35: 0.029962482 | BJ35: 0.029320025 | BK35: 0.076413426 | BL35: 0.10060673 | BM35: 0.060618277 | BN35: 0.062326518 | BO35: 0.078846837 | BP35: 0.084668925 | BQ35: 0.09353197 | BR35: 0.08514809 | BS35: 0.099285758 | BT35: 0.093251631 | BU35: 0.049139128
B36: Bandhan Core Equity Fund-Reg(G) | C36: 1.73 | D36: 45838 | E36: 9735.3598 | F36: -0.012477 | G36: 0.059945 | H36: 0.079903 | I36: 0.000762 | J36: 0.24794 | K36: 0.266451 | L36: 0.150467 | N36: 0.0204 | O36: 0.28787113 | P36: 0.36235542 | Q36: 0.069317362 | R36: 0.34075077 | S36: 0.12937063 | T36: 0.036936324 | U36: -0.051098343 | V36: 0.3728786 | W36: 0.079863436 | X36: 0.052144719 | Y36: 0.2862369 | Z36: 0.025146496 | AA36: 0.37255676 | AB36: -0.26785151 | AC36: 0.14380919 | AD36: 0.67055037 | AE36: -0.54815031 | AF36: 0.67206247 | AG36: 0.28918114 | AH36: 0.209 | AI36: NA | AJ36: NA | AK36: NA | AL36: NA | AM36: NA | AS36: TRUSTMF Banking & PSU Fund-Reg(G) | AT36: 0.71 | AU36: 45716 | AV36: 219.21459 | AX36: 0.01061 | AY36: 0.021104 | AZ36: 0.035627 | BA36: 0.078579 | BB36: 0.057286 | BC36: NA | BD36: NA | BF36: 0.021104 | BG36: 0.074403405 | BH36: 0.064901266 | BI36: 0.02073183 | BJ36: 0.0407282 | BK36: NA | BL36: NA | BM36: NA | BN36: NA | BO36: NA | BP36: NA | BQ36: NA | BR36: NA | BS36: NA | BT36: NA | BU36: NA
B37: Canara Rob Emerg Equities Fund-Reg(G) | C37: 1.6 | D37: 45838 | E37: 26117.614 | F37: -0.025189 | G37: 0.055282 | H37: 0.073313 | I37: 0.005758 | J37: 0.173117 | K37: 0.221895 | L37: 0.147989 | N37: 0.002476 | O37: 0.26315789 | P37: 0.24037692 | Q37: -0.016475862 | R37: 0.36992781 | S37: 0.24545267 | T37: 0.086824666 | U37: -0.092919002 | V37: 0.52052672 | W37: 0.025579917 | X37: 0.13059098 | Y37: 0.96021127 | Z37: 0.031601889 | AA37: 0.48891293 | AB37: -0.22278268 | AC37: 0.28317152 | AD37: 1.1237113 | AE37: -0.66057543 | AF37: 0.58667489 | AG37: 0.2507716 | AH37: 0.296 | AI37: NA | AJ37: NA | AK37: NA | AL37: NA | AM37: NA | AN37: 0.71 | AO37: 0.97 | AP37: 37.16 | AQ37: 5.99 | AS37: UTI Banking & PSU Fund-Reg(G) | AT37: 0.54 | AU37: 45716 | AV37: 825.4587 | AX37: 0.010101 | AY37: 0.021094 | AZ37: 0.036605 | BA37: 0.077871 | BB37: 0.086104 | BC37: 0.072117 | BD37: 0.068095 | BF37: 0.021094 | BG37: 0.076359849 | BH37: 0.066586036 | BI37: 0.10315141 | BJ37: 0.028155725 | BK37: 0.088871616 | BL37: -0.010354307 | BM37: 0.068107452 | BN37: 0.063844341 | BO37: 0.11680771 | BP37: 0.085937356 | BQ37: 0.08486 | BR37: NA | BS37: NA | BT37: NA | BU37: NA
B38: DSP Equity Opportunities Fund-Reg(G) | C38: 1.68 | D38: 45838 | E38: 15663.379 | F38: -0.026616 | G38: 0.028275 | H38: 0.063456 | I38: -0.023299 | J38: 0.207303 | K38: 0.233106 | L38: 0.147141 | N38: 0.015901 | O38: 0.23850697 | P38: 0.32470459 | Q38: 0.043712456 | R38: 0.31197078 | S38: 0.14239935 | T38: 0.1144796 | U38: -0.092434581 | V38: 0.40111146 | W38: 0.11164291 | X38: 0.060911859 | Y38: 0.45404111 | Z38: 0.0646162 | AA38: 0.2935523 | AB38: -0.25061267 | AC38: 0.2419655 | AD38: 0.86444962 | AE38: -0.55104856 | AF38: 0.59846707 | AG38: 0.43963134 | AH38: 0.49884881 | AI38: 0.30365183 | AJ38: 1.3797619 | AK38: 0.25748503 | AL38: -0.21411765 | AM38: -0.15 | AS38: Category Average | AX38: =AVERAGE(AX16:AX37) -> 0.012919682 | AY38: =AVERAGE(AY16:AY37) -> 0.0223995 | AZ38: =AVERAGE(AZ16:AZ37) -> 0.037734091 | BA38: =AVERAGE(BA16:BA37) -> 0.079929909 | BB38: =AVERAGE(BB16:BB37) -> 0.06400765 | BC38: =AVERAGE(BC16:BC37) -> 0.062348813 | BD38: =AVERAGE(BD16:BD37) -> 0.071081533 | BF38: =AVERAGE(BF16:BF37) -> 0.0223995 | BG38: =AVERAGE(BG16:BG37) -> 0.07819831 | BH38: =AVERAGE(BH16:BH37) -> 0.063664206 | BI38: =AVERAGE(BI16:BI37) -> 0.032399938 | BJ38: =AVERAGE(BJ16:BJ37) -> 0.034616306 | BK38: =AVERAGE(BK16:BK37) -> 0.086565271 | BL38: =AVERAGE(BL16:BL37) -> 0.096961508 | BM38: =AVERAGE(BM16:BM37) -> 0.066347029 | ... BU38: =AVERAGE(BU16:BU37) -> 0.053021341
B39: Edelweiss Large & Mid Cap Fund-Reg(G) | C39: 1.84 | D39: 45838 | E39: 4139.4816 | F39: -0.033928 | G39: 0.054652 | H39: 0.052899 | I39: -0.00812 | J39: 0.18257 | K39: 0.226557 | L39: 0.138024 | N39: -0.013214 | O39: 0.24476398 | P39: 0.29697805 | Q39: 0.013405332 | R39: 0.3695343 | S39: 0.16974683 | T39: 0.1110327 | U39: -0.033455679 | V39: 0.38107841 | W39: 0.0048683736 | X39: 0.026751828 | Y39: 0.44715338 | Z39: 0.052965653 | AA39: 0.26745329 | AB39: -0.2260274 | AC39: 0.26401399 | AD39: 0.71619391 | AE39: -0.55389663 | AF39: 0.4936 | AG39: NA | AH39: NA | AI39: NA | AJ39: NA | AK39: NA | AL39: NA | AM39: NA | AS39: Crisil Short Term Fund | AX39: 0.0087263868 | AY39: 0.020764393 | AZ39: 0.037718441 | BA39: 0.080280059 | BB39: 0.065930171 | BC39: 0.065514977 | BD39: 0.073804732 | BF39: 0.020764393 | BG39: 0.079702926 | BH39: 0.072598887 | BI39: 0.035868229 | BJ39: 0.043796599 | BK39: 0.10416197 | BL39: 0.095336484 | BM39: 0.066506819 | BN39: 0.060295716 | BO39: 0.098673876 | BP39: 0.086554994 | BQ39: 0.10468193 | BR39: 0.082720616 | BS39: 0.091237132 | BT39: 0.078677103 | BU39: 0.047004033
B40: Franklin India Equity Advantage Fund(G) | C40: 2.01 | D40: 45838 | E40: 3684.3191 | F40: -0.02752 | G40: 0.066995 | H40: 0.082437 | I40: 0.022043 | J40: 0.166943 | K40: 0.23272 | L40: 0.114271 | N40: 0.046536 | O40: 0.18801624 | P40: 0.26963386 | Q40: -0.028204301 | R40: 0.39053178 | S40: 0.12022042 | T40: 0.021090416 | U40: -0.049931065 | V40: 0.3113038 | W40: 0.039993169 | X40: 0.01957231 | Y40: 0.55897514 | Z40: 0.070734605 | AA40: 0.31445008 | AB40: -0.22251445 | AC40: 0.21007946 | AD40: 0.88734407 | AE40: -0.51630743 | AF40: 0.49053181 | AG40: 0.41913747 | AH40: 0.484 | AI40: NA | AJ40: NA | AK40: NA | AL40: NA | AM40: NA
B41: HDFC Large and Mid Cap Fund-Reg(G) | C41: 1.64 | D41: 45838 | E41: 26848.847 | F41: -0.025748 | G41: 0.056588 | H41: 0.075193 | I41: -0.020426 | J41: 0.213638 | K41: 0.271973 | L41: 0.137948 | N41: 0.024092 | O41: 0.19404647 | P41: 0.37718102 | Q41: 0.081656581 | R41: 0.43080229 | S41: 0.11433297 | T41: 0.065813394 | U41: -0.038312451 | V41: 0.29412773 | W41: 0.039174009 | X41: -0.048397121 | Y41: 0.27462192 | Z41: 0.045412112 | AA41: 0.35513885 | AB41: -0.29156247 | AC41: 0.20634395 | AD41: 0.81762282 | AE41: -0.56763053 | AF41: 0.46467282 | AG41: 0.36196714 | AH41: 0.47829457 | AI41: 0.19417939 | AJ41: 0.85909823 | AK41: 0.13321168 | AL41: -0.16382498 | AM41: -0.30044653 | AS41: Corporate Bond | AT41: Expense Ratio | AU41: Corpus | AX41: Risk Return | BF41: Yearly Performance
B42: HSBC Large & Mid Cap Fund-Reg(G) | C42: 1.9 | D42: 45838 | E42: 4365.0351 | F42: -0.020548 | G42: 0.08281 | H42: 0.064959 | I42: -0.033972 | J42: 0.198359 | K42: 0.228155 | L42: NA | N42: -0.067565 | O42: 0.38570358 | P42: 0.30319478 | Q42: -0.037971495 | R42: 0.3507929 | S42: 0.15255939 | T42: 0.04556 | U42: NA | V42: NA | W42: NA | X42: NA | Y42: NA | Z42: NA | AA42: NA | AB42: NA | AC42: NA | AD42: NA | AE42: NA | AF42: NA | AG42: NA | AH42: NA | AI42: NA | AJ42: NA | AK42: NA | AL42: NA | AM42: NA | AT42: Ratio | AU42: Month End | AV42: AUM (Cr.) | AX42: 1 Month | AY42: 3 Months | AZ42: 6 Months | BA42: 1 Year | BB42: 3 Years | BC42: 5 Years | BD42: 10 Years | BF42: 2025 | BG42: 2024 | BH42: 2023 | BI42: 2022 | BJ42: 2021 | BK42: 2020 | BL42: 2019 | BM42: 2018 | BN42: 2017 | BO42: 2016 | BP42: 2015 | BQ42: 2014 | BR42: 2013 | BS42: 2012 | BT42: 2011 | BU42: 2010
B43: ICICI Pru Large & Mid Cap Fund(G) | C43: 1.65 | D43: 45838 | E43: 22856.589 | F43: -0.027323 | G43: 0.027621 | H43: 0.059936 | I43: 0.008509 | J43: 0.217245 | K43: 0.274919 | L43: 0.152887 | N43: 0.067757 | O43: 0.20378849 | P43: 0.29937107 | Q43: 0.11701825 | R43: 0.41795224 | S43: 0.11725071 | T43: 0.057410941 | U43: -0.062136444 | V43: 0.29823406 | W43: 0.10265608 | X43: -0.0064067207 | Y43: 0.38291381 | Z43: 0.11377598 | AA43: 0.32829861 | AB43: -0.2032644 | AC43: 0.17543289 | AD43: 0.74606104 | AE43: -0.47741265 | AF43: 0.44398029 | AG43: 0.42774124 | AH43: 0.49531214 | AI43: 0.13348885 | AJ43: 0.94651867 | AK43: 0.12358277 | AL43: -0.13529412 | AM43: -0.33398629 | AN43: 1.17 | AO43: 0.84 | AP43: 24.56 | AQ43: 3.65 | AS43: Aditya Birla SL Corp Bond Fund(G) | AT43: 0.51 | AU43: 45716 | AV43: 25293.291 | AX43: 0.01307 | AY43: 0.023926 | AZ43: 0.040279 | BA43: 0.087219 | BB43: 0.070382 | BC43: 0.071649 | BD43: 0.077675 | BF43: 0.023926 | BG43: 0.085380813 | BH43: 0.072910548 | BI43: 0.040790616 | BJ43: 0.040384966 | BK43: 0.11889365 | BL43: 0.095998637 | BM43: 0.070013936 | BN43: 0.065148312 | BO43: 0.10243873 | BP43: 0.088894459 | BQ43: 0.10906651 | BR43: 0.084171366 | BS43: 0.10553333 | BT43: 0.09525846 | BU43: 0.038299296
B44: Invesco India Growth Opp Fund(G) | C44: 1.78 | D44: 45838 | E44: 7886.657 | F44: -0.011946 | G44: 0.115891 | H44: 0.147617 | I44: 0.105015 | J44: 0.26175 | K44: 0.248538 | L44: 0.152354 | N44: 0.050052 | O44: 0.37482117 | P44: 0.31564088 | Q44: -0.0037502344 | R44: 0.29662047 | S44: 0.1327458 | T44: 0.1070122 | U44: -0.00243309 | V44: 0.39617834 | W44: 0.03334796 | X44: 0.038268793 | Y44: 0.43745907 | Z44: 0.11541271 | AA44: 0.26524954 | AB44: -0.21820809 | AC44: 0.22261484 | AD44: 0.6217765 | AE44: -0.48901903 | AF44: 0.366 | AG44: NA | AH44: NA | AI44: NA | AJ44: NA | AK44: NA | AL44: NA | AM44: NA | AS44: Aditya Birla SL CRISIL IBX 60:40 SDL + AAA PSU - Apr 2025 Index Fund-Reg(G) | AT44: 0.35 | AU44: 45716 | AV44: 164.4394 | AX44: 0.005473 | AY44: 0.016243 | AZ44: 0.032896 | BA44: 0.070343 | BB44: 0.056867 | BC44: NA | BD44: NA | BF44: 0.016243 | BG44: 0.073051394 | BH44: 0.069340652 | BI44: 0.01297 | BJ44: NA | BK44: NA | BL44: NA | BM44: NA | BN44: NA | BO44: NA | BP44: NA | BQ44: NA | BR44: NA | BS44: NA | BT44: NA | BU44: NA
B45: Kotak Equity Opp Fund(G) | C45: 1.58 | D45: 45838 | E45: 28294.149 | F45: -0.015459 | G45: 0.069466 | H45: 0.085821 | I45: -0.014114 | J45: 0.199487 | K45: 0.230121 | L45: 0.146777 | N45: 0.018433 | O45: 0.24158789 | P45: 0.29334584 | Q45: 0.069862252 | R45: 0.30418846 | S45: 0.16462733 | T45: 0.13159688 | U45: -0.056165608 | V45: 0.34870651 | W45: 0.095928116 | X45: 0.032707481 | Y45: 0.49945529 | Z45: 0.042334051 | AA45: 0.30142598 | AB45: -0.22847656 | AC45: 0.18498151 | AD45: 0.80128944 | AE45: -0.56772669 | AF45: 0.91013573 | AG45: 0.38704156 | AH45: 0.58736319 | AI45: 0.2883 | AJ45: NA | AK45: NA | AL45: NA | AM45: NA | AS45: Aditya Birla SL CRISIL IBX 60:40 SDL + AAA PSU - Apr 2027 Index Fund-Reg(G) | AT45: 0.32 | AU45: 45716 | AV45: 1684.6227 | AX45: 0.008097 | AY45: 0.02071 | AZ45: 0.036912 | BA45: 0.079396 | BB45: 0.059463 | BC45: NA | BD45: NA | BF45: 0.02071 | BG45: 0.077507346 | BH45: 0.068679827 | BI45: 0.01267 | BJ45: NA | BK45: NA | BL45: NA | BM45: NA | BN45: NA | BO45: NA | BP45: NA | BQ45: NA | BR45: NA | BS45: NA | BT45: NA | BU45: NA
B46: Mirae Asset Emerging Bluechip-Reg(G) | C46: 1.52 | D46: 45838 | E46: 41201.87 | F46: -0.019514 | G46: 0.064122 | H46: 0.085592 | I46: -0.026001 | J46: 0.163582 | K46: 0.220446 | L46: 0.166869 | N46: 0.028941 | O46: 0.15561308 | P46: 0.29340705 | Q46: -0.014481832 | R46: 0.3913142 | S46: 0.2239642 | T46: 0.14716298 | U46: -0.054192383 | V46: 0.4901301 | W46: 0.12165052 | X46: 0.14078645 | Y46: 0.84619461 | Z46: 0.086115108 | AA46: 0.45564981 | AB46: -0.15150169 | AC46: 0.1254 | AD46: NA | AE46: NA | AF46: NA | AG46: NA | AH46: NA | AI46: NA | AJ46: NA | AK46: NA | AL46: NA | AM46: NA | AS46: Aditya Birla SL CRISIL IBX 60:40 SDL + AAA PSU Apr 2026 Index Fund-Reg(G) | AT46: 0.45 | AU46: 45716 | AV46: 52.8246 | AX46: 0.007072 | AY46: 0.01891 | AZ46: 0.035319 | BA46: 0.074483 | BB46: NA | BC46: NA | BD46: NA | BF46: 0.01891 | BG46: 0.074039144 | BH46: 0.067802018 | BI46: 0.00292 | BJ46: NA | BK46: NA | BL46: NA | BM46: NA | BN46: NA | BO46: NA | BP46: NA | BQ46: NA | BR46: NA | BS46: NA | BT46: NA | BU46: NA
B47: Motilal Oswal Large & Midcap Fund-Reg(G) | C47: 1.71 | D47: 45838 | E47: 11816.301 | F47: -0.029309 | G47: 0.125195 | H47: 0.106496 | I47: 0.084857 | J47: 0.287255 | K47: 0.288825 | L47: NA | N47: -0.037926 | O47: 0.46107405 | P47: 0.38047513 | Q47: 0.016579798 | R47: 0.40815649 | S47: 0.12562382 | T47: 0.07002 | U47: NA | V47: NA | W47: NA | X47: NA | Y47: NA | Z47: NA | AA47: NA | AB47: NA | AC47: NA | AD47: NA | AE47: NA | AF47: NA | AG47: NA | AH47: NA | AI47: NA | AJ47: NA | AK47: NA | AL47: NA | AM47: NA | AS47: Aditya Birla SL Nifty SDL Plus PSU Bond Sep 2026 60:40 Index Fund-Reg(G) | AT47: 0.34 | AU47: 45716 | AV47: 9553.9426 | AX47: 0.007877 | AY47: 0.020445 | AZ47: 0.036915 | BA47: 0.078188 | BB47: 0.059025 | BC47: NA | BD47: NA | BF47: 0.020445 | BG47: 0.077044869 | BH47: 0.068236827 | BI47: 0.020746929 | BJ47: 0.00786 | BK47: NA | BL47: NA | BM47: NA | BN47: NA | BO47: NA | BP47: NA | BQ47: NA | BR47: NA | BS47: NA | BT47: NA | BU47: NA
B48: Nippon India Vision Fund(G) | C48: 1.92 | D48: 45838 | E48: 6197.9854 | F48: -0.019363 | G48: 0.041949 | H48: 0.070586 | I48: 0.010001 | J48: 0.21768 | K48: 0.249048 | L48: 0.123305 | N48: 0.0201 | O48: 0.25641708 | P48: 0.34246309 | Q48: 0.024333858 | R48: 0.33778202 | S48: 0.13326272 | T48: 0.055708242 | U48: -0.16945929 | V48: 0.41390655 | W48: 0.039542025 | X48: -0.022318569 | Y48: 0.60431041 | Z48: -0.0030775495 | AA48: 0.29976233 | AB48: -0.28545062 | AC48: 0.15261139 | AD48: 0.82125898 | AE48: -0.51917124 | AF48: 0.56617847 | AG48: 0.45804557 | AH48: 0.53472222 | AI48: 0.19807327 | AJ48: 1.5515829 | AK48: 0.74577373 | AL48: -0.16139586 | AM48: -0.20226185 | AS48: Axis Corp Bond Fund-Reg(G) | AT48: 0.91 | AU48: 45716 | AV48: 6298.5759 | AX48: 0.012837 | AY48: 0.023696 | AZ48: 0.039576 | BA48: 0.083363 | BB48: 0.066278 | BC48: 0.066906 | BD48: NA | BF48: 0.023696 | BG48: 0.080547506 | BH48: 0.067810533 | BI48: 0.03689644 | BJ48: 0.036768624 | BK48: 0.11554401 | BL48: 0.060549566 | BM48: 0.078639569 | BN48: 0.02938 | BO48: NA | BP48: NA | BQ48: NA | BR48: NA | BS48: NA | BT48: NA | BU48: NA
B49: Quant Large & Mid Cap Fund(G) | C49: 1.88 | D49: 45838 | E49: 3840.481 | F49: -0.037538 | G49: 0.022908 | H49: 0.008133 | I49: -0.12968 | J49: 0.189612 | K49: 0.233129 | L49: 0.158011 | N49: -0.021805 | O49: 0.17849755 | P49: 0.32248305 | Q49: 0.12991027 | R49: 0.36843235 | S49: 0.28828939 | T49: 0.032613651 | U49: -0.084490683 | V49: 0.33133395 | W49: 0.13509396 | X49: 0.18720427 | Y49: 0.6467403 | Z49: -0.028335318 | AA49: 0.24416328 | AB49: -0.26872767 | AC49: 0.2855539 | AD49: 0.4446992 | AE49: -0.44282647 | AF49: 0.47166 | AG49: 0 | AH49: NA | AI49: NA | AJ49: NA | AK49: NA | AL49: NA | AM49: NA | AS49: Axis CRISIL IBX 70:30 CPSE Plus SDL April 2025 Index Fund-Reg(G) | AT49: 0.29 | AU49: 45716 | AV49: 463.515 | AX49: 0.00586 | AY49: 0.017259 | AZ49: 0.034818 | BA49: 0.072467 | BB49: 0.056648 | BC49: NA | BD49: NA | BF49: 0.017259 | BG49: 0.074322834 | BH49: 0.069031903 | BI49: 0.01808 | BJ49: NA | BK49: NA | BL49: NA | BM49: NA | BN49: NA | BO49: NA | BP49: NA | BQ49: NA | BR49: NA | BS49: NA | BT49: NA | BU49: NA
B50: SBI Large & Midcap Fund-Reg(G) | C50: 1.58 | D50: 45838 | E50: 33031.135 | F50: -0.009427 | G50: 0.065682 | H50: 0.085126 | I50: 0.02127 | J50: 0.192237 | K50: 0.246868 | L50: 0.141788 | N50: 0.049623 | O50: 0.18042995 | P50: 0.26792765 | Q50: 0.072700548 | R50: 0.39345344 | S50: 0.15756187 | T50: 0.068227156 | U50: -0.052504277 | V50: 0.40457244 | W50: 0.0042386426 | X50: 0.11053028 | Y50: 0.482552 | Z50: 0.10538593 | AA50: 0.32468708 | AB50: -0.25752995 | AC50: 0.19302698 | AD50: 0.8752505 | AE50: -0.5519138 | AF50: 0.64889876 | AG50: 0.49833611 | AH50: 0.70174611 | AI50: 0.29429239 | AJ50: 1.1760479 | AK50: -0.022248244 | AL50: -0.41586867 | AM50: -0.51205049 | AN50: 0.82 | AO50: 0.86 | AP50: 24.05 | AQ50: 3.61 | AS50: Bandhan Corp Bond Fund-Reg(G) | AT50: 0.65 | AU50: 45716 | AV50: 13995.734 | AX50: 0.01226 | AY50: 0.022817 | AZ50: 0.038924 | BA50: 0.082463 | BB50: 0.061241 | BC50: 0.064145 | BD50: NA | BF50: 0.022817 | BG50: 0.076731659 | BH50: 0.068011556 | BI50: 0.02626732 | BJ50: 0.036671124 | BK50: 0.11563126 | BL50: 0.084808812 | BM50: 0.06339421 | BN50: 0.061706286 | BO50: 0.10005 | BP50: NA | BQ50: NA | BR50: NA | BS50: NA | BT50: NA | BU50: NA
B51: Tata Large & Mid Cap Fund(G) | C51: 1.74 | D51: 45838 | E51: 8886.8832 | F51: -0.013422 | G51: 0.048437 | H51: 0.075309 | I51: -0.02183 | J51: 0.171726 | K51: 0.209077 | L51: 0.129751 | N51: 0.02572 | O51: 0.15527193 | P51: 0.22883474 | Q51: 0.11205504 | R51: 0.28526255 | S51: 0.1548703 | T51: 0.13873429 | U51: -0.053152592 | V51: 0.31938518 | W51: 0.015272854 | X51: 0.065717248 | Y51: 0.48540867 | Z51: 0.086936625 | AA51: 0.33718917 | AB51: -0.23033852 | AC51: 0.098149213 | AD51: 0.95121263 | AE51: -0.60914455 | AF51: 0.76355287 | AG51: 0.37952404 | AH51: 0.51171125 | AI51: 0.29857782 | AJ51: 1.6508615 | AK51: 0.17953578 | AL51: -0.29797339 | AM51: -0.011133603 | AS51: Baroda BNP Paribas Corp Bond Fund(G) | AT51: 0.58 | AU51: 45716 | AV51: 210.0986 | AX51: 0.014595 | AY51: 0.02542 | AZ51: 0.040426 | BA51: 0.085741 | BB51: 0.062594 | BC51: 0.058543 | BD51: 0.059602 | BF51: 0.02542 | BG51: 0.083050167 | BH51: 0.069732537 | BI51: 0.015991327 | BJ51: 0.02208695 | BK51: 0.099287877 | BL51: 0.0086047377 | BM51: 0.052498578 | BN51: 0.066720846 | BO51: 0.10752068 | BP51: 0.072319456 | BQ51: 0.10767713 | BR51: 0.071395154 | BS51: 0.095071947 | BT51: 0.09115005 | BU51: NA
B52: UTI Core Equity Fund-Reg(G) | C52: 1.92 | D52: 45838 | E52: 4866.1141 | F52: -0.029695 | G52: 0.04598 | H52: 0.058835 | I52: -0.006067 | J52: 0.222354 | K52: 0.260465 | L52: 0.133206 | N52: 0.013978 | O52: 0.27197655 | P52: 0.34434345 | Q52: 0.045752922 | R52: 0.40759911 | S52: 0.12803468 | T52: 0.014509413 | U52: -0.079477437 | V52: 0.35226589 | W52: 0.033940779 | X52: 0.0047422593 | Y52: 0.41698733 | Z52: 0.062628882 | AA52: 0.22614841 | AB52: -0.16161949 | AC52: 0.12894835 | AD52: 0.24583333 | AE52: NA | AF52: NA | AG52: NA | AH52: NA | AI52: NA | AJ52: NA | AK52: NA | AL52: NA | AM52: NA | AS52: Canara Rob Corp Bond Fund-Reg(G) | AT52: 1.03 | AU52: 45716 | AV52: 119.592 | AX52: 0.013939 | AY52: 0.021185 | AZ52: 0.035048 | BA52: 0.077088 | BB52: 0.059001 | BC52: 0.057425 | BD52: 0.065294 | BF52: 0.021185 | BG52: 0.075062822 | BH52: 0.060191012 | BI52: 0.029017845 | BJ52: 0.028341318 | BK52: 0.095824726 | BL52: 0.094093008 | BM52: 0.052901235 | BN52: 0.053395379 | BO52: 0.095681683 | BP52: 0.07602133 | BQ52: 0.1064 | BR52: NA | BS52: NA | BT52: NA | BU52: NA
B53: S&P BSE 200 | F53: -0.02971 | G53: 0.026524 | H53: 0.054662 | I53: -0.02863 | J53: 0.145994 | K53: 0.192965 | L53: 0.120911 | N53: 0.02902 | O53: 0.13404855 | P53: 0.22758307 | Q53: 0.041838106 | R53: 0.27591601 | S53: 0.16312687 | T53: 0.091274003 | U53: -0.0053816528 | V53: 0.3326099 | W53: 0.039538003 | X53: -0.014754572 | Y53: 0.35466573 | Z53: 0.043805014 | AA53: 0.30984553 | AB53: -0.26954892 | AC53: 0.16220617 | AD53: 0.88506731 | AE53: -0.56462214 | AF53: 0.60443065 | AG53: 0.39580014 | AH53: 0.33802944 | AI53: 0.15690778 | AJ53: 0.9447518 | AK53: 0.15469597 | AL53: -0.2193755 | AM53: -0.26205709 | AS53: DSP Corp Bond Fund-Reg(G) | AT53: 0.55 | AU53: 45716 | AV53: 2762.5762 | AX53: 0.009715 | AY53: 0.020621 | AZ53: 0.03753 | BA53: 0.077875 | BB53: 0.057425 | BC53: 0.057625 | BD53: NA | BF53: 0.020621 | BG53: 0.076779475 | BH53: 0.064874272 | BI53: 0.020876411 | BJ53: 0.033961786 | BK53: 0.093875324 | BL53: 0.11104588 | BM53: 0.03912 | BN53: NA | BO53: NA | BP53: NA | BQ53: NA | BR53: NA | BS53: NA | BT53: NA | BU53: NA
B54: Category Average | F54: =AVERAGE(F34:F52) -> -0.022661053 | G54: =AVERAGE(G34:G52) -> 0.060852579 | H54: =AVERAGE(H34:H52) -> 0.074302211 | I54: =AVERAGE(I34:I52) -> -0.00265 | J54: =AVERAGE(J34:J52) -> 0.20191268 | K54: =AVERAGE(K34:K52) -> 0.23978868 | L54: =AVERAGE(L34:L52) -> 0.14081644 | N54: =AVERAGE(N34:N52) -> 0.014052158 | O54: =AVERAGE(O34:O52) -> 0.24697373 | P54: =AVERAGE(P34:P52) -> 0.30744942 | Q54: =(AVERAGE(Q34:Q52)) -> 0.025091506 | R54: =(AVERAGE(R34:R52)) -> 0.3685969 | S54: =(AVERAGE(S34:S52)) -> 0.1647569 | T54: =(AVERAGE(T34:T52)) -> 0.081986592 | U54: =(AVERAGE(U34:U52)) -> -0.064138306 | V54: =(AVERAGE(V34:V52)) -> 0.37838696 | W54: =(AVERAGE(W34:W52)) -> 0.06047275 | X54: =(AVERAGE(X34:X52)) -> 0.052822466 | ... AM54: =(AVERAGE(AM34:AM52)) -> -0.28154167 | AS54: Edelweiss CRISIL PSU Plus SDL 50:50 Oct 2025 Index Fund-Reg(G) | AT54: 0.4 | AU54: 45716 | AV54: 811.1993 | AX54: 0.006477 | AY54: 0.017755 | AZ54: 0.034464 | BA54: 0.072948 | BB54: 0.057227 | BC54: NA | BD54: NA | BF54: 0.017755 | BG54: 0.073944148 | BH54: 0.06839734 | BI54: 0.01656 | BJ54: NA | BK54: NA | BL54: NA | BM54: NA | BN54: NA | BO54: NA | BP54: NA | BQ54: NA | BR54: NA | BS54: NA | BT54: NA | BU54: NA
AS55: Edelweiss Nifty PSU Bond Plus SDL Apr 2026 50:50 Index Fund-Reg(G) | AT55: 0.4 | AU55: 45716 | AV55: 7734.4343 | AX55: 0.007791 | AY55: 0.019552 | AZ55: 0.036498 | BA55: 0.075625 | BB55: 0.058029 | BC55: NA | BD55: NA | BF55: 0.019552 | BG55: 0.075079817 | BH55: 0.068012165 | BI55: 0.020521405 | BJ55: 0.06328 | BK55: NA | BL55: NA | BM55: NA | BN55: NA | BO55: NA | BP55: NA | BQ55: NA | BR55: NA | BS55: NA | BT55: NA | BU55: NA
AS56: Edelweiss Nifty PSU Bond Plus SDL Apr 2027 50:50 Index Fund-Reg(G) | AT56: 0.4 | AU56: 45716 | AV56: 2298.6091 | AX56: 0.009151 | AY56: 0.020833 | AZ56: 0.036937 | BA56: 0.080088 | BB56: 0.058804 | BC56: NA | BD56: NA | BF56: 0.020833 | BG56: 0.079038582 | BH56: 0.066531476 | BI56: 0.023191168 | BJ56: 0.00728 | BK56: NA | BL56: NA | BM56: NA | BN56: NA | BO56: NA | BP56: NA | BQ56: NA | BR56: NA | BS56: NA | BT56: NA | BU56: NA
B57: Multi-Cap / Flexi Cap | C57: Expense Ratio | D57: Corpus | F57: Returns | N57: CY Year Returns | AS57: Franklin India Corp Debt Fund-A(G) | AT57: 0.83 | AU57: 45716 | AV57: 753.55522 | AX57: 0.010832 | AY57: 0.020274 | AZ57: 0.038348 | BA57: 0.079153 | BB57: 0.061705 | BC57: 0.060674 | BD57: 0.070892 | BF57: 0.020274 | BG57: 0.076276053 | BH57: 0.065460472 | BI57: 0.031685479 | BJ57: 0.037789906 | BK57: 0.0902481 | BL57: 0.092090063 | BM57: 0.074973789 | BN57: 0.076665895 | BO57: 0.089858786 | BP57: 0.084309243 | BQ57: 0.12982305 | BR57: 0.07535429 | BS57: 0.11975395 | BT57: 0.098617354 | BU57: 0.048367212
D58: Month End | E58: AUM (Cr.) | F58: 1 month | G58: 3 months | H58: 6 months | I58: 1 Year | J58: 3 Year | K58: 5 Year | L58: 10 Year | N58: CY 2025 | O58: 2024 | P58: 2023 | Q58: 2022 | R58: 2021 | S58: 2020 | T58: 2019 | U58: 2018 | V58: 2017 | W58: 2016 | X58: 2015 | Y58: 2014 | Z58: 2013 | AA58: 2012 | AB58: 2011 | AC58: 2010 | AD58: 2009 | AE58: 2008 | AF58: 2007 | AG58: 2006 | AH58: 2005 | AI58: 2004 | AJ58: 2003 | AK58: 2002 | AL58: 2001 | AM58: 2000 | AS58: HDFC Corp Bond Fund(G) | AT58: 0.59 | AU58: 45716 | AV58: 32190.898 | AX58: 0.013466 | AY58: 0.023216 | AZ58: 0.039394 | BA58: 0.086256 | BB58: 0.068271 | BC58: 0.068138 | BD58: 0.076814 | BF58: 0.023216 | BG58: 0.085567481 | BH58: 0.072037699 | BI58: 0.032674845 | BJ58: 0.039047119 | BK58: 0.11811465 | BL58: 0.10323235 | BM58: 0.064936501 | BN58: 0.065132014 | BO58: 0.10634679 | BP58: 0.086110886 | BQ58: 0.10947224 | BR58: 0.0755567 | BS58: 0.1048557 | BT58: 0.086782647 | BU58: 0.03523
B59: Aditya Birla SL Flexi Cap Fund(G) | C59: 1.66 | D59: 45838 | E59: 23606.242 | F59: -0.025144 | G59: 0.03614 | H59: 0.080411 | I59: 0.017159 | J59: 0.177161 | K59: 0.209698 | L59: 0.133877 | N59: 0.04068 | O59: 0.18520581 | P59: 0.25954406 | Q59: -0.011090012 | R59: 0.30275509 | S59: 0.16072061 | T59: 0.085339822 | U59: -0.040917156 | V59: 0.33511908 | W59: 0.15214562 | X59: 0.029324689 | Y59: 0.56609584 | Z59: 0.071123033 | AA59: 0.35737834 | AB59: -0.29377628 | AC59: 0.14158204 | AD59: 0.89249249 | AE59: -0.56620856 | AF59: 0.69909252 | AG59: 0.42839077 | AH59: 0.54292683 | AI59: 0.4413781 | AJ59: 1.1872357 | AK59: 0.088740059 | AL59: -0.27737447 | AM59: -0.17781646 | AS59: HSBC Corporate Bond Fund-Reg(G) | AT59: 0.64 | AU59: 45716 | AV59: 5875.9179 | AX59: 0.012565 | AY59: 0.022828 | AZ59: 0.037747 | BA59: 0.081889 | BB59: 0.061597 | BC59: 0.062108 | BD59: 0.069227 | BF59: 0.022828 | BG59: 0.08066701 | BH59: 0.064494918 | BI59: 0.022194445 | BJ59: 0.037639577 | BK59: 0.12387972 | BL59: 0.12618116 | BM59: 0.060028565 | BN59: 0.01593485 | BO59: 0.12445346 | BP59: 0.044791661 | BQ59: 0.12583708 | BR59: 0.039336681 | BS59: 0.10158466 | BT59: 0.064735101 | BU59: 0.036670795
B60: Axis Flexi Cap Fund-Reg(G) | C60: 1.72 | D60: 45838 | E60: 13316.498 | F60: -0.015096 | G60: 0.067438 | H60: 0.086957 | I60: 0.026477 | J60: 0.148445 | K60: 0.17536 | L60: NA | N60: 0.020992 | O60: 0.22315593 | P60: 0.2020202 | Q60: -0.087090164 | R60: 0.28336621 | S60: 0.19294118 | T60: 0.171875 | U60: 0.070866142 | V60: 0.016 | W60: NA | X60: NA | Y60: NA | Z60: NA | AA60: NA | AB60: NA | AC60: NA | AD60: NA | AE60: NA | AF60: NA | AG60: NA | AH60: NA | AI60: NA | AJ60: NA | AK60: NA | AL60: NA | AM60: NA | AS60: ICICI Pru Corp Bond Fund(G) | AT60: 0.58 | AU60: 45716 | AV60: 29545.488 | AX60: 0.0117 | AY60: 0.022751 | AZ60: 0.041033 | BA60: 0.08302 | BB60: 0.072439 | BC60: 0.06977 | BD60: 0.075591 | BF60: 0.022751 | BG60: 0.080312421 | BH60: 0.07602151 | BI60: 0.044650989 | BJ60: 0.041172248 | BK60: 0.10446855 | BL60: 0.098945364 | BM60: 0.064198393 | BN60: 0.062597685 | BO60: 0.098315432 | BP60: 0.088007442 | BQ60: 0.094076489 | BR60: 0.084757165 | BS60: 0.0904585 | BT60: -0.0086339521 | BU60: 0.053225442
B61: Bandhan Flexi Cap Fund-Reg(G) | C61: 1.86 | D61: 45838 | E61: 7606.9856 | F61: -0.019892 | G61: 0.043397 | H61: 0.07561 | I61: 0.003622 | J61: 0.158939 | K61: 0.196968 | L61: 0.104684 | N61: 0.049205 | O61: 0.14931051 | P61: 0.24458189 | Q61: -0.013892464 | R61: 0.32230311 | S61: 0.098224483 | T61: 0.075848972 | U61: -0.087533394 | V61: 0.38043177 | W61: -0.026963419 | X61: 0.082897445 | Y61: 0.58905891 | Z61: 0.056247076 | AA61: 0.40840095 | AB61: -0.17997333 | AC61: 0.32071876 | AD61: 1.0211899 | AE61: -0.53142469 | AF61: 1.1047403 | AG61: 0.31901198 | AH61: 0.002 | AI61: NA | AJ61: NA | AK61: NA | AL61: NA | AM61: NA | AS61: ICICI Pru Nifty PSU Bond Plus SDL Sep 2027 40:60 Index Fund-Reg(G) | AT61: 0.39 | AU61: 45716 | AV61: 8996.0986 | AX61: 0.008397 | AY61: 0.021244 | AZ61: 0.036143 | BA61: 0.081541 | BB61: 0.059217 | BC61: NA | BD61: NA | BF61: 0.021244 | BG61: 0.080360568 | BH61: 0.066309588 | BI61: 0.019094689 | BJ61: 0.00761 | BK61: NA | BL61: NA | BM61: NA | BN61: NA | BO61: NA | BP61: NA | BQ61: NA | BR61: NA | BS61: NA | BT61: NA | BU61: NA
B62: Canara Rob Flexi Cap Fund-Reg(G) | C62: 1.69 | D62: 45838 | E62: 13588.065 | F62: -0.017894 | G62: 0.060958 | H62: 0.086959 | I62: 0.017704 | J62: 0.159507 | K62: 0.195921 | L62: 0.129733 | N62: 0.040743 | O62: 0.17878164 | P62: 0.2283978 | Q62: -0.016662305 | R62: 0.32612217 | S62: 0.22228507 | T62: 0.12280702 | U62: 0.0088091615 | V62: 0.37764784 | W62: -0.019684188 | X62: 0.00075765776 | Y62: 0.39709663 | Z62: 0.043059937 | AA62: 0.31317316 | AB62: -0.15859184 | AC62: 0.20672976 | AD62: 0.92978896 | AE62: -0.50837989 | AF62: 0.6341702 | AG62: 0.31349036 | AH62: 0.37030516 | AI62: 0.17598344 | AJ62: 0.449 | AK62: NA | AL62: NA | AM62: NA | AS62: Invesco India Corporate Bond Fund(G) | AT62: 0.68 | AU62: 45716 | AV62: 5903.2528 | AX62: 0.013233 | AY62: 0.023692 | AZ62: 0.038549 | BA62: 0.083595 | BB62: 0.063528 | BC62: 0.06275 | BD62: 0.065949 | BF62: 0.023692 | BG62: 0.080860665 | BH62: 0.066850391 | BI62: 0.028605136 | BJ62: 0.033669919 | BK62: 0.101201 | BL62: 0.11069603 | BM62: 0.039582152 | BN62: 0.01840432 | BO62: 0.14139935 | BP62: 0.05151643 | BQ62: 0.099437033 | BR62: 0.055973557 | BS62: 0.10459783 | BT62: 0.091893127 | BU62: 0.061379214
B63: DSP Flexi Cap Fund-Reg(G) | C63: 1.72 | D63: 45838 | E63: 12187.762 | F63: -0.029292 | G63: 0.038066 | H63: 0.064362 | I63: -0.013801 | J63: 0.173503 | K63: 0.206678 | L63: 0.133929 | N63: 0.011937 | O63: 0.18161036 | P63: 0.32193595 | Q63: -0.045370054 | R63: 0.32430729 | S63: 0.18736847 | T63: 0.17042065 | U63: -0.074891764 | V63: 0.4004042 | W63: 0.040507637 | X63: -0.0074334468 | Y63: 0.5300874 | Z63: 0.00072890384 | AA63: 0.33256127 | AB63: -0.23889679 | AC63: 0.19821477 | AD63: 0.9067169 | AE63: -0.49715816 | AF63: 0.5307 | AG63: NA | AH63: NA | AI63: NA | AJ63: NA | AK63: NA | AL63: NA | AM63: NA | AS63: Kotak Corporate Bond Fund(G) | AT63: 0.67 | AU63: 45716 | AV63: 14448.901 | AX63: 0.012135 | AY63: 0.023207 | AZ63: 0.038869 | BA63: 0.084885 | BB63: 0.067231 | BC63: 0.065053 | BD63: 0.073557 | BF63: 0.023207 | BG63: 0.082762836 | BH63: 0.068689475 | BI63: 0.036727274 | BJ63: 0.037640313 | BK63: 0.096572176 | BL63: 0.096155634 | BM63: 0.074670234 | BN63: 0.068955652 | BO63: 0.093661844 | BP63: 0.088212283 | BQ63: 0.11305716 | BR63: 0.06224116 | BS63: 0.093551398 | BT63: 0.089352655 | BU63: 0.054196614
B64: Edelweiss Flexi Cap Fund-Reg(G) | C64: 1.92 | D64: 45838 | E64: 2801.601 | F64: -0.031157 | G64: 0.036603 | H64: 0.051805 | I64: -0.024848 | J64: 0.186493 | K64: 0.2223 | L64: 0.135288 | N64: -0.010754 | O64: 0.25380156 | P64: 0.29294097 | Q64: 0.0068138692 | R64: 0.34696486 | S64: 0.14370183 | T64: 0.083813364 | U64: -0.04915788 | V64: 0.47371607 | W64: 0.0038488808 | X64: -0.0127 | Y64: NA | Z64: NA | AA64: NA | AB64: NA | AC64: NA | AD64: NA | AE64: NA | AF64: NA | AG64: NA | AH64: NA | AI64: NA | AJ64: NA | AK64: NA | AL64: NA | AM64: NA | AS64: Kotak Nifty AAA Bond Jun 2025 HTM Index Fund-Reg(G) | AT64: 0.23 | AU64: 45716 | AV64: 381.4238 | AX64: 0.006923 | AY64: 0.019301 | AZ64: 0.037709 | BA64: 0.075367 | BB64: NA | BC64: NA | BD64: NA | BF64: 0.019301 | BG64: 0.05589 | BH64: NA | BI64: NA | BJ64: NA | BK64: NA | BL64: NA | BM64: NA | BN64: NA | BO64: NA | BP64: NA | BQ64: NA | BR64: NA | BS64: NA | BT64: NA | BU64: NA
B65: Franklin India Flexi Cap Fund(G) | C65: 1.69 | D65: 45838 | E65: 19364.973 | F65: -0.023703 | G65: 0.030195 | H65: 0.066194 | I65: -0.001094 | J65: 0.203466 | K65: 0.251147 | L65: 0.134991 | N65: 0.012143 | O65: 0.21752757 | P65: 0.30752935 | Q65: 0.053438978 | R65: 0.40308149 | S65: 0.15978341 | T65: 0.033437034 | U65: -0.043769665 | V65: 0.30633988 | W65: 0.04981955 | X65: 0.04377962 | Y65: 0.56791215 | Z65: 0.055472336 | AA65: 0.3103752 | AB65: -0.16421365 | AC65: 0.19481523 | AD65: 0.73098438 | AE65: -0.47705941 | AF65: 0.54902349 | AG65: 0.49359253 | AH65: 0.47611414 | AI65: 0.27150428 | AJ65: 1.0726658 | AK65: 0.19364599 | AL65: -0.054363376 | AM65: -0.31893472 | AS65: Kotak Nifty SDL Apr 2027 Top 12 Equal Weight Index Fund-Reg(G) | AT65: 0.35 | AU65: 45716 | AV65: 7712.2374 | AX65: 0.006611 | AY65: 0.020229 | AZ65: 0.036099 | BA65: 0.082662 | BB65: 0.060695 | BC65: NA | BD65: NA | BF65: 0.020229 | BG65: 0.081389889 | BH65: 0.06923607 | BI65: 0.0158 | BJ65: NA | BK65: NA | BL65: NA | BM65: NA | BN65: NA | BO65: NA | BP65: NA | BQ65: NA | BR65: NA | BS65: NA | BT65: NA | BU65: NA
B66: HDFC Flexi Cap Fund(G) | C66: 1.38 | D66: 45838 | E66: 79584.535 | F66: -0.014808 | G66: 0.025105 | H66: 0.085334 | I66: 0.057026 | J66: 0.233427 | K66: 0.286401 | L66: 0.151524 | N66: 0.05882 | O66: 0.23479209 | P66: 0.30604793 | Q66: 0.1829066 | R66: 0.36173937 | S66: 0.06438026 | T66: 0.068285741 | U66: -0.03533426 | V66: 0.36857081 | W66: 0.072641191 | X66: -0.05086895 | Y66: 0.53772092 | Z66: 0.038197284 | AA66: 0.34144658 | AB66: -0.26721519 | AC66: 0.29215618 | AD66: 1.0556698 | AE66: -0.49679837 | AF66: 0.53607638 | AG66: 0.35863339 | AH66: 0.62704314 | AI66: 0.27526031 | AJ66: 1.2629662 | AK66: 0.24196185 | AL66: -0.028072034 | AM66: -0.2 | AS66: Kotak Nifty SDL Apr 2032 Top 12 Equal Weight Index Fund-Reg(G) | AT66: 0.36 | AU66: 45716 | AV66: 2919.2551 | AX66: 0.014651 | AY66: 0.02589 | AZ66: 0.041602 | BA66: 0.093918 | BB66: 0.074476 | BC66: NA | BD66: NA | BF66: 0.02589 | BG66: 0.09923934 | BH66: 0.071550702 | BI66: 0.02934 | BJ66: NA | BK66: NA | BL66: NA | BM66: NA | BN66: NA | BO66: NA | BP66: NA | BQ66: NA | BR66: NA | BS66: NA | BT66: NA | BU66: NA
B67: HSBC Flexi Cap Fund-Reg(G) | C67: 1.92 | D67: 45838 | E67: 5169.21 | F67: -0.020644 | G67: 0.075081 | H67: 0.076128 | I67: 0.001079 | J67: 0.202881 | K67: 0.223342 | L67: 0.125926 | N67: -0.005231 | O67: 0.28620453 | P67: 0.31783047 | Q67: -0.046152281 | R67: 0.33936391 | S67: 0.15998351 | T67: 0.061717319 | U67: -0.10603981 | V67: 0.40269855 | W67: 0.055825063 | X67: -0.020956607 | Y67: 0.54769564 | Z67: 0.080021704 | AA67: 0.25035652 | AB67: -0.18660173 | AC67: 0.15742524 | AD67: 0.60059455 | AE67: -0.54564478 | AF67: 0.50993163 | AG67: 0.51712596 | AH67: 0.43730558 | AI67: 0.34693 | AJ67: NA | AK67: NA | AL67: NA | AM67: NA | AS67: Kotak Nifty SDL Plus AAA PSU Bond Jul 2028 60:40 Index Fund-Reg(G) | AT67: 0.4 | AU67: 45716 | AV67: 586.4315 | AX67: 0.008086 | AY67: 0.021778 | AZ67: 0.036588 | BA67: 0.082668 | BB67: NA | BC67: NA | BD67: NA | BF67: 0.021778 | BG67: 0.081406657 | BH67: 0.06845206 | BI67: 0.02013 | BJ67: NA | BK67: NA | BL67: NA | BM67: NA | BN67: NA | BO67: NA | BP67: NA | BQ67: NA | BR67: NA | BS67: NA | BT67: NA | BU67: NA
B68: ICICI Pru Flexicap Fund(G) | C68: 1.69 | D68: 45838 | E68: 17945.864 | F68: -0.003215 | G68: 0.065903 | H68: 0.075145 | I68: -0.004815 | J68: 0.187917 | K68: NA | L68: NA | N68: 0.0299 | O68: 0.21208054 | P68: 0.27896996 | Q68: 0.087768441 | R68: 0.071 | S68: NA | T68: NA | U68: NA | V68: NA | W68: NA | X68: NA | Y68: NA | Z68: NA | AA68: NA | AB68: NA | AC68: NA | AD68: NA | AE68: NA | AF68: NA | AG68: NA | AH68: NA | AI68: NA | AJ68: NA | AK68: NA | AL68: NA | AM68: NA | AS68: Mirae Asset Corp Bond Fund-Reg(G) | AT68: 0.63 | AU68: 45716 | AV68: 40.969872 | AX68: 0.012749 | AY68: 0.022057 | AZ68: 0.039393 | BA68: 0.081465 | BB68: 0.06159 | BC68: NA | BD68: NA | BF68: 0.022057 | BG68: 0.080069303 | BH68: 0.062734267 | BI68: 0.028462943 | BJ68: 0.03503 | BK68: NA | BL68: NA | BM68: NA | BN68: NA | BO68: NA | BP68: NA | BQ68: NA | BR68: NA | BS68: NA | BT68: NA | BU68: NA
B69: Invesco India Flexi Cap Fund-Reg(G) | C69: 1.92 | D69: 45838 | E69: 3266.8754 | F69: -0.016079 | G69: 0.09023 | H69: 0.108708 | I69: 0.06573 | J69: 0.235139 | K69: NA | L69: NA | N69: 0.004235 | O69: 0.34448399 | P69: 0.33555133 | Q69: 0.052 | R69: NA | S69: NA | T69: NA | U69: NA | V69: NA | W69: NA | X69: NA | Y69: NA | Z69: NA | AA69: NA | AB69: NA | AC69: NA | AD69: NA | AE69: NA | AF69: NA | AG69: NA | AH69: NA | AI69: NA | AJ69: NA | AK69: NA | AL69: NA | AM69: NA | AS69: Mirae Asset Nifty AAA PSU Bond Plus SDL Apr 2026 50:50 Index Fund-Reg(G) | AT69: 0.31 | AU69: 45716 | AV69: 94.163144 | AX69: 0.007721 | AY69: 0.019679 | AZ69: 0.036516 | BA69: 0.07582 | BB69: NA | BC69: NA | BD69: NA | BF69: 0.019679 | BG69: 0.075596805 | BH69: 0.067331007 | BI69: 0.01454 | BJ69: NA | BK69: NA | BL69: NA | BM69: NA | BN69: NA | BO69: NA | BP69: NA | BQ69: NA | BR69: NA | BS69: NA | BT69: NA | BU69: NA
B70: Kotak Flexicap Fund(G) | C70: 1.45 | D70: 45838 | E70: 54840.977 | F70: -0.028541 | G70: 0.056688 | H70: 0.091275 | I70: 0.003181 | J70: 0.178964 | K70: 0.199253 | L70: 0.133756 | N70: 0.061932 | O70: 0.16503447 | P70: 0.24203196 | Q70: 0.049978046 | R70: 0.2537217 | S70: 0.11788313 | T70: 0.12280702 | U70: -0.0088137208 | V70: 0.34309138 | W70: 0.094406513 | X70: 0.029560202 | Y70: 0.57871523 | Z70: 0.061306153 | AA70: 0.33450882 | AB70: -0.22290949 | AC70: 0.20048877 | AD70: 0.0639 | AE70: NA | AF70: NA | AG70: NA | AH70: NA | AI70: NA | AJ70: NA | AK70: NA | AL70: NA | AM70: NA | AS70: Nippon India Corp Bond Fund(G) | AT70: 0.74 | AU70: 45716 | AV70: 6497.7632 | AX70: 0.013364 | AY70: 0.023977 | AZ70: 0.040005 | BA70: 0.085928 | BB70: 0.0706 | BC70: 0.068045 | BD70: 0.073243 | BF70: 0.023977 | BG70: 0.084402794 | BH70: 0.071488438 | BI70: 0.043224487 | BJ70: 0.047116566 | BK70: 0.095196706 | BL70: 0.077793042 | BM70: 0.068899257 | BN70: 0.06615097 | BO70: 0.091285699 | BP70: 0.086879477 | BQ70: 0.092559888 | BR70: 0.084570087 | BS70: 0.097780927 | BT70: 0.091610875 | BU70: 0.055471032
B71: Motilal Oswal Flexi Cap Fund-Reg(G) | C71: 1.71 | D71: 45838 | E71: 13893.764 | F71: -0.028643 | G71: 0.0799 | H71: 0.090446 | I71: 0.067212 | J71: 0.24413 | K71: 0.198776 | L71: 0.128169 | N71: -0.033758 | O71: 0.45690986 | P71: 0.30986172 | Q71: -0.029780178 | R71: 0.15304472 | S71: 0.10299035 | T71: 0.079231755 | U71: -0.078483927 | V71: 0.43052489 | W71: 0.084526031 | X71: 0.14598626 | Y71: 0.53398 | Z71: NA | AA71: NA | AB71: NA | AC71: NA | AD71: NA | AE71: NA | AF71: NA | AG71: NA | AH71: NA | AI71: NA | AJ71: NA | AK71: NA | AL71: NA | AM71: NA | AS71: Nippon India CRISIL-IBX AAA Financial Services - Dec 2026 Index Fund-Reg(G) | AT71: 0.32 | AU71: 45716 | AV71: 71.794 | AX71: 0.00851 | AY71: 0.019745 | AZ71: NA | BA71: NA | BB71: NA | BC71: NA | BD71: NA | BF71: 0.019745 | BG71: 0.01343 | BH71: NA | BI71: NA | BJ71: NA | BK71: NA | BL71: NA | BM71: NA | BN71: NA | BO71: NA | BP71: NA | BQ71: NA | BR71: NA | BS71: NA | BT71: NA | BU71: NA
B72: Nippon India Flexi Cap Fund-Reg(G) | C72: 1.72 | D72: 45838 | E72: 9299.746 | F72: -0.02066 | G72: 0.0462 | H72: 0.058224 | I72: -0.042921 | J72: 0.161616 | K72: NA | L72: NA | N72: -0.000801 | O72: 0.15422499 | P72: 0.33108915 | Q72: -0.0086250728 | R72: 0.08173 | S72: NA | T72: NA | U72: NA | V72: NA | W72: NA | X72: NA | Y72: NA | Z72: NA | AA72: NA | AB72: NA | AC72: NA | AD72: NA | AE72: NA | AF72: NA | AG72: NA | AH72: NA | AI72: NA | AJ72: NA | AK72: NA | AL72: NA | AM72: NA | AS72: Nippon India CRISIL-IBX AAA Financial Services - Jan 2028 Index Fund-Reg(G) | AT72: 0.35 | AU72: 45716 | AV72: 139.0506 | AX72: 0.009253 | AY72: 0.021313 | AZ72: NA | BA72: NA | BB72: NA | BC72: NA | BD72: NA | BF72: 0.021313 | BG72: 0.01347 | BH72: NA | BI72: NA | BJ72: NA | BK72: NA | BL72: NA | BM72: NA | BN72: NA | BO72: NA | BP72: NA | BQ72: NA | BR72: NA | BS72: NA | BT72: NA | BU72: NA
B73: Nippon India Multi Cap Fund(G) | C73: 1.52 | D73: 45838 | E73: 45366.089 | F73: -0.011124 | G73: 0.084613 | H73: 0.105766 | I73: 0.008236 | J73: 0.246716 | K73: 0.318071 | L73: 0.145514 | N73: 0.03611 | O73: 0.25822018 | P73: 0.38130297 | Q73: 0.14122571 | R73: 0.48913349 | S73: 0.00037737007 | T73: 0.021980813 | U73: -0.021944154 | V73: 0.40866926 | W73: -0.066683153 | X73: 0.0051047425 | Y73: 0.59672326 | Z73: 0.045584425 | AA73: 0.47353467 | AB73: -0.21632039 | AC73: 0.3045174 | AD73: 1.0875217 | AE73: -0.55872642 | AF73: 0.47322487 | AG73: 0.51279852 | AH73: 0.43376 | AI73: NA | AJ73: NA | AK73: NA | AL73: NA | AM73: NA | AN73: 1.1 | AO73: 0.87 | AP73: 28.9 | AQ73: 3.97 | AS73: Nippon India Nifty AAA CPSE Bond Plus SDL - Apr 2027 Maturity 60:40 Index Fund(G) | AT73: 0.31 | AU73: 45716 | AV73: 3451.0384 | AX73: 0.008818 | AY73: 0.020747 | AZ73: 0.037443 | BA73: 0.079188 | BB73: 0.057972 | BC73: NA | BD73: NA | BF73: 0.020747 | BG73: 0.078630974 | BH73: 0.066008393 | BI73: 0.010688196 | BJ73: NA | BK73: NA | BL73: NA | BM73: NA | BN73: NA | BO73: NA | BP73: NA | BQ73: NA | BR73: NA | BS73: NA | BT73: NA | BU73: NA
B74: Parag Parikh Flexi Cap Fund-Reg(G) | C74: 1.28 | D74: 45838 | E74: 110392.32 | F74: -0.008539 | G74: 0.052609 | H74: 0.050593 | I74: 0.078166 | J74: 0.216301 | K74: 0.236511 | L74: 0.173728 | N74: 0.047122 | O74: 0.2391628 | P74: 0.36572718 | Q74: -0.07229246 | R74: 0.45512008 | S74: 0.32294735 | T74: 0.1443386 | U74: -0.0043033774 | V74: 0.29364672 | W74: 0.032752697 | X74: 0.089393902 | Y74: 0.44821014 | Z74: 0.11248012 | AA74: NA | AB74: NA | AC74: NA | AD74: NA | AE74: NA | AF74: NA | AG74: NA | AH74: NA | AI74: NA | AJ74: NA | AK74: NA | AL74: NA | AM74: NA | AN74: 1.22 | AO74: 0.62 | AP74: 17.67 | AQ74: 3.29 | AS74: Nippon India Nifty AAA PSU Bond Plus SDL - Sep 2026 Maturity 50:50 Index Fund-Reg(G) | AT74: 0.38 | AU74: 45716 | AV74: 426.3721 | AX74: 0.007969 | AY74: 0.019587 | AZ74: 0.036285 | BA74: 0.076558 | BB74: NA | BC74: NA | BD74: NA | BF74: 0.019587 | BG74: 0.076820788 | BH74: 0.066601661 | BI74: 0.01529 | BJ74: NA | BK74: NA | BL74: NA | BM74: NA | BN74: NA | BO74: NA | BP74: NA | BQ74: NA | BR74: NA | BS74: NA | BT74: NA | BU74: NA
B75: Quant Active Fund(G) | C75: 1.73 | D75: 45838 | E75: 10129.783 | F75: -0.038543 | G75: 0.037258 | H75: 0.008661 | I75: -0.155413 | J75: 0.145087 | K75: 0.24625 | L75: 0.168725 | N75: -0.035649 | O75: 0.11841999 | P75: 0.24880495 | Q75: 0.10437309 | R75: 0.55643586 | S75: 0.43553969 | T75: 0.03972103 | U75: -0.012779313 | V75: 0.3824457 | W75: -0.015165279 | X75: 0.12791734 | Y75: 0.67056721 | Z75: -0.018490754 | AA75: 0.37979685 | AB75: -0.35057621 | AC75: 0.17365904 | AD75: 0.72225441 | AE75: -0.59158486 | AF75: 0.78751632 | AG75: 0.29521645 | AH75: 0.55000997 | AI75: 0.21859436 | AJ75: 0.78235138 | AK75: 0.18478509 | AL75: 0.05252 | AM75: NA | AS75: PGIM India Corp Bond Fund(G) | AT75: 1.01 | AU75: 45716 | AV75: 94.8665 | AX75: 0.012393 | AY75: 0.022383 | AZ75: 0.036813 | BA75: 0.078543 | BB75: 0.061706 | BC75: 0.061715 | BD75: 0.064706 | BF75: 0.022383 | BG75: 0.076142674 | BH75: 0.064093463 | BI75: 0.031047447 | BJ75: 0.040674234 | BK75: 0.095942451 | BL75: 0.089489615 | BM75: 0.04292119 | BN75: 0.046385397 | BO75: 0.089775983 | BP75: 0.072115167 | BQ75: 0.096977768 | BR75: 0.054340651 | BS75: 0.090069047 | BT75: 0.06750759 | BU75: 0.069025972
B76: Quant Flexi Cap Fund(G) | C76: 1.77 | D76: 45838 | E76: 7326.1647 | F76: -0.029319 | G76: 0.021985 | H76: 0.040058 | I76: -0.126913 | J76: 0.194879 | K76: 0.290521 | L76: 0.18157 | N76: 0.005567 | O76: 0.15276221 | P76: 0.29779442 | Q76: 0.11096569 | R76: 0.57905355 | S76: 0.4742734 | T76: -0.030391486 | U76: -0.10056346 | V76: 0.44479417 | W76: 0.081522217 | X76: 0.020380679 | Y76: 0.68165176 | Z76: -0.079640791 | AA76: 0.20571327 | AB76: -0.45728006 | AC76: 0.027869781 | AD76: 0.69157419 | AE76: 0.01201 | AF76: NA | AG76: NA | AH76: NA | AI76: NA | AJ76: NA | AK76: NA | AL76: NA | AM76: NA | AS76: SBI Corp Bond Fund-Reg(G) | AT76: 0.76 | AU76: 45716 | AV76: 20671.63 | AX76: 0.013128 | AY76: 0.023757 | AZ76: 0.039669 | BA76: 0.082955 | BB76: 0.06421 | BC76: 0.062085 | BD76: NA | BF76: 0.023757 | BG76: 0.079196235 | BH76: 0.066265809 | BI76: 0.032998427 | BJ76: 0.028873385 | BK76: 0.10511428 | BL76: 0.09595 | BM76: NA | BN76: NA | BO76: NA | BP76: NA | BQ76: NA | BR76: NA | BS76: NA | BT76: NA | BU76: NA
B77: SBI Flexicap Fund-Reg(G) | C77: 1.67 | D77: 45838 | E77: 22499.736 | F77: -0.021484 | G77: 0.026544 | H77: 0.025685 | I77: -0.032438 | J77: 0.132381 | K77: 0.187915 | L77: 0.121057 | N77: -0.000122 | O77: 0.14222859 | P77: 0.22813459 | Q77: 0.0068428967 | R77: 0.30774017 | S77: 0.13596476 | T77: 0.10969887 | U77: -0.055103562 | V77: 0.36983115 | W77: 0.05815521 | X77: 0.098084514 | Y77: 0.55981998 | Z77: 0.051994638 | AA77: 0.38353116 | AB77: -0.30694087 | AC77: 0.097629797 | AD77: 0.80816327 | AE77: -0.57538995 | AF77: 0.45615142 | AG77: 0.42664266 | AH77: 0.111 | AI77: NA | AJ77: NA | AK77: NA | AL77: NA | AM77: NA | AS77: SBI CPSE Bond Plus SDL Sep 2026 50:50 Index Fund-Reg(G) | AT77: 0.34 | AU77: 45716 | AV77: 9296.5896 | AX77: 0.008043 | AY77: 0.020076 | AZ77: 0.036526 | BA77: 0.077436 | BB77: 0.057782 | BC77: NA | BD77: NA | BF77: 0.020076 | BG77: 0.077016184 | BH77: 0.067492169 | BI77: 0.0216 | BJ77: NA | BK77: NA | BL77: NA | BM77: NA | BN77: NA | BO77: NA | BP77: NA | BQ77: NA | BR77: NA | BS77: NA | BT77: NA | BU77: NA
B78: Tata Flexi Cap Fund-Reg(G) | C78: 1.89 | D78: 45838 | E78: 3418.7625 | F78: -0.026757 | G78: 0.03884 | H78: 0.078756 | I78: 0.020189 | J78: 0.16424 | K78: 0.18151 | L78: NA | N78: 0.068894 | O78: 0.12575131 | P78: 0.27835932 | Q78: -0.034912105 | R78: 0.26570684 | S78: 0.14313293 | T78: 0.10509654 | U78: 0.01716 | V78: NA | W78: NA | X78: NA | Y78: NA | Z78: NA | AA78: NA | AB78: NA | AC78: NA | AD78: NA | AE78: NA | AF78: NA | AG78: NA | AH78: NA | AI78: NA | AJ78: NA | AK78: NA | AL78: NA | AM78: NA | AS78: Sundaram Corp Bond Fund(G) | AT78: 0.51 | AU78: 45716 | AV78: 704.66033 | AX78: 0.013979 | AY78: 0.023433 | AZ78: 0.038145 | BA78: 0.083524 | BB78: 0.064137 | BC78: 0.064289 | BD78: 0.072847 | BF78: 0.023433 | BG78: 0.079805632 | BH78: 0.062644554 | BI78: 0.036613698 | BJ78: 0.034976917 | BK78: 0.10983416 | BL78: 0.11314821 | BM78: 0.048003885 | BN78: 0.054410336 | BO78: 0.117138 | BP78: 0.086608651 | BQ78: 0.149177 | BR78: -0.0025333723 | BS78: 0.086779266 | BT78: 0.057339995 | BU78: 0.04309552
B79: UTI Flexi Cap Fund-Reg(G) | C79: 1.66 | D79: 45838 | E79: 26324.594 | F79: -0.01965 | G79: 0.040314 | H79: 0.054485 | I79: 0.030152 | J79: 0.109698 | K79: 0.170372 | L79: 0.11867 | N79: 0.018382 | O79: 0.14321942 | P79: 0.19810303 | Q79: -0.13418295 | R79: 0.33977243 | S79: 0.31546231 | T79: 0.117282 | U79: 0.035242287 | V79: 0.30089843 | W79: 0.011399887 | X79: 0.0091037461 | Y79: 0.46758593 | Z79: 0.075572385 | AA79: 0.32153392 | AB79: -0.19093079 | AC79: 0.20501233 | AD79: 0.85165462 | AE79: -0.45251978 | AF79: 0.47481572 | AG79: 0.22775264 | AH79: 0.22777778 | AI79: NA | AJ79: NA | AK79: NA | AL79: NA | AM79: NA | AN79: 0.29 | AO79: 0.9 | AP79: 40.07 | AQ79: 5.79 | AS79: Tata Corp Bond Fund-Reg(G) | AT79: 0.87 | AU79: 45716 | AV79: 3274.5857 | AX79: 0.013893 | AY79: 0.023251 | AZ79: 0.038993 | BA79: 0.084137 | BB79: 0.063266 | BC79: NA | BD79: NA | BF79: 0.023251 | BG79: 0.082601151 | BH79: 0.069133874 | BI79: 0.022474266 | BJ79: 0.00159 | BK79: NA | BL79: NA | BM79: NA | BN79: NA | BO79: NA | BP79: NA | BQ79: NA | BR79: NA | BS79: NA | BT79: NA | BU79: NA
B80: WOC Flexi Cap Fund-Reg(G) | C80: 1.8 | D80: 45838 | E80: 5446.0488 | F80: -0.018897 | G80: 0.055201 | H80: 0.077159 | I80: 0.044681 | J80: NA | K80: NA | L80: NA | N80: 0.014762 | O80: 0.236673 | P80: 0.3115602 | Q80: 0.0441 | R80: NA | S80: NA | T80: NA | U80: NA | V80: NA | W80: NA | X80: NA | Y80: NA | Z80: NA | AA80: NA | AB80: NA | AC80: NA | AD80: NA | AE80: NA | AF80: NA | AG80: NA | AH80: NA | AI80: NA | AJ80: NA | AK80: NA | AL80: NA | AM80: NA | AS80: Tata Nifty SDL Plus AAA PSU Bond Dec 2027 60:40 Index Fund-Reg(G) | AT80: 0.47 | AU80: 45716 | AV80: 854.60161 | AX80: 0.008531 | AY80: 0.021305 | AZ80: 0.035933 | BA80: 0.081535 | BB80: 0.064623 | BC80: NA | BD80: NA | BF80: 0.021305 | BG80: 0.079883414 | BH80: 0.068265449 | BI80: 0.02453 | BJ80: NA | BK80: NA | BL80: NA | BM80: NA | BN80: NA | BO80: NA | BP80: NA | BQ80: NA | BR80: NA | BS80: NA | BT80: NA | BU80: NA
B81: S&P BSE 500 | F81: -0.028654 | G81: 0.038723 | H81: 0.05945 | I81: -0.032041 | J81: 0.154431 | K81: 0.201781 | L81: 0.123351 | N81: 0.022527 | O81: 0.1454658 | P81: 0.24849852 | Q81: 0.033378691 | R81: 0.30114043 | S81: 0.16803383 | T81: 0.077511676 | U81: -0.030817058 | V81: 0.35938129 | W81: 0.037823178 | X81: -0.0081517532 | Y81: 0.36959049 | Z81: 0.032548667 | AA81: 0.31198994 | AB81: -0.27413184 | AC81: 0.16351493 | AD81: 0.9022895 | AE81: -0.58139316 | AF81: 0.63020703 | AG81: 0.38851832 | AH81: 0.36562517 | AI81: 0.17465221 | AJ81: 1.0109626 | AK81: 0.16992106 | AL81: -0.22905585 | AM81: -0.27172554 | AS81: TRUSTMF Corporate Bond Fund-Reg(G) | AT81: 0.65 | AU81: 45716 | AV81: 59.255954 | AX81: 0.009749 | AY81: 0.017246 | AZ81: 0.030754 | BA81: 0.073871 | BB81: NA | BC81: NA | BD81: NA | BF81: 0.017246 | BG81: 0.075799108 | BH81: 0.0626286 | BI81: NA | BJ81: NA | BK81: NA | BL81: NA | BM81: NA | BN81: NA | BO81: NA | BP81: NA | BQ81: NA | BR81: NA | BS81: NA | BT81: NA | BU81: NA
B82: Category Average | F82: =AVERAGE(F59:F80) -> -0.021321864 | G82: =AVERAGE(G59:G80) -> 0.050421273 | H82: =AVERAGE(H59:H80) -> 0.069941864 | I82: =AVERAGE(I59:I80) -> 0.0017441364 | J82: =AVERAGE(J59:J80) -> 0.1838519 | K82: =AVERAGE(K59:K80) -> 0.22205522 | L82: =AVERAGE(L59:L80) -> 0.13882131 | N82: =AVERAGE(N59:N80) -> 0.019777682 | O82: =AVERAGE(O59:O80) -> 0.21179824 | P82: =AVERAGE(P59:P80) -> 0.28582361 | Q82: =AVERAGE(Q59:Q80) -> 0.015471058 | R82: =AVERAGE(R59:R80) -> 0.32812312 | S82: =AVERAGE(S59:S80) -> 0.19099778 | T82: =AVERAGE(T59:T80) -> 0.08796167 | U82: =AVERAGE(U59:U80) -> -0.032642103 | ... AM82: =AVERAGE(AM59:AM80) -> -0.23225039 | AS82: Union Corporate Bond Fund-Reg(G) | AT82: 0.71 | AU82: 45716 | AV82: 328.8168 | AX82: 0.013663 | AY82: 0.023238 | AZ82: 0.038061 | BA82: 0.08231 | BB82: 0.060646 | BC82: 0.060214 | BD82: NA | BF82: 0.023238 | BG82: 0.079808731 | BH82: 0.064350429 | BI82: 0.024033691 | BJ82: 0.02908309 | BK82: 0.10676382 | BL82: 0.043242777 | BM82: 0.04318 | BN82: NA | BO82: NA | BP82: NA | BQ82: NA | BR82: NA | BS82: NA | BT82: NA | BU82: NA
AS83: UTI Corporate Bond Fund-Reg(G) | AT83: 0.59 | AU83: 45716 | AV83: 4848.0574 | AX83: 0.013121 | AY83: 0.023765 | AZ83: 0.039431 | BA83: 0.082385 | BB83: 0.065507 | BC83: 0.063958 | BD83: NA | BF83: 0.023765 | BG83: 0.078925608 | BH83: 0.068785718 | BI83: 0.033922439 | BJ83: 0.034322798 | BK83: 0.11024545 | BL83: 0.11416046 | BM83: 0.02645 | BN83: NA | BO83: NA | BP83: NA | BQ83: NA | BR83: NA | BS83: NA | BT83: NA | BU83: NA
B84: Value | C84: Expense Ratio | D84: Corpus | F84: Returns | N84: CY Year Returns | AS84: Category Average | AX84: =AVERAGE(AX43:AX83) -> 0.010431634 | AY84: =AVERAGE(AY43:AY83) -> 0.021447341 | AZ84: =AVERAGE(AZ43:AZ83) -> 0.037502308 | BA84: =AVERAGE(BA43:BA83) -> 0.080458872 | BB84: =AVERAGE(BB43:BB83) -> 0.06255097 | BC84: =AVERAGE(BC43:BC83) -> 0.063616222 | BD84: =AVERAGE(BD43:BD83) -> 0.07044975 | BF84: =AVERAGE(BF43:BF83) -> 0.021447341 | BG84: =AVERAGE(BG43:BG83) -> 0.075558851 | BH84: =AVERAGE(BH43:BH83) -> 0.067539194 | BI84: =AVERAGE(BI43:BI83) -> 0.02480616 | BJ84: =AVERAGE(BJ43:BJ83) -> 0.031786285 | BK84: =AVERAGE(BK43:BK83) -> 0.10536877 | BL84: =AVERAGE(BL43:BL83) -> 0.089788075 | BM84: =AVERAGE(BM43:BM83) -> 0.056730088 | ... BU84: =AVERAGE(BU43:BU83) -> 0.04949611
D85: Month End | E85: AUM (Cr.) | F85: 1 month | G85: 3 months | H85: 6 months | I85: 1 Year | J85: 3 Year | K85: 5 Year | L85: 10 Year | N85: CY 2025 | O85: 2024 | P85: 2023 | Q85: 2022 | R85: 2021 | S85: 2020 | T85: 2019 | U85: 2018 | V85: 2017 | W85: 2016 | X85: 2015 | Y85: 2014 | Z85: 2013 | AA85: 2012 | AB85: 2011 | AC85: 2010 | AD85: 2009 | AE85: 2008 | AF85: 2007 | AG85: 2006 | AH85: 2005 | AI85: 2004 | AJ85: 2003 | AK85: 2002 | AL85: 2001 | AM85: 2000 | AS85: Crisil Short Term Fund | AX85: 0.0087263868 | AY85: 0.020764393 | AZ85: 0.037718441 | BA85: 0.080280059 | BB85: 0.065930171 | BC85: 0.065514977 | BD85: 0.073804732 | BF85: 0.020764393 | BG85: 0.079702926 | BH85: 0.072598887 | BI85: 0.035868229 | BJ85: 0.043796599 | BK85: 0.10416197 | BL85: 0.095336484 | BM85: 0.066506819 | BN85: 0.060295716 | BO85: 0.098673876 | BP85: 0.086554994 | BQ85: 0.10468193 | BR85: 0.082720616 | BS85: 0.091237132 | BT85: 0.078677103 | BU85: 0.047004033
B86: Aditya Birla SL Pure Value Fund(G) | C86: 1.87 | D86: 45838 | E86: 6371.3812 | F86: -0.041049 | G86: 0.052683 | H86: 0.030642 | I86: -0.06854 | J86: 0.206111 | K86: 0.245838 | L86: 0.117086 | N86: -0.029936 | O86: 0.18470502 | P86: 0.43015071 | Q86: 0.034852864 | R86: 0.34452683 | S86: 0.15603695 | T86: -0.10693305 | U86: -0.23473761 | V86: 0.56038672 | W86: 0.089934712 | X86: 0.04151264 | Y86: 0.99001119 | Z86: 0.054214885 | AA86: 0.3338747 | AB86: -0.24042277 | AC86: 0.23719888 | AD86: 0.91374365 | AE86: -0.23994 | AF86: NA | AG86: NA | AH86: NA | AI86: NA | AJ86: NA | AK86: NA | AL86: NA | AM86: NA
B87: HDFC Capital Builder Value Fund(G) | C87: 1.84 | D87: 45838 | E87: 7443.4495 | F87: -0.019414 | G87: 0.050191 | H87: 0.083942 | I87: 0.005225 | J87: 0.206401 | K87: 0.234983 | L87: 0.13521 | N87: 0.039684 | O87: 0.20707907 | P87: 0.29594075 | Q87: 0.036086945 | R87: 0.3558271 | S87: 0.12941172 | T87: -6.2902093e-05 | U87: -0.054744791 | V87: 0.42312104 | W87: 0.03827569 | X87: 0.046148976 | Y87: 0.51954874 | Z87: 0.10367713 | AA87: 0.28415589 | AB87: -0.23640303 | AC87: 0.28438002 | AD87: 0.92911535 | AE87: -0.54885581 | AF87: 0.68650172 | AG87: 0.21576212 | AH87: 0.47529813 | AI87: 0.47778291 | AJ87: 1.2190875 | AK87: 0.16233766 | AL87: -0.23064113 | AM87: -0.17172414 | AS87: Credit Risk Fund | AT87: Expense Ratio | AU87: Corpus | AX87: Risk Return | BF87: Yearly Performance
B88: HSBC Value Fund-Reg(G) | C88: 1.71 | D88: 45838 | E88: 14053.516 | F88: -0.021093 | G88: 0.08057 | H88: 0.088355 | I88: -0.00389 | J88: 0.254177 | K88: 0.271801 | L88: 0.156125 | N88: 0.026615 | O88: 0.25915927 | P88: 0.39355229 | Q88: 0.052373257 | R88: 0.40325188 | S88: 0.14612365 | T88: 0.045982995 | U88: -0.11438377 | V88: 0.41264156 | W88: 0.081295724 | X88: 0.12877015 | Y88: 0.74058417 | Z88: 0.066393443 | AA88: 0.39812056 | AB88: -0.27088904 | AC88: 0.1968 | AD88: NA | AE88: NA | AF88: NA | AG88: NA | AH88: NA | AI88: NA | AJ88: NA | AK88: NA | AL88: NA | AM88: NA | AT88: Ratio | AU88: Month End | AV88: AUM (Cr.) | AX88: 1 Month | AY88: 3 Months | AZ88: 6 Months | BA88: 1 Year | BB88: 3 Years | BC88: 5 Years | BD88: 10 Years | BF88: 2025 | BG88: 2024 | BH88: 2023 | BI88: 2022 | BJ88: 2021 | BK88: 2020 | BL88: 2019 | BM88: 2018 | BN88: 2017 | BO88: 2016 | BP88: 2015 | BQ88: 2014 | BR88: 2013 | BS88: 2012 | BT88: 2011 | BU88: 2010
B89: ICICI Pru Value Discovery Fund(G) | C89: 1.51 | D89: 45838 | E89: 54096.423 | F89: -0.014375 | G89: 0.033215 | H89: 0.070475 | I89: 0.021841 | J89: 0.223314 | K89: 0.263948 | L89: 0.146958 | N89: 0.065346 | O89: 0.19984669 | P89: 0.31395683 | Q89: 0.14952034 | R89: 0.38518816 | S89: 0.22872827 | T89: 0.0059469027 | U89: -0.042243016 | V89: 0.23818319 | W89: 0.046109257 | X89: 0.054356885 | Y89: 0.73757039 | Z89: 0.08313001 | AA89: 0.46005089 | AB89: -0.23733747 | AC89: 0.27707559 | AD89: 1.3432056 | AE89: -0.54564644 | AF89: 0.39646279 | AG89: 0.28686581 | AH89: 0.63742236 | AI89: 0.288 | AJ89: NA | AK89: NA | AL89: NA | AM89: NA | AS89: Aditya Birla SL Credit Risk Fund-Reg(G) | AT89: 1.54 | AU89: 45716 | AV89: 963.5658 | AX89: 0.010542 | AY89: 0.057891 | AZ89: 0.101141 | BA89: 0.160628 | BB89: 0.102093 | BC89: 0.091084 | BD89: NA | BF89: 0.057891 | BG89: 0.1191565 | BH89: 0.068890986 | BI89: 0.070965971 | BJ89: 0.063614886 | BK89: 0.09363796 | BL89: 0.020856332 | BM89: 0.066003759 | BN89: 0.080896037 | BO89: 0.10295281 | BP89: 0.060237596 | BQ89: NA | BR89: NA | BS89: NA | BT89: NA | BU89: NA
B90: Invesco India Contra Fund(G) | C90: 1.64 | D90: 45838 | E90: 19257.397 | F90: -0.009413 | G90: 0.058392 | H90: 0.081064 | I90: 0.017081 | J90: 0.214411 | K90: 0.229464 | L90: 0.154051 | N90: 0.012908 | O90: 0.30138848 | P90: 0.28818011 | Q90: 0.037907309 | R90: 0.29571068 | S90: 0.21178149 | T90: 0.059382423 | U90: -0.03258826 | V90: 0.45634317 | W90: 0.067207792 | X90: 0.040189125 | Y90: 0.62960925 | Z90: 0.046658986 | AA90: 0.30722892 | AB90: -0.22065728 | AC90: 0.12922465 | AD90: 1.0474898 | AE90: -0.48961219 | AF90: 0.444 | AG90: NA | AH90: NA | AI90: NA | AJ90: NA | AK90: NA | AL90: NA | AM90: NA | AS90: Axis Credit Risk Fund-Reg(G) | AT90: 1.57 | AU90: 45716 | AV90: 380.5396 | AX90: 0.010409 | AY90: 0.021017 | AZ90: 0.038479 | BA90: 0.081446 | BB90: 0.066685 | BC90: 0.0662 | BD90: 0.067971 | BF90: 0.021017 | BG90: 0.080487316 | BH90: 0.070080604 | BI90: 0.040212697 | BJ90: 0.059804099 | BK90: 0.082105845 | BL90: 0.043532679 | BM90: 0.058887913 | BN90: 0.064324149 | BO90: 0.097906661 | BP90: 0.087009155 | BQ90: 0.05736 | BR90: NA | BS90: NA | BT90: NA | BU90: NA
B91: Kotak India EQ Contra Fund(G) | C91: 1.87 | D91: 45838 | E91: 4502.483 | F91: -0.018827 | G91: 0.063214 | H91: 0.074125 | I91: -0.025721 | J91: 0.219105 | K91: 0.239011 | L91: 0.150219 | N91: 0.020387 | O91: 0.22101761 | P91: 0.35013769 | Q91: 0.073671966 | R91: 0.30170347 | S91: 0.15172213 | T91: 0.10021186 | U91: 0.025581109 | V91: 0.35392557 | W91: 0.070562719 | X91: -0.033565912 | Y91: 0.39308 | Z91: 0.074436995 | AA91: 0.33203572 | AB91: -0.23813678 | AC91: 0.15616963 | AD91: 0.80380207 | AE91: -0.50734899 | AF91: 0.51788872 | AG91: 0.26045953 | AH91: 0.1664 | AI91: NA | AJ91: NA | AK91: NA | AL91: NA | AM91: NA | AS91: Bandhan Credit Risk Fund-Reg(G) | AT91: 1.68 | AU91: 45716 | AV91: 289.4598 | AX91: 0.010393 | AY91: 0.019447 | AZ91: 0.034558 | BA91: 0.074206 | BB91: 0.058184 | BC91: 0.054745 | BD91: NA | BF91: 0.019447 | BG91: 0.073689789 | BH91: 0.057810074 | BI91: 0.030531976 | BJ91: 0.039691341 | BK91: 0.074400132 | BL91: 0.091473932 | BM91: 0.049951168 | BN91: 0.05463 | BO91: NA | BP91: NA | BQ91: NA | BR91: NA | BS91: NA | BT91: NA | BU91: NA
B92: Nippon India Value Fund(G) | C92: 1.82 | D92: 45838 | E92: 8954.7991 | F92: -0.02258 | G92: 0.041111 | H92: 0.059082 | I92: -0.010922 | J92: 0.229195 | K92: 0.267763 | L92: 0.14678 | N92: 0.006485 | O92: 0.22330346 | P92: 0.42379002 | Q92: 0.047760171 | R92: 0.39404844 | S92: 0.16302609 | T92: 0.056926716 | U92: -0.08439455 | V92: 0.45707444 | W92: -0.016253968 | X92: 0.06120783 | Y92: 0.56148207 | Z92: -0.037348306 | AA92: 0.46006213 | AB92: -0.29983033 | AC92: 0.19611392 | AD92: 1.0287988 | AE92: -0.54611572 | AF92: 0.92984161 | AG92: 0.55949223 | AH92: 0.00282 | AI92: NA | AJ92: NA | AK92: NA | AL92: NA | AM92: NA | AS92: Bank of India Credit Risk Fund-Reg(G) | AT92: 1.38 | AU92: 45716 | AV92: 113.5433 | AX92: 0.009338 | AY92: 0.017971 | AZ92: 0.031285 | BA92: 0.052776 | BB92: 0.053276 | BC92: 0.096312 | BD92: 0.017767 | BF92: 0.017971 | BG92: 0.060091661 | BH92: 0.055557136 | BI92: 1.4313423 | BJ92: 0.093651474 | BK92: -0.44429961 | BL92: -0.45226324 | BM92: -0.0028706815 | BN92: 0.093228779 | BO92: 0.11217528 | BP92: 0.07439 | BQ92: NA | BR92: NA | BS92: NA | BT92: NA | BU92: NA
B93: Quant Value Fund-Reg(G) | C93: 2.01 | D93: 45838 | E93: 1829.7896 | F93: -0.019806 | G93: 0.063272 | H93: 0.045217 | I93: -0.124541 | J93: 0.250253 | K93: NA | L93: NA | N93: -0.018356 | O93: 0.24069875 | P93: 0.36854647 | Q93: 0.15052565 | R93: 0.01398 | S93: NA | T93: NA | U93: NA | V93: NA | W93: NA | X93: NA | Y93: NA | Z93: NA | AA93: NA | AB93: NA | AC93: NA | AD93: NA | AE93: NA | AF93: NA | AG93: NA | AH93: NA | AI93: NA | AJ93: NA | AK93: NA | AL93: NA | AM93: NA | AS93: Baroda BNP Paribas Credit Risk Fund-Reg(G) | AT93: 1.6 | AU93: 45716 | AV93: 175.9341 | AX93: 0.009167 | AY93: 0.021297 | AZ93: 0.037834 | BA93: 0.082403 | BB93: 0.069408 | BC93: 0.088459 | BD93: 0.077824 | BF93: 0.021297 | BG93: 0.081736356 | BH93: 0.073508089 | BI93: 0.045690942 | BJ93: 0.19239061 | BK93: 0.023982005 | BL93: 0.020852202 | BM93: 0.05936525 | BN93: 0.084308827 | BO93: 0.11299028 | BP93: 0.09682 | BQ93: NA | BR93: NA | BS93: NA | BT93: NA | BU93: NA
B94: SBI Contra Fund-Reg(G) | C94: 1.49 | D94: 45838 | E94: 47389.62 | F94: -0.024044 | G94: 0.027091 | H94: 0.041015 | I94: -0.040405 | J94: 0.217907 | K94: 0.30947 | L94: 0.154169 | N94: 0.008711 | O94: 0.18799304 | P94: 0.38219516 | Q94: 0.127586 | R94: 0.49921054 | S94: 0.30601557 | T94: -0.010292175 | U94: -0.14334592 | V94: 0.40228997 | W94: 0.023980734 | X94: -0.00097715476 | Y94: 0.47657674 | Z94: -0.017474472 | AA94: 0.34185887 | AB94: -0.28236644 | AC94: 0.095905172 | AD94: 0.90554415 | AE94: -0.5314304 | AF94: 0.66293333 | AG94: 0.50481541 | AH94: 0.70919067 | AI94: 0.64486906 | AJ94: 1.1443142 | AK94: 0.32741117 | AL94: -0.054804544 | AM94: -0.35077445 | AN94: 1.15 | AO94: 0.86 | AP94: 18.56 | AQ94: 2.59 | AS94: DSP Credit Risk Fund-Reg(G) | AT94: 1.16 | AU94: 45716 | AV94: 191.6104 | AX94: 0.086455 | AY94: 0.14982 | AZ94: 0.169395 | BA94: 0.215552 | BB94: 0.134665 | BC94: 0.105583 | BD94: 0.079789 | BF94: 0.14982 | BG94: 0.077979637 | BH94: 0.15592962 | BI94: 0.092535842 | BJ94: 0.028685517 | BK94: 0.048348797 | BL94: 0.043949545 | BM94: -0.026281737 | BN94: 0.064289119 | BO94: 0.10599854 | BP94: 0.096416774 | BQ94: 0.10763852 | BR94: 0.081351834 | BS94: 0.088373734 | BT94: 0.084848367 | BU94: 0.052487093
B95: Tata Equity P/E Fund(G) | C95: 1.77 | D95: 45838 | E95: 8839.9967 | F95: -0.025851 | G95: 0.045127 | H95: 0.050863 | I95: -0.06581 | J95: 0.208595 | K95: 0.217145 | L95: 0.141669 | N95: -0.019328 | O95: 0.21696695 | P95: 0.36990696 | Q95: 0.05943054 | R95: 0.27996271 | S95: 0.1250386 | T95: 0.053003641 | U95: -0.070644714 | V95: 0.39380425 | W95: 0.16184454 | X95: 0.0030821701 | Y95: 0.695422 | Z95: 0.017529806 | AA95: 0.29527473 | AB95: -0.23758328 | AC95: 0.16834354 | AD95: 1.0359488 | AE95: -0.53843435 | AF95: 0.83601284 | AG95: 0.29028816 | AH95: 0.39972844 | AI95: 0.3993 | AJ95: NA | AK95: NA | AL95: NA | AM95: NA | AS95: HDFC Credit Risk Debt Fund-(G) | AT95: 1.59 | AU95: 45716 | AV95: 7252.4194 | AX95: 0.008665 | AY95: 0.020088 | AZ95: 0.03444 | BA95: 0.078153 | BB95: 0.064542 | BC95: 0.071275 | BD95: 0.076352 | BF95: 0.020088 | BG95: 0.08193833 | BH95: 0.06620881 | BI95: 0.037115159 | BJ95: 0.069754517 | BK95: 0.10913787 | BL95: 0.086475481 | BM95: 0.053591967 | BN95: 0.065692607 | BO95: 0.10957864 | BP95: 0.0900905 | BQ95: 0.09945 | BR95: NA | BS95: NA | BT95: NA | BU95: NA
B96: Templeton India Value Fund(G) | C96: 2.04 | D96: 45838 | E96: 2298.637 | F96: -0.027209 | G96: 0.021432 | H96: 0.047538 | I96: -0.065496 | J96: 0.199174 | K96: 0.282066 | L96: 0.137029 | N96: 0.018433 | O96: 0.15188792 | P96: 0.3372477 | Q96: 0.15462878 | R96: 0.44544928 | S96: 0.11503003 | T96: -0.0030928496 | U96: -0.12822913 | V96: 0.37645733 | W96: 0.094610829 | X96: 0.00052778687 | Y96: 0.49152043 | Z96: -0.0060457342 | AA96: 0.35902345 | AB96: -0.2957162 | AC96: 0.21958436 | AD96: 1.0469955 | AE96: -0.51004272 | AF96: 0.63105062 | AG96: 0.30518962 | AH96: 0.34931322 | AI96: 0.19774194 | AJ96: 0.50558524 | AK96: NA | AL96: NA | AM96: NA | AS96: HSBC Credit Risk Fund-Reg(G) | AT96: 1.68 | AU96: 45716 | AV96: 581.6123 | AX96: 0.021703 | AY96: 0.032296 | AZ96: 0.047483 | BA96: 0.087314 | BB96: 0.064656 | BC96: 0.056545 | BD96: 0.062281 | BF96: 0.032296 | BG96: 0.071542569 | BH96: 0.064628016 | BI96: 0.031927238 | BJ96: 0.056686787 | BK96: 0.049843588 | BL96: 0.022640268 | BM96: 0.055771864 | BN96: 0.07202603 | BO96: 0.10054859 | BP96: 0.094108646 | BQ96: 0.11418787 | BR96: 0.058208711 | BS96: 0.094877646 | BT96: 0.096970037 | BU96: 0.058310681
B97: UTI Value Opp Fund-Reg(G) | C97: 1.82 | D97: 45838 | E97: 10117.32 | F97: -0.020084 | G97: 0.04248 | H97: 0.054995 | I97: -5e-06 | J97: 0.192292 | K97: 0.226054 | L97: 0.13074 | N97: 0.024006 | O97: 0.23412755 | P97: 0.26719129 | Q97: 0.042717042 | R97: 0.30418104 | S97: 0.19019143 | T97: 0.10396543 | U97: -0.024430248 | V97: 0.2909176 | W97: 0.02603367 | X97: -0.059411297 | Y97: 0.41216814 | Z97: 0.058522551 | AA97: 0.27276326 | AB97: -0.12108559 | AC97: 0.19401745 | AD97: 0.97619048 | AE97: -0.49037657 | AF97: 0.71326165 | AG97: 0.10890302 | AH97: 0.258 | AI97: NA | AJ97: NA | AK97: NA | AL97: NA | AM97: NA | AS97: ICICI Pru Credit Risk Fund(G) | AT97: 1.41 | AU97: 45716 | AV97: 6187.431 | AX97: 0.008885 | AY97: 0.021544 | AZ97: 0.037276 | BA97: 0.08264 | BB97: 0.071351 | BC97: 0.073173 | BD97: 0.077521 | BF97: 0.021544 | BG97: 0.084625432 | BH97: 0.072364609 | BI97: 0.050535957 | BJ97: 0.062327896 | BK97: 0.097900651 | BL97: 0.094762579 | BM97: 0.066443067 | BN97: 0.0677377 | BO97: 0.095434992 | BP97: 0.089991672 | BQ97: 0.10965202 | BR97: 0.074990817 | BS97: 0.09432411 | BT97: 0.088620813 | BU97: 0.00552
B98: S&P BSE 500 | F98: -0.028654 | G98: 0.038723 | H98: 0.05945 | I98: -0.032041 | J98: 0.154431 | K98: 0.201781 | L98: 0.123351 | N98: 0.022527 | O98: 0.1454658 | P98: 0.24849852 | Q98: 0.033378691 | R98: 0.30114043 | S98: 0.16803383 | T98: 0.077511676 | U98: -0.030817058 | V98: 0.35938129 | W98: 0.037823178 | X98: -0.0081517532 | Y98: 0.36959049 | Z98: 0.032548667 | AA98: 0.31198994 | AB98: -0.27413184 | AC98: 0.16351493 | AD98: 0.9022895 | AE98: -0.58139316 | AF98: 0.63020703 | AG98: 0.38851832 | AH98: 0.36562517 | AI98: 0.17465221 | AJ98: 1.0109626 | AK98: 0.16992106 | AL98: -0.22905585 | AM98: -0.27172554 | AS98: Invesco India Credit Risk Fund(G) | AT98: 1.45 | AU98: 45716 | AV98: 140.3174 | AX98: 0.026429 | AY98: 0.041645 | AZ98: 0.055298 | BA98: 0.096236 | BB98: 0.082395 | BC98: 0.068712 | BD98: 0.059125 | BF98: 0.041645 | BG98: 0.072856003 | BH98: 0.11622564 | BI98: 0.022324769 | BJ98: 0.027888737 | BK98: 0.079784789 | BL98: -0.045270872 | BM98: 0.040889754 | BN98: 0.070850189 | BO98: 0.10922865 | BP98: 0.090901706 | BQ98: 0.037733 | BR98: NA | BS98: NA | BT98: NA | BU98: NA
B99: Category Average | F99: =AVERAGE(F86:F97) -> -0.02197875 | G99: =AVERAGE(G86:G97) -> 0.0482315 | H99: =AVERAGE(H86:H97) -> 0.060609417 | I99: =AVERAGE(I86:I97) -> -0.030098583 | J99: =AVERAGE(J86:J97) -> 0.21841125 | K99: =AVERAGE(K86:K97) -> 0.253413 | L99: =AVERAGE(L86:L97) -> 0.14273055 | N99: =AVERAGE(N86:N97) -> 0.012912917 | O99: =AVERAGE(O86:O97) -> 0.21901448 | P99: =AVERAGE(P86:P97) -> 0.351733 | Q99: =AVERAGE(Q86:Q97) -> 0.080588406 | R99: =AVERAGE(R86:R97) -> 0.33525334 | S99: =AVERAGE(S86:S97) -> 0.17482781 | T99: =AVERAGE(T86:T97) -> 0.027730817 | U99: =AVERAGE(U86:U97) -> -0.082196445 | ... AM99: =AVERAGE(AM86:AM97) -> -0.2612493 | AS99: Kotak Credit Risk Fund(G) | AT99: 1.71 | AU99: 45716 | AV99: 728.0749 | AX99: 0.007209 | AY99: 0.021272 | AZ99: 0.032671 | BA99: 0.064304 | BB99: 0.050866 | BC99: 0.054635 | BD99: 0.067128 | BF99: 0.021272 | BG99: 0.071188227 | BH99: 0.064289808 | BI99: 0.0090275214 | BJ99: 0.052970265 | BK99: 0.066138382 | BL99: 0.08973542 | BM99: 0.062073339 | BN99: 0.065594158 | BO99: 0.10433272 | BP99: 0.090943298 | BQ99: 0.1113071 | BR99: 0.073443838 | BS99: 0.097585883 | BT99: 0.088654626 | BU99: 0.02544
AS100: SBI Credit Risk Fund-Reg(G) | AT100: 1.55 | AU100: 45716 | AV100: 2259.2892 | AX100: 0.011704 | AY100: 0.02233 | AZ100: 0.041045 | BA100: 0.083844 | BB100: 0.072619 | BC100: 0.07073 | BD100: 0.074168 | BF100: 0.02233 | BG100: 0.080811482 | BH100: 0.083169299 | BI100: 0.042486154 | BJ100: 0.049519389 | BK100: 0.097766884 | BL100: 0.065027598 | BM100: 0.061859576 | BN100: 0.068922686 | BO100: 0.10482369 | BP100: 0.097080047 | BQ100: 0.10615916 | BR100: 0.10078499 | BS100: 0.097977108 | BT100: 0.094471224 | BU100: 0.056214852
B101: Mid-Cap | C101: Expense Ratio | D101: Corpus | F101: Returns | N101: CY Year Returns | AS101: UTI Credit Risk Fund-Reg(G) | AT101: 1.68 | AU101: 45716 | AV101: 296.9326 | AX101: 0.008496 | AY101: 0.020222 | AZ101: 0.036368 | BA101: 0.079632 | BB101: 0.064455 | BC101: 0.072783 | BD101: 0.030044 | BF101: 0.020222 | BG101: 0.078910651 | BH101: 0.065937073 | BI101: 0.038617072 | BJ101: 0.21482629 | BK101: -0.27784738 | BL101: -0.04789089 | BM101: 0.054796983 | BN101: 0.06899486 | BO101: 0.10302778 | BP101: 0.088606343 | BQ101: 0.11459405 | BR101: 0.077049391 | BS101: 0.01091 | BT101: NA | BU101: NA
...

Sheet Drop Downs
C2: Year | D2: Nifty 50 | E2: CA Blended Index | I2: MP | J2: Large Cap | K2: Large Mid Cap | L2: Multicap | M2: Mid/Small cap | O2: Year | P2: S&P BSE SENSEX | Q2: S&P BSE 500 | R2: NIFTY 50 | S2: S&P BSE Small-Cap | T2: S&P BSE Mid-Cap | U2: CA Blended Index
C3: CY 2025 | D3: -0.005306 | E3: -0.012295198 | I3: Conservative | J3: 0.3 | K3: 0.2 | L3: 0.5 | M3: 0 | O3: CY 2025 | P3: {=TRANSPOSE(performace_data!N26:U26)} -> 0.038989 | Q3: {=TRANSPOSE(performace_data!N81:U81)} -> 0.022527 | R3: {=TRANSPOSE(performace_data!N27:U27)} -> 0.047518 | S3: {=TRANSPOSE(performace_data!N141:U141)} -> -0.03181 | T3: {=TRANSPOSE(performace_data!N120:U120)} -> -0.014275 | U3: {=TRANSPOSE(performace_data!$N$228:$U$228)} -> 0.0265322
C4: 2024 | D4: 0.08804769 | E4: 0.11514819 | I4: Moderately Conservative | J4: 0.3 | K4: 0.2 | L4: 0.5 | M4: 0 | O4: 2024 | P4: 0.081654606 | Q4: 0.1454658 | R4: 0.08804769 | S4: 0.29308034 | T4: 0.26073951 | U4: 0.12210835
C5: 2023 | D5: 0.20027839 | E5: 0.15853564 | I5: Moderate | J5: 0.3 | K5: 0.2 | L5: 0.5 | M5: 0 | O5: 2023 | P5: 0.18736656 | Q5: 0.24849852 | R5: 0.20027839 | S5: 0.47523317 | T5: 0.45526161 | U5: 0.17333914
C6: 2022 | D6: 0.043289607 | E6: 0.038408609 | I6: Moderately Aggressive | J6: 0.3 | K6: 0.2 | L6: 0.4 | M6: 0.1 | O6: 2022 | P6: 0.044407732 | Q6: 0.033378691 | R6: 0.043289607 | S6: -0.018024792 | T6: 0.013793308 | U6: 0.034066195
C7: 2021 | D7: 0.24119298 | E7: 0.16871177 | I7: Aggressive | J7: 0.3 | K7: 0.2 | L7: 0.3 | M7: 0.2 | O7: 2021 | P7: 0.21994131 | Q7: 0.30114043 | R7: 0.24119298 | S7: 0.62767051 | T7: 0.39175528 | U7: 0.11732454
C8: 2020 | D8: 0.14901651 | E8: 0.14818945 | O8: 2020 | P8: 0.15750305 | Q8: 0.16803383 | R8: 0.14901651 | S8: 0.32109068 | T8: 0.19866607 | U8: 0.12302232
C9: 2019 | D9: 0.12022039 | E9: 0.088822149 | J9: Debt Alternatives | K9: Private Credit | L9: Multi Asset Allocation | O9: 2019 | P9: 0.14376629 | Q9: 0.077511676 | R9: 0.12022039 | S9: -0.068493998 | T9: -0.03048363 | U9: 0.067712613
C10: 2018 | D10: 0.031512625 | E10: 0.018833318 | I10: Conservative | J10: 0.7 | K10: 0.15 | L10: 0.15 | O10: 2018 | P10: 0.059063043 | Q10: -0.030817058 | R10: 0.031512625 | S10: -0.23525016 | T10: -0.13376145 | U10: 0.011509891
I11: Moderately Conservative | J11: 0.6 | K11: 0.3 | L11: 0.1
I12: Moderate | J12: 0.5 | K12: 0.4 | L12: 0.1 | O12: Year | P12: S&P BSE SENSEX | Q12: S&P BSE 500 | R12: NIFTY 50 | S12: S&P BSE Small-Cap | T12: S&P BSE Mid-Cap | U12: CA Blended Index
I13: Moderately Aggressive | J13: 0.5 | K13: 0.5 | L13: 0 | O13: 1 month | P13: {=TRANSPOSE(performace_data!$F$26:$L$26)} -> -0.028956 | Q13: {=TRANSPOSE(performace_data!$F$81:$L$81)} -> -0.028654 | R13: {=TRANSPOSE(performace_data!$F$27:$L$27)} -> -0.029341 | S13: {=TRANSPOSE(performace_data!$F$141:$L$141)} -> -0.023141 | T13: {=TRANSPOSE(performace_data!$F$120:$L$120)} -> -0.022897 | U13: {=TRANSPOSE(performace_data!$F$228:$L$228)} -> -0.010432806
B14: Equity Stock Exposure | I14: Aggressive | J14: 0.4 | K14: 0.6 | L14: 0 | O14: 3 months | P14: 0.011756 | Q14: 0.038723 | R14: 0.017841 | S14: 0.127108 | T14: 0.067576 | U14: 0.029856028
B15: Hybrid Stock Exposure | O15: 6 months | P15: 0.047548 | Q15: 0.05945 | R15: 0.053596 | S15: 0.069396 | T15: 0.062307 | U15: 0.050474457
B16: Equity Sector Exposure | O16: 1 Year | P16: -0.006799 | Q16: -0.032041 | R16: -0.007326 | S16: -0.034464 | T16: -0.058658 | U16: 0.017165794
B17: Hybrid Sector Exposure | O17: 3 Year | P17: 0.121048 | Q17: 0.154431 | R17: 0.129786 | S17: 0.253786 | T17: 0.238603 | U17: 0.12227436
I18: Equity | O18: 5 Year | P18: 0.166288 | Q18: 0.201781 | R18: 0.174585 | S18: 0.326015 | T18: 0.271637 | U18: 0.126014
I19: Hybrid | O19: 10 Year | P19: 0.111775 | Q19: 0.123351 | R19: 0.112352 | S19: 0.162571 | T19: 0.150311 | U19: 0.093137667
I20: Debt
I21: Alternative
B23: Model Portfolios | P23: =IF(AND('Selector Sheet '!A37=TRUE,'Selector Sheet '!B37<>""),O23&"||"&'Selector Sheet '!B37,"")
B24: Risk Profile | C24: Debt | D24: Equity | E24: Hybrid | F24: Alternative | P24: =IF(AND('Selector Sheet '!A38=TRUE,'Selector Sheet '!B38<>""),O24&"||"&'Selector Sheet '!B38,"")
B25: Conservative | C25: 0.3 | D25: 0.4 | E25: 0.2 | F25: 0.1 | P25: =IF(AND('Selector Sheet '!A39=TRUE,'Selector Sheet '!B39<>""),O25&"||"&'Selector Sheet '!B39,"")
B26: Moderately Conservative | C26: 0.3 | D26: 0.4 | E26: 0.2 | F26: 0.1 | I26: Equity | J26: Renaissance Opportunities Fund PMS | P26: =IF(AND('Selector Sheet '!A40=TRUE,'Selector Sheet '!B40<>""),O26&"||"&'Selector Sheet '!B40,"")
B27: Moderate | C27: 0.3 | D27: 0.4 | E27: 0.2 | F27: 0.1 | I27: Equity | J27: Nippon India Large Cap Fund(G) | P27: =IF(AND('Selector Sheet '!A41=TRUE,'Selector Sheet '!B41<>""),O27&"||"&'Selector Sheet '!B41,"")
B28: Moderately Aggressive | C28: 0.2 | D28: 0.5 | E28: 0.2 | F28: 0.1 | I28: Equity | J28: ICICI Pru Bluechip Fund(G) | P28: =IF(AND('Selector Sheet '!A42=TRUE,'Selector Sheet '!B42<>""),O28&"||"&'Selector Sheet '!B42,"")
B29: Aggressive | C29: 0.1 | D29: 0.75 | E29: 0.05 | F29: 0.1 | I29: Equity | J29: Kotak Bluechip Fund(G) | P29: =IF(AND('Selector Sheet '!A43=TRUE,'Selector Sheet '!B43<>""),O29&"||"&'Selector Sheet '!B43,"")
I30: Equity | J30: Canara Rob Bluechip Equity Fund-Reg(G)
I31: Equity | J31: SBI Large & Midcap Fund-Reg(G)
I32: Equity | J32: ICICI Pru Large & Mid Cap Fund(G)
I33: Equity | J33: Canara Rob Emerg Equities Fund-Reg(G)
I34: Equity | J34: AAA Budding Beast
I35: Equity | J35: AAA IOP PMS / AIF
I36: Equity | J36: Nippon India Multi Cap Fund(G)
I37: Equity | J37: SBI Contra Fund-Reg(G)
I38: Equity | J38: Abakkus All Cap PMS
I39: Equity | J39: Renaissance India Next Portfolio
I40: Equity | J40: Parag Parikh Flexi Cap Fund-Reg(G)
I41: Equity | J41: UTI Flexi Cap Fund-Reg(G)
... I59: Debt | J59: Edelweiss Multi Asset Allocation Fund

Sheet sheet_2
A1: ISIN | B1: Scheme Name | C1: Company Name | D1: Holding (%) | E1: Portfolio Weight Stock | F1: Sector | G1: Portfolio Weight Sector | M1: ISIN | N1: Scheme Name | O1: Company Name | P1: Holding (%) | Q1: Portfolio Weight Stock | R1: Sector | S1: Portfolio Weight Sector | X1: Unique ISIN | Z1: ISIN | AB1: ISIN Unique | AC1: Unique Stock | AD1: Unique Sector | AE1: P/E | AF1: ROE | AG1: Net Income | AH1: Reported EPS | AI1: MCAP | AK1: {='Output Dashboard '!$A$4:$A$30} -> Selected Funds | AL1: Allocation | AM1: Rebaced Allocation
A2: INE470A01017 | B2: Canara Rob Emerg Equities Fund-Reg(G) | C2: {=VLOOKUP($A$2:$A$1175,$AB$1:$AD$477,2,FALSE)} -> 3M India Ltd | D2: 0.0089298113 | E2: =_xlfn.IFNA(D2*VLOOKUP($B2,$AK$1:$AM$34,3,FALSE),0) -> 0.00074415094 | F2: {=VLOOKUP($A$2:$A$1175,$AB$1:$AD$477,3,FALSE)} -> Industrials | G2: =_xlfn.IFNA(D2*VLOOKUP($B2,$AK$1:$AM$34,3,FALSE),0) -> 0.00074415094 | M2: INE466L01038 | N2: Edelweiss Balanced Advantage Fund-Reg(G) | O2: {=VLOOKUP($M$2:$M$377,$AB$1:$AD$477,2,FALSE)} -> 360 ONE WAM Ltd | P2: 0.0032918203 | Q2: =P2*VLOOKUP(N2,'Selector Sheet '!$B$13:$D$43,2,FALSE) -> 0 | R2: {=VLOOKUP($M$2:$M$377,$AB$1:$AD$477,3,FALSE)} -> Financials | S2: =P2*VLOOKUP(N2,'Selector Sheet '!$B$13:$D$43,2,FALSE) -> 0 | X2: {=_xlfn.UNIQUE(Z2:Z1177)} -> INE470A01017 | Z2: INE470A01017 | AB2: INE470A01017 | AC2: 3M India Ltd | AD2: Industrials | AE2: 71.863811 | AF2: 23.842709 | AG2: 4760.674 | AH2: 422.60492 | AI2: 342120175900 | AK2: Large Cap | AL2: {=_xlfn.IFNA(VLOOKUP($AK$2:$AK$34,'Selector Sheet '!$B$14:$D$59,2,FALSE),"")} | AM2: {=_xlfn.IFNA((_xlfn.ANCHORARRAY($AL$2)*1),0)/SUM(_xlfn.ANCHORARRAY($AL$2))} -> #VALUE!
A3: INE117A01022 | B3: Canara Rob Emerg Equities Fund-Reg(G) | C3: ABB India Ltd | D3: 0.010443693 | E3: =_xlfn.IFNA(D3*VLOOKUP($B3,$AK$1:$AM$34,3,FALSE),0) -> 0.00087030776 | F3: Industrials | G3: =_xlfn.IFNA(D3*VLOOKUP($B3,$AK$1:$AM$34,3,FALSE),0) -> 0.00087030776 | M3: INE769A01020 | N3: Edelweiss Balanced Advantage Fund-Reg(G) | O3: Aarti Industries Ltd | P3: 0.003937559 | Q3: =P3*VLOOKUP(N3,'Selector Sheet '!$B$13:$D$43,2,FALSE) -> 0 | R3: Materials | S3: =P3*VLOOKUP(N3,'Selector Sheet '!$B$13:$D$43,2,FALSE) -> 0 | X3: INE117A01022 | Z3: INE117A01022 | AB3: INE117A01022 | AC3: ABB India Ltd | AD3: Industrials | AE3: 57.161429 | AF3: 28.75023 | AG3: 18716.4 | AH3: 88.32 | AI3: 1.0715147e+12 | AK3: Renaissance Opportunities Fund PMS | AL3: 0.5 | AM3: 0.41666667
A4: INE358A01014 | B4: Canara Rob Emerg Equities Fund-Reg(G) | C4: Abbott India Ltd | D4: 0.019530534 | E4: =_xlfn.IFNA(D4*VLOOKUP($B4,$AK$1:$AM$34,3,FALSE),0) -> 0.0016275445 | F4: Health Care | G4: =_xlfn.IFNA(D4*VLOOKUP($B4,$AK$1:$AM$34,3,FALSE),0) -> 0.0016275445 | M4: INE358A01014 | N4: Edelweiss Balanced Advantage Fund-Reg(G) | O4: Abbott India Ltd | P4: 0.0048174024 | Q4: =P4*VLOOKUP(N4,'Selector Sheet '!$B$13:$D$43,2,FALSE) -> 0 | R4: Health Care | S4: =P4*VLOOKUP(N4,'Selector Sheet '!$B$13:$D$43,2,FALSE) -> 0 | X4: INE358A01014 | Z4: INE358A01014 | AB4: INE358A01014 | AC4: Abbott India Ltd | AD4: Health Care | AE4: 49.803191 | AF4: 35.663965 | AG4: 14144.4 | AH4: 665.62 | AI4: 704414361300 | AK4: Nippon India Large Cap Fund(G) | AL4: 0.5 | AM4: 0.41666667
A5: INE055A01016 | B5: Canara Rob Emerg Equities Fund-Reg(G) | C5: Aditya Birla Real Estate Ltd | D5: 0.01088189 | E5: =_xlfn.IFNA(D5*VLOOKUP($B5,$AK$1:$AM$34,3,FALSE),0) -> 0.00090682418 | F5: Materials | G5: =_xlfn.IFNA(D5*VLOOKUP($B5,$AK$1:$AM$34,3,FALSE),0) -> 0.00090682418 | M5: INE674K01013 | N5: Edelweiss Balanced Advantage Fund-Reg(G) | O5: Aditya Birla Capital Ltd | P5: 0.0033089173 | Q5: =P5*VLOOKUP(N5,'Selector Sheet '!$B$13:$D$43,2,FALSE) -> 0 | R5: Financials | S5: =P5*VLOOKUP(N5,'Selector Sheet '!$B$13:$D$43,2,FALSE) -> 0 | X5: INE055A01016 | Z5: INE055A01016 | AB5: INE055A01016 | AC5: Aditya Birla Real Estate Ltd | AD5: Materials | AE5: #N/A N/A | AF5: -4.12513 | AG5: -1612.8 | AH5: -14.596217 | AI5: 200259184672 | AK5: 0 | AM5: #VALUE!
A6: INE031B01049 | B6: Canara Rob Emerg Equities Fund-Reg(G) | C6: Ajanta Pharma Ltd | D6: 0.0090296641 | E6: =_xlfn.IFNA(D6*VLOOKUP($B6,$AK$1:$AM$34,3,FALSE),0) -> 0.00075247201 | F6: Health Care | G6: =_xlfn.IFNA(D6*VLOOKUP($B6,$AK$1:$AM$34,3,FALSE),0) -> 0.00075247201 | M6: INE0CZ201020 | N6: Edelweiss Balanced Advantage Fund-Reg(G) | O6: Anthem Biosciences Ltd | P6: 0.00080173819 | Q6: =P6*VLOOKUP(N6,'Selector Sheet '!$B$13:$D$43,2,FALSE) -> 0 | R6: Health Care | S6: =P6*VLOOKUP(N6,'Selector Sheet '!$B$13:$D$43,2,FALSE) -> 0 | X6: INE031B01049 | Z6: INE031B01049 | AB6: INE031B01049 | AC6: Ajanta Pharma Ltd | AD6: Health Care | AE6: 36.352639 | AF6: 25.018586 | AG6: 9203.9 | AH6: 73.56 | AI6: 3.3409035e+11 | AK6: 0 | AM6: #VALUE!
A7: INE732I01013 | B7: Canara Rob Emerg Equities Fund-Reg(G) | C7: Angel One Ltd | D7: 0 | E7: =_xlfn.IFNA(D7*VLOOKUP($B7,$AK$1:$AM$34,3,FALSE),0) -> 0 | F7: Financials | G7: =_xlfn.IFNA(D7*VLOOKUP($B7,$AK$1:$AM$34,3,FALSE),0) -> 0 | M7: INE437A01024 | N7: Edelweiss Balanced Advantage Fund-Reg(G) | O7: Apollo Hospitals Enterprise Lt | P7: 0.010912148 | Q7: =P7*VLOOKUP(N7,'Selector Sheet '!$B$13:$D$43,2,FALSE) -> 0 | R7: Health Care | S7: =P7*VLOOKUP(N7,'Selector Sheet '!$B$13:$D$43,2,FALSE) -> 0 | X7: INE732I01013 | Z7: INE732I01013 | AB7: INE732I01013 | AC7: Angel One Ltd | AD7: Financials | AE7: 20.832372 | AF7: 27.068842 | AG7: 11720.81 | AH7: 130.05 | AI7: 245561456654 | AK7: 0 | AM7: #VALUE!
A8: INE702C01027 | B8: Canara Rob Emerg Equities Fund-Reg(G) | C8: APL Apollo Tubes Ltd | D8: 0.0029338442 | E8: =_xlfn.IFNA(D8*VLOOKUP($B8,$AK$1:$AM$34,3,FALSE),0) -> 0.00024448702 | F8: Materials | G8: =_xlfn.IFNA(D8*VLOOKUP($B8,$AK$1:$AM$34,3,FALSE),0) -> 0.00024448702 | M8: INE852O01025 | N8: Edelweiss Balanced Advantage Fund-Reg(G) | O8: Aptus Value Housing Finance In | P8: 0 | Q8: =P8*VLOOKUP(N8,'Selector Sheet '!$B$13:$D$43,2,FALSE) -> 0 | R8: Financials | S8: =P8*VLOOKUP(N8,'Selector Sheet '!$B$13:$D$43,2,FALSE) -> 0 | X8: INE702C01027 | Z8: INE702C01027 | AB8: INE702C01027 | AC8: APL Apollo Tubes Ltd | AD8: Materials | AE8: 58.764662 | AF8: 19.378652 | AG8: 7570.6 | AH8: 27.28 | AI8: 4.4489963e+11 | AK8: 0 | AM8: #VALUE!
A9: INE955V01021 | B9: Canara Rob Emerg Equities Fund-Reg(G) | C9: Arvind Fashions Ltd | D9: 0.0016182473 | E9: =_xlfn.IFNA(D9*VLOOKUP($B9,$AK$1:$AM$34,3,FALSE),0) -> 0.00013485394 | F9: Consumer Discretionary | G9: =_xlfn.IFNA(D9*VLOOKUP($B9,$AK$1:$AM$34,3,FALSE),0) -> 0.00013485394 | M9: INE949L01017 | N9: Edelweiss Balanced Advantage Fund-Reg(G) | O9: AU Small Finance Bank Ltd | P9: 0.0058606252 | Q9: =P9*VLOOKUP(N9,'Selector Sheet '!$B$13:$D$43,2,FALSE) -> 0 | R9: Financials | S9: =P9*VLOOKUP(N9,'Selector Sheet '!$B$13:$D$43,2,FALSE) -> 0 | X9: INE955V01021 | Z9: INE955V01021 | AB9: INE955V01021 | AC9: Arvind Fashions Ltd | AD9: Consumer Discretionary | AE9: #N/A N/A | AF9: -3.6288327 | AG9: -355.7 | AH9: -2.67 | AI9: 6.9394382e+10 | AK9: Large -Mid Cap | AM9: #VALUE!
A10: INE917I01010 | B10: Canara Rob Emerg Equities Fund-Reg(G) | C10: Bajaj Auto Ltd | D10: 0.0084344963 | E10: =_xlfn.IFNA(D10*VLOOKUP($B10,$AK$1:$AM$34,3,FALSE),0) -> 0.00070287469 | F10: Consumer Discretionary | G10: =_xlfn.IFNA(D10*VLOOKUP($B10,$AK$1:$AM$34,3,FALSE),0) -> 0.00070287469 | M10: INE192R01011 | N10: Edelweiss Balanced Advantage Fund-Reg(G) | O10: Avenue Supermarts Ltd | P10: 0.0060445569 | Q10: =P10*VLOOKUP(N10,'Selector Sheet '!$B$13:$D$43,2,FALSE) -> 0 | R10: Consumer Staples | S10: =P10*VLOOKUP(N10,'Selector Sheet '!$B$13:$D$43,2,FALSE) -> 0 | X10: INE917I01010 | Z10: INE917I01010 | AB10: INE917I01010 | AC10: Bajaj Auto Ltd | AD10: Consumer Discretionary | AE10: 32.712504 | AF10: 22.835849 | AG10: 73247.3 | AH10: 262.43788 | AI10: 2397426564680 | AK10: SBI Large & Midcap Fund-Reg(G) | AL10: 0.1 | AM10: 0.083333333
A11: INE296A01032 | B11: Canara Rob Emerg Equities Fund-Reg(G) | C11: Bajaj Finance Ltd | D11: 0.011779141 | E11: =_xlfn.IFNA(D11*VLOOKUP($B11,$AK$1:$AM$34,3,FALSE),0) -> 0.00098159507 | F11: Financials | G11: =_xlfn.IFNA(D11*VLOOKUP($B11,$AK$1:$AM$34,3,FALSE),0) -> 0.00098159507 | M11: INE238A01034 | N11: Edelweiss Balanced Advantage Fund-Reg(G) | O11: Axis Bank Ltd | P11: 0.014560785 | Q11: =P11*VLOOKUP(N11,'Selector Sheet '!$B$13:$D$43,2,FALSE) -> 0 | R11: Financials | S11: =P11*VLOOKUP(N11,'Selector Sheet '!$B$13:$D$43,2,FALSE) -> 0 | X11: INE296A01032 | Z11: INE296A01032 | AB11: INE296A01032 | AC11: Bajaj Finance Ltd | AD11: Financials | AE11: 33.884881 | AF11: 19.191408 | AG11: 166378.2 | AH11: 26.894 | AI11: 5663079305676 | AK11: Canara Rob Emerg Equities Fund-Reg(G) | AL11: 0.1 | AM11: 0.083333333
A12: INE176A01028 | B12: Canara Rob Emerg Equities Fund-Reg(G) | C12: Bata India Ltd | D12: 0.0095276288 | E12: =_xlfn.IFNA(D12*VLOOKUP($B12,$AK$1:$AM$34,3,FALSE),0) -> 0.00079396907 | F12: Consumer Discretionary | G12: =_xlfn.IFNA(D12*VLOOKUP($B12,$AK$1:$AM$34,3,FALSE),0) -> 0.00079396907 | M12: INE296A01032 | N12: Edelweiss Balanced Advantage Fund-Reg(G) | O12: Bajaj Finance Ltd | P12: 0.019740352 | Q12: =P12*VLOOKUP(N12,'Selector Sheet '!$B$13:$D$43,2,FALSE) -> 0 | R12: Financials | S12: =P12*VLOOKUP(N12,'Selector Sheet '!$B$13:$D$43,2,FALSE) -> 0 | X12: INE176A01028 | Z12: INE176A01028 | AB12: INE176A01028 | AC12: Bata India Ltd | AD12: Consumer Discretionary | AE12: 42.66226 | AF12: 21.320554 | AG12: 3306.56 | AH12: 25.73 | AI12: 141084680658 | AK12: 0 | AM12: #VALUE!
A13: INE463A01038 | B13: Canara Rob Emerg Equities Fund-Reg(G) | C13: Berger Paints India Ltd | D13: 0.0012555005 | E13: =_xlfn.IFNA(D13*VLOOKUP($B13,$AK$1:$AM$34,3,FALSE),0) -> 0.00010462504 | F13: Materials | G13: =_xlfn.IFNA(D13*VLOOKUP($B13,$AK$1:$AM$34,3,FALSE),0) -> 0.00010462504 | M13: INE918I01026 | N13: Edelweiss Balanced Advantage Fund-Reg(G) | O13: Bajaj Finserv Ltd | P13: 0.005967335 | Q13: =P13*VLOOKUP(N13,'Selector Sheet '!$B$13:$D$43,2,FALSE) -> 0 | R13: Financials | S13: =P13*VLOOKUP(N13,'Selector Sheet '!$B$13:$D$43,2,FALSE) -> 0 | X13: INE463A01038 | Z13: INE463A01038 | AB13: INE463A01038 | AC13: Berger Paints India Ltd | AD13: Materials | AE13: 52.979251 | AF13: 20.469832 | AG13: 11804 | AH13: 10.13 | AI13: 6.2509449e+11 | AK13: 0 | AM13: #VALUE!
A14: INE263A01024 | B14: Canara Rob Emerg Equities Fund-Reg(G) | C14: Bharat Electronics Ltd | D14: 0.033937554 | E14: =_xlfn.IFNA(D14*VLOOKUP($B14,$AK$1:$AM$34,3,FALSE),0) -> 0.0028281295 | F14: Industrials | G14: =_xlfn.IFNA(D14*VLOOKUP($B14,$AK$1:$AM$34,3,FALSE),0) -> 0.0028281295 | M14: INE263A01024 | N14: Edelweiss Balanced Advantage Fund-Reg(G) | O14: Bharat Electronics Ltd | P14: 0.0061181202 | Q14: =P14*VLOOKUP(N14,'Selector Sheet '!$B$13:$D$43,2,FALSE) -> 0 | R14: Industrials | S14: =P14*VLOOKUP(N14,'Selector Sheet '!$B$13:$D$43,2,FALSE) -> 0 | X14: INE263A01024 | Z14: INE263A01024 | AB14: INE263A01024 | AC14: Bharat Electronics Ltd | AD14: Industrials | AE14: 53.166207 | AF14: 29.318938 | AG14: 53214.4 | AH14: 7.28 | AI14: 2.8292499e+12 | AK14: Mid/Small cap | AM14: #VALUE!
A15: INE465A01025 | B15: Canara Rob Emerg Equities Fund-Reg(G) | C15: Bharat Forge Ltd | D15: 0.0063286755 | E15: =_xlfn.IFNA(D15*VLOOKUP($B15,$AK$1:$AM$34,3,FALSE),0) -> 0.00052738962 | F15: Consumer Discretionary | G15: =_xlfn.IFNA(D15*VLOOKUP($B15,$AK$1:$AM$34,3,FALSE),0) -> 0.00052738962 | M15: INE029A01011 | N15: Edelweiss Balanced Advantage Fund-Reg(G) | O15: Bharat Petroleum Corp Ltd | P15: 0.0051262275 | Q15: =P15*VLOOKUP(N15,'Selector Sheet '!$B$13:$D$43,2,FALSE) -> 0 | R15: Energy | S15: =P15*VLOOKUP(N15,'Selector Sheet '!$B$13:$D$43,2,FALSE) -> 0 | X15: INE465A01025 | Z15: INE465A01025 | AB15: INE465A01025 | AC15: Bharat Forge Ltd | AD15: Consumer Discretionary | AE15: 59.276808 | AF15: 11.46104 | AG15: 9411.53 | AH15: 20.05 | AI15: 568208339132 | AK15: No funds selected | AM15: #VALUE!
A16: INE397D01024 | B16: Canara Rob Emerg Equities Fund-Reg(G) | C16: Bharti Airtel Ltd | D16: 0.015415422 | E16: =_xlfn.IFNA(D16*VLOOKUP($B16,$AK$1:$AM$34,3,FALSE),0) -> 0.0012846185 | F16: Communication Services | G16: =_xlfn.IFNA(D16*VLOOKUP($B16,$AK$1:$AM$34,3,FALSE),0) -> 0.0012846185 | M16: INE397D01024 | N16: Edelweiss Balanced Advantage Fund-Reg(G) | O16: Bharti Airtel Ltd | P16: 0.026476013 | Q16: =P16*VLOOKUP(N16,'Selector Sheet '!$B$13:$D$43,2,FALSE) -> 0 | R16: Communication Services | S16: =P16*VLOOKUP(N16,'Selector Sheet '!$B$13:$D$43,2,FALSE) -> 0 | X16: INE397D01024 | Z16: INE397D01024 | AB16: INE397D01024 | AC16: Bharti Airtel Ltd | AD16: Communication Services | AE16: 30.824184 | AF16: 33.979762 | AG16: 335561 | AH16: 58 | AI16: 1.1286222e+13 | AK16: 0 | AM16: #VALUE!
A17: INE343G01021 | B17: Canara Rob Emerg Equities Fund-Reg(G) | C17: Bharti Hexacom Ltd | D17: 0.0048441784 | E17: =_xlfn.IFNA(D17*VLOOKUP($B17,$AK$1:$AM$34,3,FALSE),0) -> 0.00040368154 | F17: Communication Services | G17: =_xlfn.IFNA(D17*VLOOKUP($B17,$AK$1:$AM$34,3,FALSE),0) -> 0.00040368154 | M17: INE376G01013 | N17: Edelweiss Balanced Advantage Fund-Reg(G) | O17: Biocon Ltd | P17: 0 | Q17: =P17*VLOOKUP(N17,'Selector Sheet '!$B$13:$D$43,2,FALSE) -> 0 | R17: Health Care | S17: =P17*VLOOKUP(N17,'Selector Sheet '!$B$13:$D$43,2,FALSE) -> 0 | X17: INE343G01021 | Z17: INE343G01021 | AB17: INE343G01021 | AC17: Bharti Hexacom Ltd | AD17: Communication Services | AE17: 61.200875 | AF17: 23.952096 | AG17: 14936 | AH17: 29.87 | AI17: 840900000000 | AK17: Multicap | AM17: #VALUE!
A18: INE376G01013 | B18: Canara Rob Emerg Equities Fund-Reg(G) | C18: Biocon Ltd | D18: 0.00089804128 | E18: =_xlfn.IFNA(D18*VLOOKUP($B18,$AK$1:$AM$34,3,FALSE),0) -> 7.4836774e-05 | F18: Health Care | G18: =_xlfn.IFNA(D18*VLOOKUP($B18,$AK$1:$AM$34,3,FALSE),0) -> 7.4836774e-05 | M18: INE791I01019 | N18: Edelweiss Balanced Advantage Fund-Reg(G) | O18: Brigade Enterprises Ltd | P18: 0.0055044257 | Q18: =P18*VLOOKUP(N18,'Selector Sheet '!$B$13:$D$43,2,FALSE) -> 0 | R18: Real Estate | S18: =P18*VLOOKUP(N18,'Selector Sheet '!$B$13:$D$43,2,FALSE) -> 0 | X18: INE376G01013 | Z18: INE376G01013 | AB18: INE376G01013 | AC18: Biocon Ltd | AD18: Health Care | AE18: 112.90959 | AF18: #N/A N/A | AG18: 10133 | AH18: 8.46 | AI18: 485585192232 | AK18: No funds selected | AM18: #VALUE!
A19: INE233B01017 | B19: Canara Rob Emerg Equities Fund-Reg(G) | C19: Blue Dart Express Ltd | D19: 0.0041084308 | E19: =_xlfn.IFNA(D19*VLOOKUP($B19,$AK$1:$AM$34,3,FALSE),0) -> 0.00034236923 | F19: Industrials | G19: =_xlfn.IFNA(D19*VLOOKUP($B19,$AK$1:$AM$34,3,FALSE),0) -> 0.00034236923 | M19: INE216A01030 | N19: Edelweiss Balanced Advantage Fund-Reg(G) | O19: Britannia Industries Ltd | P19: 0.0039639511 | Q19: =P19*VLOOKUP(N19,'Selector Sheet '!$B$13:$D$43,2,FALSE) -> 0 | R19: Consumer Staples | S19: =P19*VLOOKUP(N19,'Selector Sheet '!$B$13:$D$43,2,FALSE) -> 0 | X19: INE233B01017 | Z19: INE233B01017 | AB19: INE233B01017 | AC19: Blue Dart Express Ltd | AD19: Industrials | AE19: 56.361896 | AF19: #N/A N/A | AG19: 2524.2 | AH19: 106.38 | AI19: 139686347458 | AK19: 0 | AM19: #VALUE!
A20: INE118H01025 | B20: Canara Rob Emerg Equities Fund-Reg(G) | C20: BSE Ltd | D20: 0.0021375813 | E20: =_xlfn.IFNA(D20*VLOOKUP($B20,$AK$1:$AM$34,3,FALSE),0) -> 0.00017813178 | F20: Financials | G20: =_xlfn.IFNA(D20*VLOOKUP($B20,$AK$1:$AM$34,3,FALSE),0) -> 0.00017813178 | M20: INE0V7W01012 | N20: Edelweiss Balanced Advantage Fund-Reg(G) | O20: Carraro India Ltd | P20: 0.0010440436 | Q20: =P20*VLOOKUP(N20,'Selector Sheet '!$B$13:$D$43,2,FALSE) -> 0 | R20: Industrials | S20: =P20*VLOOKUP(N20,'Selector Sheet '!$B$13:$D$43,2,FALSE) -> 0 | X20: INE118H01025 | Z20: INE118H01025 | AB20: INE118H01025 | AC20: BSE Ltd | AD20: Financials | AE20: 77.706109 | AF20: 34.322717 | AG20: 13258.9 | AH20: 32.653368 | AI20: 1.02641e+12 | AK20: 0 | AM20: #VALUE!
A21: INE120A01034 | B21: Canara Rob Emerg Equities Fund-Reg(G) | C21: Carborundum Universal Ltd | D21: 0.0023179058 | E21: =_xlfn.IFNA(D21*VLOOKUP($B21,$AK$1:$AM$34,3,FALSE),0) -> 0.00019315882 | F21: Materials | G21: =_xlfn.IFNA(D21*VLOOKUP($B21,$AK$1:$AM$34,3,FALSE),0) -> 0.00019315882 | M21: INE067A01029 | N21: Edelweiss Balanced Advantage Fund-Reg(G) | O21: CG Power & Industrial Solution | P21: 0.0058782773 | Q21: =P21*VLOOKUP(N21,'Selector Sheet '!$B$13:$D$43,2,FALSE) -> 0 | R21: Industrials | S21: =P21*VLOOKUP(N21,'Selector Sheet '!$B$13:$D$43,2,FALSE) -> 0 | X21: INE120A01034 | Z21: INE120A01034 | AB21: INE120A01034 | AC21: Carborundum Universal Ltd | AD21: Materials | AE21: 55.458921 | AF21: 8.7984529 | AG21: 2927.39 | AH21: 15.58 | AI21: 1.6453561e+11 | AK21: 0 | AM21: #VALUE!
A22: INE0LMW01024 | B22: Canara Rob Emerg Equities Fund-Reg(G) | C22: Cello World Ltd | D22: 0.0036229198 | E22: =_xlfn.IFNA(D22*VLOOKUP($B22,$AK$1:$AM$34,3,FALSE),0) -> 0.00030190998 | F22: Consumer Discretionary | G22: =_xlfn.IFNA(D22*VLOOKUP($B22,$AK$1:$AM$34,3,FALSE),0) -> 0.00030190998 | M22: INE149A01033 | N22: Edelweiss Balanced Advantage Fund-Reg(G) | O22: Cholamandalam Financial Holdin | P22: 0.0087977235 | Q22: =P22*VLOOKUP(N22,'Selector Sheet '!$B$13:$D$43,2,FALSE) -> 0 | R22: Financials | S22: =P22*VLOOKUP(N22,'Selector Sheet '!$B$13:$D$43,2,FALSE) -> 0 | X22: INE0LMW01024 | Z22: INE0LMW01024 | AB22: INE0LMW01024 | AC22: Cello World Ltd | AD22: Consumer Discretionary | AE22: 34.483871 | AF22: 20.431352 | AG22: 3388.152 | AH22: 15.5 | AI22: 118063050673 | AK22: 0 | AM22: #VALUE!
A23: INE736A01011 | B23: Canara Rob Emerg Equities Fund-Reg(G) | C23: Central Depository Services In | D23: 0.0046720808 | E23: =_xlfn.IFNA(D23*VLOOKUP($B23,$AK$1:$AM$34,3,FALSE),0) -> 0.00038934006 | F23: Financials | G23: =_xlfn.IFNA(D23*VLOOKUP($B23,$AK$1:$AM$34,3,FALSE),0) -> 0.00038934006 | M23: INE121A01024 | N23: Edelweiss Balanced Advantage Fund-Reg(G) | O23: Cholamandalam Investment and F | P23: 0.00480208 | Q23: =P23*VLOOKUP(N23,'Selector Sheet '!$B$13:$D$43,2,FALSE) -> 0 | R23: Financials | S23: =P23*VLOOKUP(N23,'Selector Sheet '!$B$13:$D$43,2,FALSE) -> 0 | X23: INE736A01011 | Z23: INE736A01011 | AB23: INE736A01011 | AC23: Central Depository Services In | AD23: Financials | AE23: 62.884919 | AF23: 32.673211 | AG23: 5266.412 | AH23: 25.2 | AI23: 331202300000 | AK23: 0 | AM23: #VALUE!
A24: INE067A01029 | B24: Canara Rob Emerg Equities Fund-Reg(G) | C24: CG Power & Industrial Solution | D24: 0.0050800085 | E24: =_xlfn.IFNA(D24*VLOOKUP($B24,$AK$1:$AM$34,3,FALSE),0) -> 0.00042333404 | F24: Industrials | G24: =_xlfn.IFNA(D24*VLOOKUP($B24,$AK$1:$AM$34,3,FALSE),0) -> 0.00042333404 | M24: INE059A01026 | N24: Edelweiss Balanced Advantage Fund-Reg(G) | O24: Cipla Ltd/India | P24: 0.010508254 | Q24: =P24*VLOOKUP(N24,'Selector Sheet '!$B$13:$D$43,2,FALSE) -> 0 | R24: Health Care | S24: =P24*VLOOKUP(N24,'Selector Sheet '!$B$13:$D$43,2,FALSE) -> 0 | X24: INE067A01029 | Z24: INE067A01029 | AB24: INE067A01029 | AC24: CG Power & Industrial Solution | AD24: Industrials | AE24: 105.87774 | AF24: 28.408238 | AG24: 9746 | AH24: 6.38 | AI24: 1.0636095e+12 | AK24: 0 | AM24: #VALUE!
A25: INE121A01024 | B25: Canara Rob Emerg Equities Fund-Reg(G) | C25: Cholamandalam Investment and F | D25: 0.019405277 | E25: =_xlfn.IFNA(D25*VLOOKUP($B25,$AK$1:$AM$34,3,FALSE),0) -> 0.0016171064 | F25: Financials | G25: =_xlfn.IFNA(D25*VLOOKUP($B25,$AK$1:$AM$34,3,FALSE),0) -> 0.0016171064 | M25: INE522F01014 | N25: Edelweiss Balanced Advantage Fund-Reg(G) | O25: Coal India Ltd | P25: 0.0041949992 | Q25: =P25*VLOOKUP(N25,'Selector Sheet '!$B$13:$D$43,2,FALSE) -> 0 | R25: Energy | S25: =P25*VLOOKUP(N25,'Selector Sheet '!$B$13:$D$43,2,FALSE) -> 0 | X25: INE121A01024 | Z25: INE121A01024 | AB25: INE121A01024 | AC25: Cholamandalam Investment and F | AD25: Financials | AE25: 30.029574 | AF25: 19.706472 | AG25: 42627 | AH25: 50.72 | AI25: 1.2812444e+12 | AK25: 0 | AM25: #VALUE!
A26: INE591G01025 | B26: Canara Rob Emerg Equities Fund-Reg(G) | C26: Coforge Ltd | D26: 0.0091233018 | E26: =_xlfn.IFNA(D26*VLOOKUP($B26,$AK$1:$AM$34,3,FALSE),0) -> 0.00076027515 | F26: Information Technology | G26: =_xlfn.IFNA(D26*VLOOKUP($B26,$AK$1:$AM$34,3,FALSE),0) -> 0.00076027515 | M26: INE591G01025 | N26: Edelweiss Balanced Advantage Fund-Reg(G) | O26: Coforge Ltd | P26: 0.0059364712 | Q26: =P26*VLOOKUP(N26,'Selector Sheet '!$B$13:$D$43,2,FALSE) -> 0 | R26: Information Technology | S26: =P26*VLOOKUP(N26,'Selector Sheet '!$B$13:$D$43,2,FALSE) -> 0 | X26: INE591G01025 | Z26: INE591G01025 | AB26: INE591G01025 | AC26: Coforge Ltd | AD26: Information Technology | AE26: 29.043865 | AF26: 15.9812 | AG26: 8121 | AH26: 24.602 | AI26: 556046341326 | AK26: 0 | AM26: #VALUE!
A27: INE596I01012 | B27: Canara Rob Emerg Equities Fund-Reg(G) | C27: Computer Age Management Servic | D27: 0.0022051727 | E27: =_xlfn.IFNA(D27*VLOOKUP($B27,$AK$1:$AM$34,3,FALSE),0) -> 0.00018376439 | F27: Industrials | G27: =_xlfn.IFNA(D27*VLOOKUP($B27,$AK$1:$AM$34,3,FALSE),0) -> 0.00018376439 | M27: INE169A01031 | N27: Edelweiss Balanced Advantage Fund-Reg(G) | O27: Coromandel International Ltd | P27: 0.0043909386 | Q27: =P27*VLOOKUP(N27,'Selector Sheet '!$B$13:$D$43,2,FALSE) -> 0 | R27: Materials | S27: =P27*VLOOKUP(N27,'Selector Sheet '!$B$13:$D$43,2,FALSE) -> 0 | X27: INE596I01012 | Z27: INE596I01012 | AB27: INE596I01012 | AC27: Computer Age Management Servic | AD27: Industrials | AE27: 40.579603 | AF27: 46.254181 | AG27: 4701.938 | AH27: 95.41 | AI27: 1.9155146e+11 | AK27: 0 | AM27: #VALUE!
A28: INE111A01025 | B28: Canara Rob Emerg Equities Fund-Reg(G) | C28: Container Corp Of India Ltd | D28: 0.0015099641 | E28: =_xlfn.IFNA(D28*VLOOKUP($B28,$AK$1:$AM$34,3,FALSE),0) -> 0.00012583034 | F28: Industrials | G28: =_xlfn.IFNA(D28*VLOOKUP($B28,$AK$1:$AM$34,3,FALSE),0) -> 0.00012583034 | M28: INE00LO01017 | N28: Edelweiss Balanced Advantage Fund-Reg(G) | O28: Craftsman Automation Ltd | P28: 0.0059649819 | Q28: =P28*VLOOKUP(N28,'Selector Sheet '!$B$13:$D$43,2,FALSE) -> 0 | R28: Industrials | S28: =P28*VLOOKUP(N28,'Selector Sheet '!$B$13:$D$43,2,FALSE) -> 0 | X28: INE111A01025 | Z28: INE111A01025 | AB28: INE111A01025 | AC28: Container Corp Of India Ltd | AD28: Industrials | AE28: 31.676215 | AF28: 10.64933 | AG28: 12887.5 | AH28: 16.921214 | AI28: 408227213160 | AM28: #VALUE!
A29: INE741K01010 | B29: Canara Rob Emerg Equities Fund-Reg(G) | C29: CreditAccess Grameen Ltd | D29: 0.0097568875 | E29: =_xlfn.IFNA(D29*VLOOKUP($B29,$AK$1:$AM$34,3,FALSE),0) -> 0.00081307396 | F29: Financials | G29: =_xlfn.IFNA(D29*VLOOKUP($B29,$AK$1:$AM$34,3,FALSE),0) -> 0.00081307396 | M29: INE935N01020 | N29: Edelweiss Balanced Advantage Fund-Reg(G) | O29: Dixon Technologies India Ltd | P29: 0.0041538632 | Q29: =P29*VLOOKUP(N29,'Selector Sheet '!$B$13:$D$43,2,FALSE) -> 0 | R29: Consumer Discretionary | S29: =P29*VLOOKUP(N29,'Selector Sheet '!$B$13:$D$43,2,FALSE) -> 0 | X29: INE741K01010 | Z29: INE741K01010 | AB29: INE741K01010 | AC29: CreditAccess Grameen Ltd | AD29: Financials | AE29: 39.67587 | AF29: 7.8574888 | AG29: 5314 | AH29: 33.32 | AI29: 211185613320 | AM29: #VALUE!
A30: INE299U01018 | B30: Canara Rob Emerg Equities Fund-Reg(G) | C30: Crompton Greaves Consumer Elec | D30: 0.0091307106 | E30: =_xlfn.IFNA(D30*VLOOKUP($B30,$AK$1:$AM$34,3,FALSE),0) -> 0.00076089255 | F30: Consumer Discretionary | G30: =_xlfn.IFNA(D30*VLOOKUP($B30,$AK$1:$AM$34,3,FALSE),0) -> 0.00076089255 | M30: INE089A01031 | N30: Edelweiss Balanced Advantage Fund-Reg(G) | O30: Dr Reddy's Laboratories Ltd | P30: 0.0062115401 | Q30: =P30*VLOOKUP(N30,'Selector Sheet '!$B$13:$D$43,2,FALSE) -> 0 | R30: Health Care | S30: =P30*VLOOKUP(N30,'Selector Sheet '!$B$13:$D$43,2,FALSE) -> 0 | X30: INE299U01018 | Z30: INE299U01018 | AB30: INE299U01018 | AC30: Crompton Greaves Consumer Elec | AD30: Consumer Discretionary | AE30: 37.939813 | AF30: 17.401307 | AG30: 5559.5 | AH30: 8.64 | AI30: 2.1105498e+11 | AM30: #VALUE!
A31: INE298A01020 | B31: Canara Rob Emerg Equities Fund-Reg(G) | C31: Cummins India Ltd | D31: 0.0006476441 | E31: =_xlfn.IFNA(D31*VLOOKUP($B31,$AK$1:$AM$34,3,FALSE),0) -> 5.3970342e-05 | F31: Industrials | G31: =_xlfn.IFNA(D31*VLOOKUP($B31,$AK$1:$AM$34,3,FALSE),0) -> 5.3970342e-05 | M31: INE236E01022 | N31: Edelweiss Balanced Advantage Fund-Reg(G) | O31: Ellenbarrie Industrial Gases L | P31: 0 | Q31: =P31*VLOOKUP(N31,'Selector Sheet '!$B$13:$D$43,2,FALSE) -> 0 | R31: Materials | S31: =P31*VLOOKUP(N31,'Selector Sheet '!$B$13:$D$43,2,FALSE) -> 0 | X31: INE298A01020 | Z31: INE298A01020 | AB31: INE298A01020 | AC31: Cummins India Ltd | AD31: Industrials | AE31: 53.115732 | AF31: 28.220397 | AG31: 19999.4 | AH31: 72.15 | AI31: 1062313560000 | AM31: #VALUE!
A32: INE288B01029 | B32: Canara Rob Emerg Equities Fund-Reg(G) | C32: Deepak Nitrite Ltd | D32: 0.0013046422 | E32: =_xlfn.IFNA(D32*VLOOKUP($B32,$AK$1:$AM$34,3,FALSE),0) -> 0.00010872018 | F32: Materials | G32: =_xlfn.IFNA(D32*VLOOKUP($B32,$AK$1:$AM$34,3,FALSE),0) -> 0.00010872018 | M32: INE758T01015 | N32: Edelweiss Balanced Advantage Fund-Reg(G) | O32: Eternal Ltd | P32: 0.0060391706 | Q32: =P32*VLOOKUP(N32,'Selector Sheet '!$B$13:$D$43,2,FALSE) -> 0 | R32: Consumer Discretionary | S32: =P32*VLOOKUP(N32,'Selector Sheet '!$B$13:$D$43,2,FALSE) -> 0 | X32: INE288B01029 | Z32: INE288B01029 | AB32: INE288B01029 | AC32: Deepak Nitrite Ltd | AD32: Materials | AE32: 35.554578 | AF32: 13.691117 | AG32: 6972.4 | AH32: 51.12 | AI32: 2.4790117e+11 | AM32: #VALUE!
A33: INE872J01023 | B33: Canara Rob Emerg Equities Fund-Reg(G) | C33: Devyani International Ltd | D33: 0.00068174505 | E33: =_xlfn.IFNA(D33*VLOOKUP($B33,$AK$1:$AM$34,3,FALSE),0) -> 5.6812088e-05 | F33: Consumer Discretionary | G33: =_xlfn.IFNA(D33*VLOOKUP($B33,$AK$1:$AM$34,3,FALSE),0) -> 5.6812088e-05 | M33: INE061F01013 | N33: Edelweiss Balanced Advantage Fund-Reg(G) | O33: Fortis Healthcare Ltd | P33: 0.0080255826 | Q33: =P33*VLOOKUP(N33,'Selector Sheet '!$B$13:$D$43,2,FALSE) -> 0 | R33: Health Care | S33: =P33*VLOOKUP(N33,'Selector Sheet '!$B$13:$D$43,2,FALSE) -> 0 | X33: INE872J01023 | Z33: INE872J01023 | AB33: INE872J01023 | AC33: Devyani International Ltd | AD33: Consumer Discretionary | AE33: 1937.6249 | AF33: 0.85100287 | AG33: 91.49 | AH33: 0.08 | AI33: 1.909626e+11 | AM33: #VALUE!
A34: INE935N01020 | B34: Canara Rob Emerg Equities Fund-Reg(G) | C34: Dixon Technologies India Ltd | D34: 0.035800414 | E34: =_xlfn.IFNA(D34*VLOOKUP($B34,$AK$1:$AM$34,3,FALSE),0) -> 0.0029833678 | F34: Consumer Discretionary | G34: =_xlfn.IFNA(D34*VLOOKUP($B34,$AK$1:$AM$34,3,FALSE),0) -> 0.0029833678 | M34: INE129A01019 | N34: Edelweiss Balanced Advantage Fund-Reg(G) | O34: GAIL India Ltd | P34: 0.0080325402 | Q34: =P34*VLOOKUP(N34,'Selector Sheet '!$B$13:$D$43,2,FALSE) -> 0 | R34: Utilities | S34: =P34*VLOOKUP(N34,'Selector Sheet '!$B$13:$D$43,2,FALSE) -> 0 | X34: INE935N01020 | Z34: INE935N01020 | AB34: INE935N01020 | AC34: Dixon Technologies India Ltd | AD34: Consumer Discretionary | AE34: 92.348796 | AF34: 46.568687 | AG34: 10955.4 | AH34: 181.83237 | AI34: 1015948123096 | AM34: #VALUE!
A35: INE321T01012 | B35: Canara Rob Emerg Equities Fund-Reg(G) | C35: Doms Industries Ltd | D35: 0.00092955521 | E35: =_xlfn.IFNA(D35*VLOOKUP($B35,$AK$1:$AM$34,3,FALSE),0) -> 7.7462934e-05 | F35: Industrials | G35: =_xlfn.IFNA(D35*VLOOKUP($B35,$AK$1:$AM$34,3,FALSE),0) -> 7.7462934e-05 | M35: INE200A01026 | N35: Edelweiss Balanced Advantage Fund-Reg(G) | O35: GE Vernova T&D India Ltd | P35: 0.0044380395 | Q35: =P35*VLOOKUP(N35,'Selector Sheet '!$B$13:$D$43,2,FALSE) -> 0 | R35: Industrials | S35: =P35*VLOOKUP(N35,'Selector Sheet '!$B$13:$D$43,2,FALSE) -> 0 | X35: INE321T01012 | Z35: INE321T01012 | AB35: INE321T01012 | AC35: Doms Industries Ltd | AD35: Industrials | AE35: 75.332936 | AF35: 22.268932 | AG35: 2023.367 | AH35: 33.34 | AI35: 1.5242294e+11
A36: INE600L01024 | B36: Canara Rob Emerg Equities Fund-Reg(G) | C36: Dr Lal PathLabs Ltd | D36: 0.0024085025 | E36: =_xlfn.IFNA(D36*VLOOKUP($B36,$AK$1:$AM$34,3,FALSE),0) -> 0.00020070854 | F36: Health Care | G36: =_xlfn.IFNA(D36*VLOOKUP($B36,$AK$1:$AM$34,3,FALSE),0) -> 0.00020070854 | M36: INE159A01016 | N36: Edelweiss Balanced Advantage Fund-Reg(G) | O36: GlaxoSmithKline Pharmaceutical | P36: 0.0026581597 | Q36: =P36*VLOOKUP(N36,'Selector Sheet '!$B$13:$D$43,2,FALSE) -> 0 | R36: Health Care | S36: =P36*VLOOKUP(N36,'Selector Sheet '!$B$13:$D$43,2,FALSE) -> 0 | X36: INE600L01024 | Z36: INE600L01024 | AB36: INE600L01024 | AC36: Dr Lal PathLabs Ltd | AD36: Health Care | AE36: 55.337013 | AF36: #N/A N/A | AG36: 4871.38 | AH36: 58.48 | AI36: 284384346246
A37: INE230A01023 | B37: Canara Rob Emerg Equities Fund-Reg(G) | C37: EIH Ltd | D37: 0.01809323 | E37: =_xlfn.IFNA(D37*VLOOKUP($B37,$AK$1:$AM$34,3,FALSE),0) -> 0.0015077691 | F37: Consumer Discretionary | G37: =_xlfn.IFNA(D37*VLOOKUP($B37,$AK$1:$AM$34,3,FALSE),0) -> 0.0015077691 | M37: INE935A01035 | N37: Edelweiss Balanced Advantage Fund-Reg(G) | O37: Glenmark Pharmaceuticals Ltd | P37: 0.0026693545 | Q37: =P37*VLOOKUP(N37,'Selector Sheet '!$B$13:$D$43,2,FALSE) -> 0 | R37: Health Care | S37: =P37*VLOOKUP(N37,'Selector Sheet '!$B$13:$D$43,2,FALSE) -> 0 | X37: INE230A01023 | Z37: INE230A01023 | AB37: INE230A01023 | AC37: EIH Ltd | AD37: Consumer Discretionary | AE37: 33.248731 | AF37: 17.292131 | AG37: 7394.45 | AH37: 11.82 | AI37: 245768123526
A38: INE758T01015 | B38: Canara Rob Emerg Equities Fund-Reg(G) | C38: Eternal Ltd | D38: 0.030623464 | E38: =_xlfn.IFNA(D38*VLOOKUP($B38,$AK$1:$AM$34,3,FALSE),0) -> 0.0025519553 | F38: Consumer Discretionary | G38: =_xlfn.IFNA(D38*VLOOKUP($B38,$AK$1:$AM$34,3,FALSE),0) -> 0.0025519553 | M38: INE101D01020 | N38: Edelweiss Balanced Advantage Fund-Reg(G) | O38: Granules India Ltd | P38: 0.008203526 | Q38: =P38*VLOOKUP(N38,'Selector Sheet '!$B$13:$D$43,2,FALSE) -> 0 | R38: Health Care | S38: =P38*VLOOKUP(N38,'Selector Sheet '!$B$13:$D$43,2,FALSE) -> 0 | X38: INE758T01015 | Z38: INE758T01015 | AB38: INE758T01015 | AC38: Eternal Ltd | AD38: Consumer Discretionary | AE38: 937.79414 | AF38: 1.1613455 | AG38: 5270 | AH38: 0.6 | AI38: 3.0770143e+12
A39: INE200A01026 | B39: Canara Rob Emerg Equities Fund-Reg(G) | C39: GE Vernova T&D India Ltd | D39: 0.0061592627 | E39: =_xlfn.IFNA(D39*VLOOKUP($B39,$AK$1:$AM$34,3,FALSE),0) -> 0.00051327189 | F39: Industrials | G39: =_xlfn.IFNA(D39*VLOOKUP($B39,$AK$1:$AM$34,3,FALSE),0) -> 0.00051327189 | M39: INE860A01027 | N39: Edelweiss Balanced Advantage Fund-Reg(G) | O39: HCL Technologies Ltd | P39: 0.011277924 | Q39: =P39*VLOOKUP(N39,'Selector Sheet '!$B$13:$D$43,2,FALSE) -> 0 | R39: Information Technology | S39: =P39*VLOOKUP(N39,'Selector Sheet '!$B$13:$D$43,2,FALSE) -> 0 | X39: INE200A01026 | Z39: INE200A01026 | AB39: INE200A01026 | AC39: GE Vernova T&D India Ltd | AD39: Industrials | AE39: 120.5745 | AF39: 40.339517 | AG39: 6083.3 | AH39: 23.76 | AI39: 7.3353492e+11
A40: INE474Q01031 | B40: Canara Rob Emerg Equities Fund-Reg(G) | C40: Global Health Ltd/India | D40: 0.011210673 | E40: =_xlfn.IFNA(D40*VLOOKUP($B40,$AK$1:$AM$34,3,FALSE),0) -> 0.00093422275 | F40: Health Care | G40: =_xlfn.IFNA(D40*VLOOKUP($B40,$AK$1:$AM$34,3,FALSE),0) -> 0.00093422275 | M40: INE756I01012 | N40: Edelweiss Balanced Advantage Fund-Reg(G) | O40: HDB Financial Services Ltd | P40: 0.0011965643 | Q40: =P40*VLOOKUP(N40,'Selector Sheet '!$B$13:$D$43,2,FALSE) -> 0 | R40: Financials | S40: =P40*VLOOKUP(N40,'Selector Sheet '!$B$13:$D$43,2,FALSE) -> 0 | X40: INE474Q01031 | Z40: INE474Q01031 | AB40: INE474Q01031 | AC40: Global Health Ltd/India | AD40: Health Care | AE40: 68.812877 | AF40: #N/A N/A | AG40: 4814.37 | AH40: 17.92 | AI40: 367554762576
A41: INE756I01012 | B41: Canara Rob Emerg Equities Fund-Reg(G) | C41: HDB Financial Services Ltd | D41: 0.0013211232 | E41: =_xlfn.IFNA(D41*VLOOKUP($B41,$AK$1:$AM$34,3,FALSE),0) -> 0.0001100936 | F41: Financials | G41: =_xlfn.IFNA(D41*VLOOKUP($B41,$AK$1:$AM$34,3,FALSE),0) -> 0.0001100936 | M41: INE040A01034 | N41: Edelweiss Balanced Advantage Fund-Reg(G) | O41: HDFC Bank Ltd | P41: 0.054265057 | Q41: =P41*VLOOKUP(N41,'Selector Sheet '!$B$13:$D$43,2,FALSE) -> 0 | R41: Financials | S41: =P41*VLOOKUP(N41,'Selector Sheet '!$B$13:$D$43,2,FALSE) -> 0 | X41: INE756I01012 | Z41: INE756I01012 | AB41: INE756I01012 | AC41: HDB Financial Services Ltd | AD41: Financials | AE41: 28.15511 | AF41: 14.720832 | AG41: 21759.2 | AH41: 27.4 | AI41: 6.3996925e+11
A42: INE127D01025 | B42: Canara Rob Emerg Equities Fund-Reg(G) | C42: HDFC Asset Management Co Ltd | D42: 0.0082116562 | E42: =_xlfn.IFNA(D42*VLOOKUP($B42,$AK$1:$AM$34,3,FALSE),0) -> 0.00068430468 | F42: Financials | G42: =_xlfn.IFNA(D42*VLOOKUP($B42,$AK$1:$AM$34,3,FALSE),0) -> 0.00068430468 | M42: INE795G01014 | N42: Edelweiss Balanced Advantage Fund-Reg(G) | O42: HDFC Life Insurance Co Ltd | P42: 0.0095655647 | Q42: =P42*VLOOKUP(N42,'Selector Sheet '!$B$13:$D$43,2,FALSE) -> 0 | R42: Financials | S42: =P42*VLOOKUP(N42,'Selector Sheet '!$B$13:$D$43,2,FALSE) -> 0 | X42: INE127D01025 | Z42: INE127D01025 | AB42: INE127D01025 | AC42: HDFC Asset Management Co Ltd | AD42: Financials | AE42: 49.157694 | AF42: 32.360276 | AG42: 24601.9 | AH42: 115.16 | AI42: 1211106737277
A43: INE040A01034 | B43: Canara Rob Emerg Equities Fund-Reg(G) | C43: HDFC Bank Ltd | D43: 8.7849185e-05 | E43: =_xlfn.IFNA(D43*VLOOKUP($B43,$AK$1:$AM$34,3,FALSE),0) -> 7.3207654e-06 | F43: Financials | G43: =_xlfn.IFNA(D43*VLOOKUP($B43,$AK$1:$AM$34,3,FALSE),0) -> 7.3207654e-06 | M43: INE158A01026 | N43: Edelweiss Balanced Advantage Fund-Reg(G) | O43: Hero MotoCorp Ltd | P43: 0.0016988898 | Q43: =P43*VLOOKUP(N43,'Selector Sheet '!$B$13:$D$43,2,FALSE) -> 0 | R43: Consumer Discretionary | S43: =P43*VLOOKUP(N43,'Selector Sheet '!$B$13:$D$43,2,FALSE) -> 0 | X43: INE040A01034 | Z43: INE040A01034 | AB43: INE040A01034 | AC43: HDFC Bank Ltd | AD43: Financials | AE43: 21.849827 | AF43: 13.859084 | AG43: 707922.5 | AH43: 92.81 | AI43: 1.5488408e+13
A44: INE158A01026 | B44: Canara Rob Emerg Equities Fund-Reg(G) | C44: Hero MotoCorp Ltd | D44: 0.0016213118 | E44: =_xlfn.IFNA(D44*VLOOKUP($B44,$AK$1:$AM$34,3,FALSE),0) -> 0.00013510931 | F44: Consumer Discretionary | G44: =_xlfn.IFNA(D44*VLOOKUP($B44,$AK$1:$AM$34,3,FALSE),0) -> 0.00013510931 | M44: INE038A01020 | N44: Edelweiss Balanced Advantage Fund-Reg(G) | O44: Hindalco Industries Ltd | P44: 0.0078742892 | Q44: =P44*VLOOKUP(N44,'Selector Sheet '!$B$13:$D$43,2,FALSE) -> 0 | R44: Materials | S44: =P44*VLOOKUP(N44,'Selector Sheet '!$B$13:$D$43,2,FALSE) -> 0 | X44: INE158A01026 | Z44: INE158A01026 | AB44: INE158A01026 | AC44: Hero MotoCorp Ltd | AD44: Consumer Discretionary | AE44: 23.185285 | AF44: 23.68605 | AG44: 43784.8 | AH44: 218.96 | AI44: 1015674501469
A45: INE267A01025 | B45: Canara Rob Emerg Equities Fund-Reg(G) | C45: Hindustan Zinc Ltd | D45: 0.00076784085 | E45: =_xlfn.IFNA(D45*VLOOKUP($B45,$AK$1:$AM$34,3,FALSE),0) -> 6.3986738e-05 | F45: Materials | G45: =_xlfn.IFNA(D45*VLOOKUP($B45,$AK$1:$AM$34,3,FALSE),0) -> 6.3986738e-05 | M45: INE030A01027 | N45: Edelweiss Balanced Advantage Fund-Reg(G) | O45: Hindustan Unilever Ltd | P45: 0.0071663462 | Q45: =P45*VLOOKUP(N45,'Selector Sheet '!$B$13:$D$43,2,FALSE) -> 0 | R45: Consumer Staples | S45: =P45*VLOOKUP(N45,'Selector Sheet '!$B$13:$D$43,2,FALSE) -> 0 | X45: INE267A01025 | Z45: INE267A01025 | AB45: INE267A01025 | AC45: Hindustan Zinc Ltd | AD45: Materials | AE45: 17.616495 | AF45: #N/A N/A | AG45: 103530 | AH45: 24.5 | AI45: 1805056276800
A46: INE090A01021 | B46: Canara Rob Emerg Equities Fund-Reg(G) | C46: ICICI Bank Ltd | D46: 0.067285207 | E46: =_xlfn.IFNA(D46*VLOOKUP($B46,$AK$1:$AM$34,3,FALSE),0) -> 0.0056071006 | F46: Financials | G46: =_xlfn.IFNA(D46*VLOOKUP($B46,$AK$1:$AM$34,3,FALSE),0) -> 0.0056071006 | M46: INE267A01025 | N46: Edelweiss Balanced Advantage Fund-Reg(G) | O46: Hindustan Zinc Ltd | P46: 0.0022785935 | Q46: =P46*VLOOKUP(N46,'Selector Sheet '!$B$13:$D$43,2,FALSE) -> 0 | R46: Materials | S46: =P46*VLOOKUP(N46,'Selector Sheet '!$B$13:$D$43,2,FALSE) -> 0 | X46: INE090A01021 | Z46: INE090A01021 | AB46: INE090A01021 | AC46: ICICI Bank Ltd | AD46: Financials | AE46: 19.380851 | AF46: 17.562255 | AG46: 510291.96 | AH46: 72.41 | AI46: 1.0346887e+13
A47: INE562A01011 | B47: Canara Rob Emerg Equities Fund-Reg(G) | C47: Indian Bank | D47: 0.0050919181 | E47: =_xlfn.IFNA(D47*VLOOKUP($B47,$AK$1:$AM$34,3,FALSE),0) -> 0.00042432651 | F47: Financials | G47: =_xlfn.IFNA(D47*VLOOKUP($B47,$AK$1:$AM$34,3,FALSE),0) -> 0.00042432651 | M47: INE031A01017 | N47: Edelweiss Balanced Advantage Fund-Reg(G) | O47: Housing & Urban Development Co | P47: 0.0030466614 | Q47: =P47*VLOOKUP(N47,'Selector Sheet '!$B$13:$D$43,2,FALSE) -> 0 | R47: Financials | S47: =P47*VLOOKUP(N47,'Selector Sheet '!$B$13:$D$43,2,FALSE) -> 0 | X47: INE562A01011 | Z47: INE562A01011 | AB47: INE562A01011 | AC47: Indian Bank | AD47: Financials | AE47: 8.0821672 | AF47: 17.093769 | AG47: 112614.7 | AH47: 83.61 | AI47: 9.1021091e+11
A48: INE379A01028 | B48: Canara Rob Emerg Equities Fund-Reg(G) | C48: ITC Hotels Ltd | D48: 0.0070863874 | E48: =_xlfn.IFNA(D48*VLOOKUP($B48,$AK$1:$AM$34,3,FALSE),0) -> 0.00059053228 | F48: Consumer Discretionary | G48: =_xlfn.IFNA(D48*VLOOKUP($B48,$AK$1:$AM$34,3,FALSE),0) -> 0.00059053228 | M48: INE090A01021 | N48: Edelweiss Balanced Advantage Fund-Reg(G) | O48: ICICI Bank Ltd | P48: 0.04877138 | Q48: =P48*VLOOKUP(N48,'Selector Sheet '!$B$13:$D$43,2,FALSE) -> 0 | R48: Financials | S48: =P48*VLOOKUP(N48,'Selector Sheet '!$B$13:$D$43,2,FALSE) -> 0 | X48: INE379A01028 | Z48: INE379A01028 | AB48: INE379A01028 | AC48: ITC Hotels Ltd | AD48: Consumer Discretionary | AE48: 75.49508 | AF48: 11.777168 | AG48: 6345.7 | AH48: 3.05 | AI48: 4.7949009e+11
A49: INE823G01014 | B49: Canara Rob Emerg Equities Fund-Reg(G) | C49: JK Cement Ltd | D49: 0.011934624 | E49: =_xlfn.IFNA(D49*VLOOKUP($B49,$AK$1:$AM$34,3,FALSE),0) -> 0.00099455204 | F49: Materials | G49: =_xlfn.IFNA(D49*VLOOKUP($B49,$AK$1:$AM$34,3,FALSE),0) -> 0.00099455204 | M49: INE562A01011 | N49: Edelweiss Balanced Advantage Fund-Reg(G) | O49: Indian Bank | P49: 0.0045788104 | Q49: =P49*VLOOKUP(N49,'Selector Sheet '!$B$13:$D$43,2,FALSE) -> 0 | R49: Financials | S49: =P49*VLOOKUP(N49,'Selector Sheet '!$B$13:$D$43,2,FALSE) -> 0 | X49: INE823G01014 | Z49: INE823G01014 | AB49: INE823G01014 | AC49: JK Cement Ltd | AD49: Materials | AE49: 64.860014 | AF49: 15.033362 | AG49: 8611.2 | AH49: 111.44 | AI49: 558495590432
A50: INE930H01031 | B50: Canara Rob Emerg Equities Fund-Reg(G) | C50: KPR Mill Ltd | D50: 0.0052229914 | E50: =_xlfn.IFNA(D50*VLOOKUP($B50,$AK$1:$AM$34,3,FALSE),0) -> 0.00043524928 | F50: Consumer Discretionary | G50: =_xlfn.IFNA(D50*VLOOKUP($B50,$AK$1:$AM$34,3,FALSE),0) -> 0.00043524928 | M50: INE022Q01020 | N50: Edelweiss Balanced Advantage Fund-Reg(G) | O50: Indian Energy Exchange Ltd | P50: 0 | Q50: =P50*VLOOKUP(N50,'Selector Sheet '!$B$13:$D$43,2,FALSE) -> 0 | R50: Financials | S50: =P50*VLOOKUP(N50,'Selector Sheet '!$B$13:$D$43,2,FALSE) -> 0 | X50: INE930H01031 | Z50: INE930H01031 | AB50: INE930H01031 | AC50: KPR Mill Ltd | AD50: Consumer Discretionary | AE50: 40.968552 | AF50: 17.416452 | AG50: 8151.1 | AH50: 23.85 | AI50: 333986459400
A51: INE217B01036 | B51: Canara Rob Emerg Equities Fund-Reg(G) | C51: Kajaria Ceramics Ltd | D51: 0.0027655899 | E51: =_xlfn.IFNA(D51*VLOOKUP($B51,$AK$1:$AM$34,3,FALSE),0) -> 0.00023046582 | F51: Industrials | G51: =_xlfn.IFNA(D51*VLOOKUP($B51,$AK$1:$AM$34,3,FALSE),0) -> 0.00023046582 | M51: INE06ST01018 | N51: Edelweiss Balanced Advantage Fund-Reg(G) | O51: Indiqube Spaces Ltd | P51: 0.00087204156 | Q51: =P51*VLOOKUP(N51,'Selector Sheet '!$B$13:$D$43,2,FALSE) -> 0 | R51: Real Estate | S51: =P51*VLOOKUP(N51,'Selector Sheet '!$B$13:$D$43,2,FALSE) -> 0 | X51: INE217B01036 | Z51: INE217B01036 | AB51: INE217B01036 | AC51: Kajaria Ceramics Ltd | AD51: Industrials | AE51: 59.855815 | AF51: 10.981427 | AG51: 2943.5 | AH51: 18.48 | AI51: 204967510001
A52: INE918Z01012 | B52: Canara Rob Emerg Equities Fund-Reg(G) | C52: Kaynes Technology India Ltd | D52: 0.011349421 | E52: =_xlfn.IFNA(D52*VLOOKUP($B52,$AK$1:$AM$34,3,FALSE),0) -> 0.00094578509 | F52: Information Technology | G52: =_xlfn.IFNA(D52*VLOOKUP($B52,$AK$1:$AM$34,3,FALSE),0) -> 0.00094578509 | M52: INE121J01017 | N52: Edelweiss Balanced Advantage Fund-Reg(G) | O52: Indus Towers Ltd | P52: 0.0046908361 | Q52: =P52*VLOOKUP(N52,'Selector Sheet '!$B$13:$D$43,2,FALSE) -> 0 | R52: Communication Services | S52: =P52*VLOOKUP(N52,'Selector Sheet '!$B$13:$D$43,2,FALSE) -> 0 | X52: INE918Z01012 | Z52: INE918Z01012 | AB52: INE918Z01012 | AC52: Kaynes Technology India Ltd | AD52: Information Technology | AE52: 136.27784 | AF52: 11.016512 | AG52: 2934.33 | AH52: 45.788808 | AI52: 417812260320
A53: INE634I01029 | B53: Canara Rob Emerg Equities Fund-Reg(G) | C53: KNR Constructions Ltd | D53: 0.0023087162 | E53: =_xlfn.IFNA(D53*VLOOKUP($B53,$AK$1:$AM$34,3,FALSE),0) -> 0.00019239301 | F53: Industrials | G53: =_xlfn.IFNA(D53*VLOOKUP($B53,$AK$1:$AM$34,3,FALSE),0) -> 0.00019239301 | M53: INE009A01021 | N53: Edelweiss Balanced Advantage Fund-Reg(G) | O53: Infosys Ltd | P53: 0.025007163 | Q53: =P53*VLOOKUP(N53,'Selector Sheet '!$B$13:$D$43,2,FALSE) -> 0 | R53: Information Technology | S53: =P53*VLOOKUP(N53,'Selector Sheet '!$B$13:$D$43,2,FALSE) -> 0 | X53: INE634I01029 | Z53: INE634I01029 | AB53: INE634I01029 | AC53: KNR Constructions Ltd | AD53: Industrials | AE53: 5.6426167 | AF53: 24.751915 | AG53: 10018.741 | AH53: 35.62 | AI53: 56525342254
A54: INE04I401011 | B54: Canara Rob Emerg Equities Fund-Reg(G) | C54: KPIT Technologies Ltd | D54: 0.034889065 | E54: =_xlfn.IFNA(D54*VLOOKUP($B54,$AK$1:$AM$34,3,FALSE),0) -> 0.0029074221 | F54: Information Technology | G54: =_xlfn.IFNA(D54*VLOOKUP($B54,$AK$1:$AM$34,3,FALSE),0) -> 0.0029074221 | M54: INE646L01027 | N54: Edelweiss Balanced Advantage Fund-Reg(G) | O54: InterGlobe Aviation Ltd | P54: 0.0066596273 | Q54: =P54*VLOOKUP(N54,'Selector Sheet '!$B$13:$D$43,2,FALSE) -> 0 | R54: Industrials | S54: =P54*VLOOKUP(N54,'Selector Sheet '!$B$13:$D$43,2,FALSE) -> 0 | X54: INE04I401011 | Z54: INE04I401011 | AB54: INE04I401011 | AC54: KPIT Technologies Ltd | AD54: Information Technology | AE54: 39.605561 | AF54: 33.198788 | AG54: 8396 | AH54: 30.93 | AI54: 335826164800
A55: INE473A01011 | B55: Canara Rob Emerg Equities Fund-Reg(G) | C55: Linde India Ltd | D55: 0.0012169809 | E55: =_xlfn.IFNA(D55*VLOOKUP($B55,$AK$1:$AM$34,3,FALSE),0) -> 0.00010141507 | F55: Materials | G55: =_xlfn.IFNA(D55*VLOOKUP($B55,$AK$1:$AM$34,3,FALSE),0) -> 0.00010141507 | M55: INE154A01025 | N55: Edelweiss Balanced Advantage Fund-Reg(G) | O55: ITC Ltd | P55: 0.016835517 | Q55: =P55*VLOOKUP(N55,'Selector Sheet '!$B$13:$D$43,2,FALSE) -> 0 | R55: Consumer Staples | S55: =P55*VLOOKUP(N55,'Selector Sheet '!$B$13:$D$43,2,FALSE) -> 0 | X55: INE473A01011 | Z55: INE473A01011 | AB55: INE473A01011 | AC55: Linde India Ltd | AD55: Materials | AE55: 117.31671 | AF55: 12.481381 | AG55: 4548.45 | AH55: 53.33 | AI55: 5.3358074e+11
A56: INE214T01019 | B56: Canara Rob Emerg Equities Fund-Reg(G) | C56: LTIMindtree Ltd | D56: 0.0019010468 | E56: =_xlfn.IFNA(D56*VLOOKUP($B56,$AK$1:$AM$34,3,FALSE),0) -> 0.00015842057 | F56: Information Technology | G56: =_xlfn.IFNA(D56*VLOOKUP($B56,$AK$1:$AM$34,3,FALSE),0) -> 0.00015842057 | M56: INE121E01018 | N56: Edelweiss Balanced Advantage Fund-Reg(G) | O56: JSW Energy Ltd | P56: 0.0078515558 | Q56: =P56*VLOOKUP(N56,'Selector Sheet '!$B$13:$D$43,2,FALSE) -> 0 | R56: Utilities | S56: =P56*VLOOKUP(N56,'Selector Sheet '!$B$13:$D$43,2,FALSE) -> 0 | X56: INE214T01019 | Z56: INE214T01019 | AB56: INE214T01019 | AC56: LTIMindtree Ltd | AD56: Information Technology | AE56: 32.032065 | AF56: 22.13342 | AG56: 45987 | AH56: 155.36149 | AI56: 1513355798813
A57: INE101A01026 | B57: Canara Rob Emerg Equities Fund-Reg(G) | C57: Mahindra & Mahindra Ltd | D57: 0.023650475 | E57: =_xlfn.IFNA(D57*VLOOKUP($B57,$AK$1:$AM$34,3,FALSE),0) -> 0.0019708729 | F57: Consumer Discretionary | G57: =_xlfn.IFNA(D57*VLOOKUP($B57,$AK$1:$AM$34,3,FALSE),0) -> 0.0019708729 | M57: INE980O01024 | N57: Edelweiss Balanced Advantage Fund-Reg(G) | O57: Jyoti CNC Automation Ltd | P57: 0.0063748099 | Q57: =P57*VLOOKUP(N57,'Selector Sheet '!$B$13:$D$43,2,FALSE) -> 0 | R57: Industrials | S57: =P57*VLOOKUP(N57,'Selector Sheet '!$B$13:$D$43,2,FALSE) -> 0 | X57: INE101A01026 | Z57: INE101A01026 | AB57: INE101A01026 | AC57: Mahindra & Mahindra Ltd | AD57: Consumer Discretionary | AE57: 29.408161 | AF57: 18.053694 | AG57: 129291 | AH57: 115.91 | AI57: 4.2388167e+12
... A64: INE048G01026 | B64: Canara Rob Emerg Equities Fund-Reg(G) | C64: Navin Fluorine International L | D64: 0.00089204534 | E64: =_xlfn.IFNA(D64*VLOOKUP($B64,$AK$1:$AM$34,3,FALSE),0) -> 7.4337112e-05 | F64: Materials | G64: =_xlfn.IFNA(D64*VLOOKUP($B64,$AK$1:$AM$34,3,FALSE),0) -> 7.4337112e-05 | M64: INE196A01026 | N64: Edelweiss Balanced Advantage Fund-Reg(G) | O64: Marico Ltd | P64: 0.007231529 | Q64: =P64*VLOOKUP(N64,'Selector Sheet '!$B$13:$D$43,2,FALSE) -> 0 | R64: Consumer Staples | S64: =P64*VLOOKUP(N64,'Selector Sheet '!$B$13:$D$43,2,FALSE) -> 0 | X64: INE048G01026 | Z64: INE048G01026 | AB64: INE048G01026 | AC64: Navin Fluorine International L | AD64: Materials | AE64: 88.024055 | AF64: 11.52269 | AG64: 2885.8 | AH64: 58.2 | AI64: 262260811737
A65: INE239A01024 | B65: Canara Rob Emerg Equities Fund-Reg(G) | C65: Nestle India Ltd | D65: 0.00096738602 | E65: =_xlfn.IFNA(D65*VLOOKUP($B65,$AK$1:$AM$34,3,FALSE),0) -> 8.0615501e-05 | F65: Consumer Staples | G65: =_xlfn.IFNA(D65*VLOOKUP($B65,$AK$1:$AM$34,3,FALSE),0) -> 8.0615501e-05 | M65: INE585B01010 | N65: Edelweiss Balanced Advantage Fund-Reg(G) | O65: Maruti Suzuki India Ltd | P65: 0.013682341 | Q65: =P65*VLOOKUP(N65,'Selector Sheet '!$B$13:$D$43,2,FALSE) -> 0 | R65: Consumer Discretionary | S65: =P65*VLOOKUP(N65,'Selector Sheet '!$B$13:$D$43,2,FALSE) -> 0 | X65: INE239A01024 | Z65: INE239A01024 | AB65: INE239A01024 | AC65: Nestle India Ltd | AD65: Consumer Staples | AE65: 68.969044 | AF65: #N/A N/A | AG65: 32075.9 | AH65: 16.635 | AI65: 2212355019336
A66: INE733E01010 | B66: Canara Rob Emerg Equities Fund-Reg(G) | C66: NTPC Ltd | D66: 0.0022434575 | E66: =_xlfn.IFNA(D66*VLOOKUP($B66,$AK$1:$AM$34,3,FALSE),0) -> 0.00018695479 | F66: Utilities | G66: =_xlfn.IFNA(D66*VLOOKUP($B66,$AK$1:$AM$34,3,FALSE),0) -> 0.00018695479 | M66: INE027H01010 | N66: Edelweiss Balanced Advantage Fund-Reg(G) | O66: Max Healthcare Institute Ltd | P66: 0.0042119789 | Q66: =P66*VLOOKUP(N66,'Selector Sheet '!$B$13:$D$43,2,FALSE) -> 0 | R66: Health Care | S66: =P66*VLOOKUP(N66,'Selector Sheet '!$B$13:$D$43,2,FALSE) -> 0 | X66: INE733E01010 | Z66: INE733E01010 | AB66: INE733E01010 | AC66: NTPC Ltd | AD66: Utilities | AE66: 14.090159 | AF66: 13.586885 | AG66: 234224.6 | AH66: 24.155158 | AI66: 3.3002603e+12
A67: INE093I01010 | B67: Canara Rob Emerg Equities Fund-Reg(G) | C67: Oberoi Realty Ltd | D67: 0.010472452 | E67: =_xlfn.IFNA(D67*VLOOKUP($B67,$AK$1:$AM$34,3,FALSE),0) -> 0.00087270431 | F67: Real Estate | G67: =_xlfn.IFNA(D67*VLOOKUP($B67,$AK$1:$AM$34,3,FALSE),0) -> 0.00087270431 | M67: INE842C01021 | N67: Edelweiss Balanced Advantage Fund-Reg(G) | O67: Minda Corp Ltd | P67: 0.0063977545 | Q67: =P67*VLOOKUP(N67,'Selector Sheet '!$B$13:$D$43,2,FALSE) -> 0 | R67: Consumer Discretionary | S67: =P67*VLOOKUP(N67,'Selector Sheet '!$B$13:$D$43,2,FALSE) -> 0 | X67: INE093I01010 | Z67: INE093I01010 | AB67: INE093I01010 | AC67: Oberoi Realty Ltd | AD67: Real Estate | AE67: 26.959646 | AF67: 15.063066 | AG67: 22255.137 | AH67: 61.21 | AI67: 6.0001641e+11
A68: INE274J01014 | B68: Canara Rob Emerg Equities Fund-Reg(G) | C68: Oil India Ltd | D68: 0.0026380234 | E68: =_xlfn.IFNA(D68*VLOOKUP($B68,$AK$1:$AM$34,3,FALSE),0) -> 0.00021983529 | F68: Energy | G68: =_xlfn.IFNA(D68*VLOOKUP($B68,$AK$1:$AM$34,3,FALSE),0) -> 0.00021983529 | M68: INE745G01035 | N68: Edelweiss Balanced Advantage Fund-Reg(G) | O68: Multi Commodity Exchange of In | P68: 0.010840086 | Q68: =P68*VLOOKUP(N68,'Selector Sheet '!$B$13:$D$43,2,FALSE) -> 0 | R68: Financials | S68: =P68*VLOOKUP(N68,'Selector Sheet '!$B$13:$D$43,2,FALSE) -> 0 | X68: INE274J01014 | Z68: INE274J01014 | AB68: INE274J01014 | AC68: Oil India Ltd | AD68: Energy | AE68: 9.9826173 | AF68: 13.354703 | AG68: 65509.3 | AH68: 40.27 | AI68: 653896331982
A69: INE417T01026 | B69: Canara Rob Emerg Equities Fund-Reg(G) | C69: PB Fintech Ltd | D69: 0.0056802134 | E69: =_xlfn.IFNA(D69*VLOOKUP($B69,$AK$1:$AM$34,3,FALSE),0) -> 0.00047335111 | F69: Financials | G69: =_xlfn.IFNA(D69*VLOOKUP($B69,$AK$1:$AM$34,3,FALSE),0) -> 0.00047335111 | M69: INE414G01012 | N69: Edelweiss Balanced Advantage Fund-Reg(G) | O69: Muthoot Finance Ltd | P69: 0.00612661 | Q69: =P69*VLOOKUP(N69,'Selector Sheet '!$B$13:$D$43,2,FALSE) -> 0 | R69: Financials | S69: =P69*VLOOKUP(N69,'Selector Sheet '!$B$13:$D$43,2,FALSE) -> 0 | X69: INE417T01026 | Z69: INE417T01026 | AB69: INE417T01026 | AC69: PB Fintech Ltd | AD69: Financials | AE69: 245.04505 | AF69: 5.7384557 | AG69: 3530.1 | AH69: 7.77 | AI69: 874425864928
A70: INE262H01021 | B70: Canara Rob Emerg Equities Fund-Reg(G) | C70: Persistent Systems Ltd | D70: 0.0059404733 | E70: =_xlfn.IFNA(D70*VLOOKUP($B70,$AK$1:$AM$34,3,FALSE),0) -> 0.00049503944 | F70: Information Technology | G70: =_xlfn.IFNA(D70*VLOOKUP($B70,$AK$1:$AM$34,3,FALSE),0) -> 0.00049503944 | M70: INE733E01010 | N70: Edelweiss Balanced Advantage Fund-Reg(G) | O70: NTPC Ltd | P70: 0.01765601 | Q70: =P70*VLOOKUP(N70,'Selector Sheet '!$B$13:$D$43,2,FALSE) -> 0 | R70: Utilities | S70: =P70*VLOOKUP(N70,'Selector Sheet '!$B$13:$D$43,2,FALSE) -> 0 | X70: INE262H01021 | Z70: INE262H01021 | AB70: INE262H01021 | AC70: Persistent Systems Ltd | AD70: Information Technology | AE70: 53.536635 | AF70: 24.718665 | AG70: 14001.61 | AH70: 91.22 | AI70: 825088200000
A71: INE603J01030 | B71: Canara Rob Emerg Equities Fund-Reg(G) | C71: PI Industries Ltd | D71: 0.015503988 | E71: =_xlfn.IFNA(D71*VLOOKUP($B71,$AK$1:$AM$34,3,FALSE),0) -> 0.001291999 | F71: Materials | G71: =_xlfn.IFNA(D71*VLOOKUP($B71,$AK$1:$AM$34,3,FALSE),0) -> 0.001291999 | M71: INE761H01022 | N71: Edelweiss Balanced Advantage Fund-Reg(G) | O71: Page Industries Ltd | P71: 0 | Q71: =P71*VLOOKUP(N71,'Selector Sheet '!$B$13:$D$43,2,FALSE) -> 0 | R71: Consumer Discretionary | S71: =P71*VLOOKUP(N71,'Selector Sheet '!$B$13:$D$43,2,FALSE) -> 0 | X71: INE603J01030 | Z71: INE603J01030 | AB71: INE603J01030 | AC71: PI Industries Ltd | AD71: Materials | AE71: 34.009108 | AF71: 17.579416 | AG71: 16602 | AH71: 109.22368 | AI71: 5.6357212e+11
A72: INE318A01026 | B72: Canara Rob Emerg Equities Fund-Reg(G) | C72: Pidilite Industries Ltd | D72: 0.0067262472 | E72: =_xlfn.IFNA(D72*VLOOKUP($B72,$AK$1:$AM$34,3,FALSE),0) -> 0.0005605206 | F72: Materials | G72: =_xlfn.IFNA(D72*VLOOKUP($B72,$AK$1:$AM$34,3,FALSE),0) -> 0.0005605206 | M72: INE417T01026 | N72: Edelweiss Balanced Advantage Fund-Reg(G) | O72: PB Fintech Ltd | P72: 0.0031811626 | Q72: =P72*VLOOKUP(N72,'Selector Sheet '!$B$13:$D$43,2,FALSE) -> 0 | R72: Financials | S72: =P72*VLOOKUP(N72,'Selector Sheet '!$B$13:$D$43,2,FALSE) -> 0 | X72: INE318A01026 | Z72: INE318A01026 | AB72: INE318A01026 | AC72: Pidilite Industries Ltd | AD72: Materials | AE72: 75.712888 | AF72: 22.86404 | AG72: 20762.4 | AH72: 40.82 | AI72: 1572092674101
A73: INE074A01025 | B73: Canara Rob Emerg Equities Fund-Reg(G) | C73: Praj Industries Ltd | D73: 0.014097281 | E73: =_xlfn.IFNA(D73*VLOOKUP($B73,$AK$1:$AM$34,3,FALSE),0) -> 0.0011747735 | F73: Industrials | G73: =_xlfn.IFNA(D73*VLOOKUP($B73,$AK$1:$AM$34,3,FALSE),0) -> 0.0011747735 | M73: INE262H01021 | N73: Edelweiss Balanced Advantage Fund-Reg(G) | O73: Persistent Systems Ltd | P73: 0.0060409295 | Q73: =P73*VLOOKUP(N73,'Selector Sheet '!$B$13:$D$43,2,FALSE) -> 0 | R73: Information Technology | S73: =P73*VLOOKUP(N73,'Selector Sheet '!$B$13:$D$43,2,FALSE) -> 0 | X73: INE074A01025 | Z73: INE074A01025 | AB73: INE074A01025 | AC73: Praj Industries Ltd | AD73: Industrials | AE73: 34.345087 | AF73: 16.482723 | AG73: 2189.101 | AH73: 11.91 | AI73: 7.5188744e+10
A74: INE0BS701011 | B74: Canara Rob Emerg Equities Fund-Reg(G) | C74: Premier Energies Ltd | D74: 0.0016151201 | E74: =_xlfn.IFNA(D74*VLOOKUP($B74,$AK$1:$AM$34,3,FALSE),0) -> 0.00013459334 | F74: Information Technology | G74: =_xlfn.IFNA(D74*VLOOKUP($B74,$AK$1:$AM$34,3,FALSE),0) -> 0.00013459334 | M74: INE457L01029 | N74: Edelweiss Balanced Advantage Fund-Reg(G) | O74: PG Electroplast Ltd | P74: 0.0023518441 | Q74: =P74*VLOOKUP(N74,'Selector Sheet '!$B$13:$D$43,2,FALSE) -> 0 | R74: Information Technology | S74: =P74*VLOOKUP(N74,'Selector Sheet '!$B$13:$D$43,2,FALSE) -> 0 | X74: INE0BS701011 | Z74: INE0BS701011 | AB74: INE0BS701011 | AC74: Premier Energies Ltd | AD74: Information Technology | AE74: 47.751756 | AF74: 43.732622 | AG74: 9371.32 | AH74: 21.35 | AI74: 459564468176
A75: INE944F01028 | B75: Canara Rob Emerg Equities Fund-Reg(G) | C75: Radico Khaitan Ltd | D75: 0.0037689085 | E75: =_xlfn.IFNA(D75*VLOOKUP($B75,$AK$1:$AM$34,3,FALSE),0) -> 0.00031407571 | F75: Consumer Staples | G75: =_xlfn.IFNA(D75*VLOOKUP($B75,$AK$1:$AM$34,3,FALSE),0) -> 0.00031407571 | M75: INE318A01026 | N75: Edelweiss Balanced Advantage Fund-Reg(G) | O75: Pidilite Industries Ltd | P75: 0.0053206269 | Q75: =P75*VLOOKUP(N75,'Selector Sheet '!$B$13:$D$43,2,FALSE) -> 0 | R75: Materials | S75: =P75*VLOOKUP(N75,'Selector Sheet '!$B$13:$D$43,2,FALSE) -> 0 | X75: INE944F01028 | Z75: INE944F01028 | AB75: INE944F01028 | AC75: Radico Khaitan Ltd | AD75: Consumer Staples | AE75: 110.73143 | AF75: 13.309816 | AG75: 3456.113 | AH75: 25.84 | AI75: 3.8303513e+11
A76: INE775A01035 | B76: Canara Rob Emerg Equities Fund-Reg(G) | C76: Samvardhana Motherson Internat | D76: 0.002552045 | E76: =_xlfn.IFNA(D76*VLOOKUP($B76,$AK$1:$AM$34,3,FALSE),0) -> 0.00021267042 | F76: Consumer Discretionary | G76: =_xlfn.IFNA(D76*VLOOKUP($B76,$AK$1:$AM$34,3,FALSE),0) -> 0.00021267042 | M76: INE134E01011 | N76: Edelweiss Balanced Advantage Fund-Reg(G) | O76: Power Finance Corp Ltd | P76: 0.0070980676 | Q76: =P76*VLOOKUP(N76,'Selector Sheet '!$B$13:$D$43,2,FALSE) -> 0 | R76: Financials | S76: =P76*VLOOKUP(N76,'Selector Sheet '!$B$13:$D$43,2,FALSE) -> 0 | X76: INE775A01035 | Z76: INE775A01035 | AB76: INE775A01035 | AC76: Samvardhana Motherson Internat | AD76: Consumer Discretionary | AE76: 25.852713 | AF76: 12.461661 | AG76: 38030 | AH76: 3.6452653 | AI76: 9.9461625e+11
A77: INE513A01022 | B77: Canara Rob Emerg Equities Fund-Reg(G) | C77: Schaeffler India Ltd | D77: 0.0043708824 | E77: =_xlfn.IFNA(D77*VLOOKUP($B77,$AK$1:$AM$34,3,FALSE),0) -> 0.0003642402 | F77: Industrials | G77: =_xlfn.IFNA(D77*VLOOKUP($B77,$AK$1:$AM$34,3,FALSE),0) -> 0.0003642402 | M77: INE752E01010 | N77: Edelweiss Balanced Advantage Fund-Reg(G) | O77: Power Grid Corp of India Ltd | P77: 0.003683277 | Q77: =P77*VLOOKUP(N77,'Selector Sheet '!$B$13:$D$43,2,FALSE) -> 0 | R77: Utilities | S77: =P77*VLOOKUP(N77,'Selector Sheet '!$B$13:$D$43,2,FALSE) -> 0 | X77: INE513A01022 | Z77: INE513A01022 | AB77: INE513A01022 | AC77: Schaeffler India Ltd | AD77: Industrials | AE77: 65.013045 | AF77: 18.51835 | AG77: 9388.6 | AH77: 60.066408 | AI77: 610381461717
A78: INE070A01015 | B78: Canara Rob Emerg Equities Fund-Reg(G) | C78: Shree Cement Ltd | D78: 0.0005751879 | E78: =_xlfn.IFNA(D78*VLOOKUP($B78,$AK$1:$AM$34,3,FALSE),0) -> 4.7932325e-05 | F78: Materials | G78: =_xlfn.IFNA(D78*VLOOKUP($B78,$AK$1:$AM$34,3,FALSE),0) -> 4.7932325e-05 | M78: INE0BS701011 | N78: Edelweiss Balanced Advantage Fund-Reg(G) | O78: Premier Energies Ltd | P78: 0.011658999 | Q78: =P78*VLOOKUP(N78,'Selector Sheet '!$B$13:$D$43,2,FALSE) -> 0 | R78: Information Technology | S78: =P78*VLOOKUP(N78,'Selector Sheet '!$B$13:$D$43,2,FALSE) -> 0 | X78: INE070A01015 | Z78: INE070A01015 | AB78: INE070A01015 | AC78: Shree Cement Ltd | AD78: Materials | AE78: 101.9185 | AF78: 5.3160615 | AG78: 11227.7 | AH78: 311.18 | AI78: 1144300922820
A79: INE1NPP01017 | B79: Canara Rob Emerg Equities Fund-Reg(G) | C79: Siemens Energy India Ltd | D79: 0.0017941844 | E79: =_xlfn.IFNA(D79*VLOOKUP($B79,$AK$1:$AM$34,3,FALSE),0) -> 0.00014951536 | F79: Industrials | G79: =_xlfn.IFNA(D79*VLOOKUP($B79,$AK$1:$AM$34,3,FALSE),0) -> 0.00014951536 | M79: INE160A01022 | N79: Edelweiss Balanced Advantage Fund-Reg(G) | O79: Punjab National Bank | P79: 0.0034024544 | Q79: =P79*VLOOKUP(N79,'Selector Sheet '!$B$13:$D$43,2,FALSE) -> 0 | R79: Financials | S79: =P79*VLOOKUP(N79,'Selector Sheet '!$B$13:$D$43,2,FALSE) -> 0 | X79: INE1NPP01017 | Z79: INE1NPP01017 | AB79: INE1NPP01017 | AC79: Siemens Energy India Ltd | AD79: Industrials | AE79: #N/A N/A | AF79: #N/A N/A | AG79: #N/A N/A | AH79: #N/A N/A | AI79: 1146494353797
A80: INE003A01024 | B80: Canara Rob Emerg Equities Fund-Reg(G) | C80: Siemens Ltd | D80: 0.0016808681 | E80: =_xlfn.IFNA(D80*VLOOKUP($B80,$AK$1:$AM$34,3,FALSE),0) -> 0.00014007234 | F80: Industrials | G80: =_xlfn.IFNA(D80*VLOOKUP($B80,$AK$1:$AM$34,3,FALSE),0) -> 0.00014007234 | M80: INE020B01018 | N80: Edelweiss Balanced Advantage Fund-Reg(G) | O80: REC Ltd | P80: 0.0046427268 | Q80: =P80*VLOOKUP(N80,'Selector Sheet '!$B$13:$D$43,2,FALSE) -> 0 | R80: Financials | S80: =P80*VLOOKUP(N80,'Selector Sheet '!$B$13:$D$43,2,FALSE) -> 0 | X80: INE003A01024 | Z80: INE003A01024 | AB80: INE003A01024 | AC80: Siemens Ltd | AD80: Industrials | AE80: 41.454731 | AF80: 19.101527 | AG80: 27166 | AH80: 76.283213 | AI80: 1.1261599e+12
A81: INE343H01029 | B81: Canara Rob Emerg Equities Fund-Reg(G) | C81: Solar Industries India Ltd | D81: 0.0028768788 | E81: =_xlfn.IFNA(D81*VLOOKUP($B81,$AK$1:$AM$34,3,FALSE),0) -> 0.0002397399 | F81: Materials | G81: =_xlfn.IFNA(D81*VLOOKUP($B81,$AK$1:$AM$34,3,FALSE),0) -> 0.0002397399 | M81: INE002A01018 | N81: Edelweiss Balanced Advantage Fund-Reg(G) | O81: Reliance Industries Ltd | P81: 0.046558517 | Q81: =P81*VLOOKUP(N81,'Selector Sheet '!$B$13:$D$43,2,FALSE) -> 0 | R81: Energy | S81: =P81*VLOOKUP(N81,'Selector Sheet '!$B$13:$D$43,2,FALSE) -> 0 | X81: INE343H01029 | Z81: INE343H01029 | AB81: INE343H01029 | AC81: Solar Industries India Ltd | AD81: Materials | AE81: 113.36887 | AF81: 31.446943 | AG81: 12094.4 | AH81: 133.65 | AI81: 1.3710827e+12
A82: INE073K01018 | B82: Canara Rob Emerg Equities Fund-Reg(G) | C82: Sona Blw Precision Forgings Lt | D82: 0.010512639 | E82: =_xlfn.IFNA(D82*VLOOKUP($B82,$AK$1:$AM$34,3,FALSE),0) -> 0.00087605322 | F82: Consumer Discretionary | G82: =_xlfn.IFNA(D82*VLOOKUP($B82,$AK$1:$AM$34,3,FALSE),0) -> 0.00087605322 | M82: INE0W2G01015 | N82: Edelweiss Balanced Advantage Fund-Reg(G) | O82: Sagility India Ltd | P82: 0.0018756996 | Q82: =P82*VLOOKUP(N82,'Selector Sheet '!$B$13:$D$43,2,FALSE) -> 0 | R82: Industrials | S82: =P82*VLOOKUP(N82,'Selector Sheet '!$B$13:$D$43,2,FALSE) -> 0 | X82: INE073K01018 | Z82: INE073K01018 | AB82: INE073K01018 | AC82: Sona Blw Precision Forgings Lt | AD82: Consumer Discretionary | AE82: 45.29738 | AF82: 14.762573 | AG82: 6012.13 | AH82: 9.92 | AI82: 2.7937032e+11
A83: INE647A01010 | B83: Canara Rob Emerg Equities Fund-Reg(G) | C83: SRF Ltd | D83: 0 | E83: =_xlfn.IFNA(D83*VLOOKUP($B83,$AK$1:$AM$34,3,FALSE),0) -> 0 | F83: Materials | G83: =_xlfn.IFNA(D83*VLOOKUP($B83,$AK$1:$AM$34,3,FALSE),0) -> 0 | M83: INE513A01022 | N83: Edelweiss Balanced Advantage Fund-Reg(G) | O83: Schaeffler India Ltd | P83: 0.0037919099 | Q83: =P83*VLOOKUP(N83,'Selector Sheet '!$B$13:$D$43,2,FALSE) -> 0 | R83: Industrials | S83: =P83*VLOOKUP(N83,'Selector Sheet '!$B$13:$D$43,2,FALSE) -> 0 | X83: INE647A01010 | Z83: INE647A01010 | AB83: INE647A01010 | AC83: SRF Ltd | AD83: Materials | AE83: 68.097155 | AF83: 10.377669 | AG83: 12507.8 | AH83: 42.2 | AI83: 8.5183602e+11
A84: INE062A01020 | B84: Canara Rob Emerg Equities Fund-Reg(G) | C84: State Bank of India | D84: 0.0075124203 | E84: =_xlfn.IFNA(D84*VLOOKUP($B84,$AK$1:$AM$34,3,FALSE),0) -> 0.00062603503 | F84: Financials | G84: =_xlfn.IFNA(D84*VLOOKUP($B84,$AK$1:$AM$34,3,FALSE),0) -> 0.00062603503 | M84: INE002L01015 | N84: Edelweiss Balanced Advantage Fund-Reg(G) | O84: SJVN Ltd | P84: 0.00060966844 | Q84: =P84*VLOOKUP(N84,'Selector Sheet '!$B$13:$D$43,2,FALSE) -> 0 | R84: Utilities | S84: =P84*VLOOKUP(N84,'Selector Sheet '!$B$13:$D$43,2,FALSE) -> 0 | X84: INE062A01020 | Z84: INE062A01020 | AB84: INE062A01020 | AC84: State Bank of India | AD84: Financials | AE84: 9.3393999 | AF84: 16.557624 | AG84: 775613.37 | AH84: 86.91 | AI84: 7.6734124e+12
A85: INE044A01036 | B85: Canara Rob Emerg Equities Fund-Reg(G) | C85: Sun Pharmaceutical Industries | D85: 0.0076763068 | E85: =_xlfn.IFNA(D85*VLOOKUP($B85,$AK$1:$AM$34,3,FALSE),0) -> 0.00063969224 | F85: Health Care | G85: =_xlfn.IFNA(D85*VLOOKUP($B85,$AK$1:$AM$34,3,FALSE),0) -> 0.00063969224 | M85: INE062A01020 | N85: Edelweiss Balanced Advantage Fund-Reg(G) | O85: State Bank of India | P85: 0.022778094 | Q85: =P85*VLOOKUP(N85,'Selector Sheet '!$B$13:$D$43,2,FALSE) -> 0 | R85: Financials | S85: =P85*VLOOKUP(N85,'Selector Sheet '!$B$13:$D$43,2,FALSE) -> 0 | X85: INE044A01036 | Z85: INE044A01036 | AB85: INE044A01036 | AC85: Sun Pharmaceutical Industries | AD85: Health Care | AE85: 35.877193 | AF85: 16.085747 | AG85: 109290.4 | AH85: 45.6 | AI85: 3925216255840
A86: INE040H01021 | B86: Canara Rob Emerg Equities Fund-Reg(G) | C86: Suzlon Energy Ltd | D86: 0.0089626403 | E86: =_xlfn.IFNA(D86*VLOOKUP($B86,$AK$1:$AM$34,3,FALSE),0) -> 0.00074688669 | F86: Industrials | G86: =_xlfn.IFNA(D86*VLOOKUP($B86,$AK$1:$AM$34,3,FALSE),0) -> 0.00074688669 | M86: INE044A01036 | N86: Edelweiss Balanced Advantage Fund-Reg(G) | O86: Sun Pharmaceutical Industries | P86: 0.017337436 | Q86: =P86*VLOOKUP(N86,'Selector Sheet '!$B$13:$D$43,2,FALSE) -> 0 | R86: Health Care | S86: =P86*VLOOKUP(N86,'Selector Sheet '!$B$13:$D$43,2,FALSE) -> 0 | X86: INE040H01021 | Z86: INE040H01021 | AB86: INE040H01021 | AC86: Suzlon Energy Ltd | AD86: Industrials | AE86: 39.611842 | AF86: 41.325031 | AG86: 20716.3 | AH86: 1.52 | AI86: 8.2499023e+11
A87: INE00H001014 | B87: Canara Rob Emerg Equities Fund-Reg(G) | C87: Swiggy Ltd | D87: 0.0034179344 | E87: =_xlfn.IFNA(D87*VLOOKUP($B87,$AK$1:$AM$34,3,FALSE),0) -> 0.00028482787 | F87: Consumer Discretionary | G87: =_xlfn.IFNA(D87*VLOOKUP($B87,$AK$1:$AM$34,3,FALSE),0) -> 0.00028482787 | M87: INE040H01021 | N87: Edelweiss Balanced Advantage Fund-Reg(G) | O87: Suzlon Energy Ltd | P87: 0.0056784916 | Q87: =P87*VLOOKUP(N87,'Selector Sheet '!$B$13:$D$43,2,FALSE) -> 0 | R87: Industrials | S87: =P87*VLOOKUP(N87,'Selector Sheet '!$B$13:$D$43,2,FALSE) -> 0 | X87: INE00H001014 | Z87: INE00H001014 | AB87: INE00H001014 | AC87: Swiggy Ltd | AD87: Consumer Discretionary | AE87: #N/A N/A | AF87: -34.610049 | AG87: -31167.99 | AH87: -13.72 | AI87: 1.0026954e+12
A88: INE398R01022 | B88: Canara Rob Emerg Equities Fund-Reg(G) | C88: Syngene International Ltd | D88: 0.001876566 | E88: =_xlfn.IFNA(D88*VLOOKUP($B88,$AK$1:$AM$34,3,FALSE),0) -> 0.0001563805 | F88: Health Care | G88: =_xlfn.IFNA(D88*VLOOKUP($B88,$AK$1:$AM$34,3,FALSE),0) -> 0.0001563805 | M88: INE467B01029 | N88: Edelweiss Balanced Advantage Fund-Reg(G) | O88: Tata Consultancy Services Ltd | P88: 0.010174342 | Q88: =P88*VLOOKUP(N88,'Selector Sheet '!$B$13:$D$43,2,FALSE) -> 0 | R88: Information Technology | S88: =P88*VLOOKUP(N88,'Selector Sheet '!$B$13:$D$43,2,FALSE) -> 0 | X88: INE398R01022 | Z88: INE398R01022 | AB88: INE398R01022 | AC88: Syngene International Ltd | AD88: Health Care | AE88: 54.558703 | AF88: 11.045567 | AG88: 4962 | AH88: 12.35 | AI88: 271500581196
A89: INE092A01019 | B89: Canara Rob Emerg Equities Fund-Reg(G) | C89: Tata Chemicals Ltd | D89: 0.00021491074 | E89: =_xlfn.IFNA(D89*VLOOKUP($B89,$AK$1:$AM$34,3,FALSE),0) -> 1.7909229e-05 | F89: Materials | G89: =_xlfn.IFNA(D89*VLOOKUP($B89,$AK$1:$AM$34,3,FALSE),0) -> 1.7909229e-05 | M89: INE155A01022 | N89: Edelweiss Balanced Advantage Fund-Reg(G) | O89: Tata Motors Ltd | P89: 0.0071948725 | Q89: =P89*VLOOKUP(N89,'Selector Sheet '!$B$13:$D$43,2,FALSE) -> 0 | R89: Consumer Discretionary | S89: =P89*VLOOKUP(N89,'Selector Sheet '!$B$13:$D$43,2,FALSE) -> 0 | X89: INE092A01019 | Z89: INE092A01019 | AB89: INE092A01019 | AC89: Tata Chemicals Ltd | AD89: Materials | AE89: 118.99748 | AF89: 1.0722026 | AG89: 2350 | AH89: 9.23 | AI89: 2.4040076e+11
A90: INE467B01029 | B90: Canara Rob Emerg Equities Fund-Reg(G) | C90: Tata Consultancy Services Ltd | D90: 0.0012913274 | E90: =_xlfn.IFNA(D90*VLOOKUP($B90,$AK$1:$AM$34,3,FALSE),0) -> 0.00010761062 | F90: Information Technology | G90: =_xlfn.IFNA(D90*VLOOKUP($B90,$AK$1:$AM$34,3,FALSE),0) -> 0.00010761062 | M90: INE081A01020 | N90: Edelweiss Balanced Advantage Fund-Reg(G) | O90: Tata Steel Ltd | P90: 0.010509622 | Q90: =P90*VLOOKUP(N90,'Selector Sheet '!$B$13:$D$43,2,FALSE) -> 0 | R90: Materials | S90: =P90*VLOOKUP(N90,'Selector Sheet '!$B$13:$D$43,2,FALSE) -> 0 | X90: INE467B01029 | Z90: INE467B01029 | AB90: INE467B01029 | AC90: Tata Consultancy Services Ltd | AD90: Information Technology | AE90: 22.202021 | AF90: 50.698646 | AG90: 485530 | AH90: 134.19 | AI90: 1.0939649e+13
A91: INE192A01025 | B91: Canara Rob Emerg Equities Fund-Reg(G) | C91: Tata Consumer Products Ltd | D91: 0.019750161 | E91: =_xlfn.IFNA(D91*VLOOKUP($B91,$AK$1:$AM$34,3,FALSE),0) -> 0.0016458467 | F91: Consumer Staples | G91: =_xlfn.IFNA(D91*VLOOKUP($B91,$AK$1:$AM$34,3,FALSE),0) -> 0.0016458467 | M91: INE669C01036 | N91: Edelweiss Balanced Advantage Fund-Reg(G) | O91: Tech Mahindra Ltd | P91: 0.0047628749 | Q91: =P91*VLOOKUP(N91,'Selector Sheet '!$B$13:$D$43,2,FALSE) -> 0 | R91: Information Technology | S91: =P91*VLOOKUP(N91,'Selector Sheet '!$B$13:$D$43,2,FALSE) -> 0 | X91: INE192A01025 | Z91: INE192A01025 | AB91: INE192A01025 | AC91: Tata Consumer Products Ltd | AD91: Consumer Staples | AE91: 80.855491 | AF91: #N/A N/A | AG91: 12784.7 | AH91: 12.920364 | AI91: 1069982843875
